Workbook

Sheet Sheet2
A2: 1-السخان | B2: مركزي مع سخان واحد 200L MILANO
B3: مركزي مع 2 سخان 200L كل واحد MILANO
B4: عادي فوق كل حمام ArIston
B5: مركزي مع 2 سخان 200L كل واحد ARISTON
A7: 2-كراسي الحمامات | B7: معلق مع سماكة جدار 25 سنتم
B8: عادي
B9: معلق بدون خزان سماكة جدار 25 سنتم
A11: 3- الشفط | B11: عادي
B12: مركزي مخفي للسطح او للجدران الخارجية
A14: 4-النعلة | B14: شامل النعلات - مخفية
B15: شامل النعلات - مخفية مع ستيل
B16: شامل النعلات - عادية
B17: بدون نعلة ( ستيل فقط)
A19: 5-الألمنيوم | B19: بروفايل فول امبريلا عادي
B20: بروفايل كيرتين وول
A22: 6- خزان المياه | B22: تحت الأرض مع غرفة | C22: =IF(#REF!="تحت الأرض","الغرفة طابوق متروس-كونكريت"," ") -> #REF!
B23: فوق الأرض
A25: 7- خزان استرجاع مياه التكييف | B25: غرفة تحت الأرض فقط
B26: غرفة تحت الارض مع خزان
B27: لا يوجد
A28: 8- مكسرات المغاسل والحمامات | B28: مخفية داخل الجدران
B29: عادية
A31: 9- الصرف | B31: كلين اوت | C31: =IF(#REF!="عادي","اتصالات-كهرباء-صرف","اتصالات-كهرباء") -> #REF!
B32: عادي
A34: 10-حبات السيراميك | B34: كبيرة
B35: متوسطة
B36: صغيرة
A38: 11- سعة خزان المياه | B38: 1000 جالون
B39: 2000 جالون
B40: 1500 جالون
A41: 12- ارتفاعات الأبواب | B41: 220 Cm
B42: 240 Cm
B43: 250 Cm
B44: حتى الجبس
A46: الباب الرئيسي | B46: عادي
B47: فيكس + عادي
B48: دبل هايت
A50: نوع الصبغ: | B50: قرافيو ناسونال
B51: سانديكس جوتن
B52: جوتاشيلد جوتن
A54: الماء الحار والبارد: | B54: كامل حمامات البيت
B55: حمام واحد
B56: 3حمامات
B57: لا
B58: 4حمامات
A59: نقاط اضاءة الواجهة: | B59: نعم
B60: لا
A62: نقط المياه في السور: | B62: عدد 1
B63: عدد 2
B64: عدد 3
B65: عدد 4
A67: نقط الكهرباء في السور | B67: 1
B68: 2
B69: 3
B70: 4
B71: 5
A72: نقطة شحن سيارة كهرب | B72: نعم
B73: لا
A78: الحجر والبورسلان: | B78: 0
B79: 50
B80: 70
B81: 90
A83: نقاط الكاميرا | B83: لا يوجد
B84: 4
B85: 6
B86: 8
B87: 9
A89: سعر سيراميك الملاحق: | B89: 30
B90: 40
B91: 50
A94: نقطة مياه السطح: | B94: لا
B95: 1
B96: 2
A98: نقطة كهرباء السطح: | B98: لا
B99: 1
B100: 2
A102: أحواض الزراعة | B102: يوجد
B103: لايوجد
A105: نعلة مخفية للجبس بلاستر | B105: يوجد
B106: لا يوجد
A108: مدة التنفيذ: | B108: 4 أشهر
B109: 5 أشهر
B110: 6 أشهر
B111: 7 أشهر
B112: 8 أشهر
B113: 9 أشهر
B114: 10 أشهر
B115: 11 شهر
B116: 12 شهر
B117: 13 شهر
B118: 14 شهر
B119: 15 شهر
B120: 16 شهر
... B124: 20 شهر
A126: الطابوق | B126: راكنور
B127: راس الخيمة
A130: الخرسانة | B130: الخليج
B131: النعيمي
B132: اوريميكس
A135: تمرير بايايبت التغ>ية | B135: علي سقف السطح
...

Sheet المدخلات
B1: معلومات المشروع والمواصفات
B2: مدخلات الاستشاري | AD2: مدخلات المقاول
B3: المالك | P3: احمد ابراهيم النعيمي | AD3: اسم المقاول
B4: وصف المشروع | P4: فيلا دور أرضي و اول وسور | AD4: رقم رخصة المقاول
B5: الإمارة | P5: رأس الخيمة | AD5: مساحة البناء | AR5: 118 | AY5: 5549
B6: رقم هاتف المالك | AD6: المهندس المسوول
B7: تاريخ تعاقد الاستشاري و المالك: | AD7: يوم عقد المقاول: | AR7: =TODAY() -> 46021
B8: يوم عقد المالك: | P8: الاريعاء | AD8: قيمة التعاقد:
B9: أتعاب التصميم: | AD9: مدة التنفيذ: | AR9: 14 شهر
B10: أتعاب الاشراف الشهرية:
B11: المنطقة | P11: الخران | AD11: رقم هاتف المسؤول عن المقاولات
B12: رقم القسيمة | P12: 403100010
B13: عنوان المالك | P13: راس الخيمة
AD14: تاريخ تسليم الموقع:

Sheet حساب الكميات
B2: حساب كميات المشروع
B3: معلومات المشروع
B4: المالك | K4: =المدخلات!$P$3 -> احمد ابراهيم النعيمي | AD4: المنطقة | AQ4: =المدخلات!$P$11 -> الخران
B5: وصف المشروع | K5: =المدخلات!$P$4 -> فيلا دور أرضي و اول وسور | AD5: رقم القسيمة | AQ5: =المدخلات!$P$12 -> 403100010
B6: مساحة السور م.طولي | K6: =المدخلات!AR5 -> 118 | AD6: مساحة البناء بالقدم المربع | AQ6: =المدخلات!$AY$5 -> 5549
B24: بيانات المقاول
B25: اسم الشركة | F25: Contra name | K25: =المدخلات!$AR$3 -> 0 | AD25: المسوول | AI25: Engineer | AQ25: =المدخلات!$AR$6 -> 0
B26: تاريخ | E26: Date | K26: =المدخلات!$AR$7 -> 46021 | AD26: رقم الهاتف: | AI26: Phone No | AQ26: =المدخلات!$AR$11 -> 0
B27: License number | K27: =المدخلات!$AR$4 -> 0 | AD27: مدة تنفيذ | AI27: Construction period | AQ27: =المدخلات!$AR$9 -> 14 شهر
B29: عرض السعر / Price OFFER | AQ29: ختم الشركة العارضة / Contractor Stamp
B30: تكلفة انشاء وانجاز الفيلا | P30: Total villa cost | AD30: =AO236 -> 67665 | AQ30: =المدخلات!AR10 -> 0
B31: تكلفة انشاء وإنجاز السور | P31: Total Boundary wall cost | AD31: =AY231 -> 0
B32: تكلفة انشاء وإنجاز الفيلا | P32: Total Villa and Boundary wall | AD32: =AD30+AD31+AO239 -> 67665
B33: الضريبة | P33: VAT | AD33: =AD32*0.05 -> 3383.25
B34: القيمة الاجمالية للمشروع شامل الضريبة | P34: Total project value with Vat | AD34: =AD32+AD33 -> 71048.25
B36: السعر المقدم بعد دراسة جميع بنود العقد والمواصفات ومطابقة جميع المخططات ومناظير ال 3D والموافقة عليها | AI36: The prices should include all contract activities m specification , confirming all drawings with project 3d
B37: حساب الكميات يجب ان يكون دقيق وان لا تتعدا الكميات 5% | AI37: Bill of Quantities should be accurate and not pass 5%
B38: علي المقاول الاستفسار من الاستشاري عن كل بند لم يكن واضحا في المناقصة . | AI38: contractor should send queries to consultant for any item not clear in the tender
B40: أولا : اعـــــمـــــــــال الـــــهــــيكــــــل | C40: أولا : أعمال الهيكل | AI40: english
C41: A | F41: أعمال المياه الجوفية و إحلال التربة وتجهز الموقع
C42: A1 | F42: تجفيف المياه الجوفية | Y42: Dewatering | AO42: L.S | AP42: M2 | AQ42: M2 | AR42: M2 | AS42: 0 | AW42: 1 | BA42: =AW42*AS42 -> 0
C43: A2 | F43: إحلال التربة | Y43: Soil replacement | AO43: L.S | AP43: M2 | AQ43: M2 | AR43: M2 | AS43: 0 | AW43: 1 | BA43: =AW43*AS43 -> 0
C44: A3 | F44: تجهيز الموقع | Y44: Mobilization | AO44: L.S | AP44: M2 | AQ44: M2 | AR44: M2 | AS44: 1 | AW44: 1 | BA44: =AW44*AS44 -> 1
C45: المياه الجوفية و إحلال التربة وتجهز الموقع | Y45: dewatering , soil replacement and Mobilization | AO45: =SUM(BA42:BD44) -> 1
C46: B | F46: أعمال تحت منسوب الأرض | AO46: substructure works
C47: B1 | F47: الحفر | X47: Excavation | AO47: M3 | AP47: M2 | AQ47: M2 | AR47: M2 | AS47: 1 | AW47: 1 | BA47: =AW47*AS47 -> 1
C48: B2 | F48: الرودبيس | X48: Road base | AO48: M3 | AP48: M2 | AQ48: M2 | AR48: M2 | AS48: 1 | AW48: 1 | BA48: =AW48*AS48 -> 1
C49: B3 | F49: خرسانة أسفل القواعد | X49: PCC under foundation | AO49: M3 | AP49: M2 | AQ49: M2 | AR49: M2 | AW49: 1 | BA49: =AW49*AS49 -> 0
C50: B4 | F50: خرسانة للقواعد | X50: RCC Foundation | AO50: M3 | AP50: M2 | AQ50: M2 | AR50: M2 | AS50: 1 | AW50: 1 | BA50: =AW50*AS50 -> 1
C51: B5 | F51: خرسانة مسلحة رقاب أعمدة | X51: Neck Columns | AO51: M3 | AP51: M2 | AQ51: M2 | AR51: M2 | AS51: 1 | AW51: 1 | BA51: =AW51*AS51 -> 1
C52: B6 | F52: طابوق مصمت أسفل الجسور الأرضية | X52: Solid block under tie beams | AO52: M2 | AS52: 1 | AW52: 1 | BA52: =AW52*AS52 -> 1
C53: B7 | F53: الجسور الأرضية | X53: Tie beams | AO53: M3 | AS53: 1 | AW53: 1 | BA53: =AW53*AS53 -> 1
C54: B8 | F54: عزل تحت منسوب الارض | X54: water proof for substructure | AO54: L.S | AS54: 1 | AW54: 1 | BA54: =AW54*AS54 -> 1
C55: B9 | F55: لوحات البولي ايثيلين | X55: Polythene sheet | AO55: L.S | AS55: 1 | AW55: 1 | BA55: =AW55*AS55 -> 1
C56: B10 | F56: الدفان والدمك | X56: back filling and compaction | AO56: M3 | AS56: 1 | AW56: 1 | BA56: =AW56*AS56 -> 1
C57: B11 | F57: الخرسانة الأرضية | X57: Flooring | AO57: M3 | AS57: 1 | AW57: 1 | BA57: =AW57*AS57 -> 1
C58: B12 | F58: معالجة النمل الأبيض (3مرات) | X58: Ant termite | AO58: L.S | AS58: 1 | AW58: 1 | BA58: =AW58*AS58 -> 1
C59: B13 | F59: غرفة المياه تحت الأرض | X59: Under ground water tank | AO59: L.S | AS59: 1 | AW59: 1 | BA59: =AW59*AS59 -> 1
C60: B14 | F60: غرفة استرجاع مياه التكييف تحت الأرض | X60: under ground tank for AC water | AO60: L.S | AS60: 1 | AW60: 1 | BA60: =AW60*AS60 -> 1
C61: B15 | F61: بالوعة الصرف الصحي | X61: septic tank | AO61: L.S | AP61: M2 | AQ61: M2 | AR61: M2 | AS61: 1 | AW61: 1 | BA61: =AW61*AS61 -> 1
C62: B16 | F62: توريد وتركيب اعمال المناهيل | X62: manhole works | AO62: No | AP62: M2 | AQ62: M2 | AR62: M2 | AS62: 1 | AW62: 1 | BA62: =AW62*AS62 -> 1
C63: أعمال تحت منسوب الأرض | X63: substructure works | AO63: =SUM(BA47:BD62) -> 15
C64: C | F64: أعمال فوق منسوب الأرض | AO64: Super Structure
C65: C1 | F65: خرسانة مسلحة للأعمدة الارضي | X65: GF Columns | AO65: M3 | AS65: 1 | AW65: 1 | BA65: =AW65*AS65 -> 1
C66: C2 | F66: خرسانة مسلحة للسقف الارضي | X66: GF Slab | AO66: M3 | AS66: 1 | AW66: 1 | BA66: =AW66*AS66 -> 1
C67: C3 | F67: خرسانة مسلحة اعمدة الدور الاول | X67: 1st floor Columns | AO67: M3 | AP67: M2 | AQ67: M2 | AR67: M2 | AS67: 1 | AW67: 1 | BA67: =AW67*AS67 -> 1
C68: C4 | F68: خرسانة مسلحة للسقف الاول | X68: 1st floor slab | AO68: M3 | AS68: 1 | AW68: 1 | BA68: =AW68*AS68 -> 1
C69: C5 | F69: خرسانة الروف | X69: Roof slab | AO69: M3 | AS69: 1 | AW69: 1 | BA69: =AW69*AS69 -> 1
C70: C6 | F70: خرسانة مسلحة السلالم الداخلية | X70: RCC for internal stairs | AO70: M3 | AS70: 1 | AW70: 1 | BA70: =AW70*AS70 -> 1
C71: C7 | F71: خرسانة مسلحة السلالم الخارجية | X71: RCC for external stairs | AO71: M3 | AS71: 1 | AW71: 1 | BA71: =AW71*AS71 -> 1
C72: C8 | F72: خرسانة الأعتاب والأقواس ولنتل | X72: Lintels | AO72: L.M | AS72: 1 | AW72: 1 | BA72: =AW72*AS72 -> 1
C73: C9 | F73: خرسانة مسلحة للباربيت | X73: RCC Parapet | AO73: M3 | AS73: 1 | AW73: 1 | BA73: =AW73*AS73 -> 1
C74: C10 | F74: خرسانة مسلحة للكورنيش | X74: Concrete for decoration | AO74: M3 | AS74: 1 | AW74: 1 | BA74: =AW74*AS74 -> 1
C75: أعمال فوق منسوب الأرض | AO75: =SUM(BA65:BD74) -> 10
C76: D | F76: أعمال الطابوق
C77: D1 | F77: طابوق خالي 25 صم | X77: Hollow Block 25cm | AO77: M2 | AP77: M2 | AQ77: M2 | AR77: M2 | AS77: 1 | AW77: 1 | BA77: =AW77*AS77 -> 1
C78: D2 | F78: طابوق معزول 25 صم | X78: Insulated Block 25 cm | AO78: M2 | AS78: 1 | AW78: 1 | BA78: =AW78*AS78 -> 1
C79: D3 | F79: طابوق 20 صم معزول | X79: Insulated Block 20 cm | AO79: M2 | AP79: M2 | AQ79: M2 | AR79: M2 | AS79: 1 | AW79: 1 | BA79: =AW79*AS79 -> 1
C80: D4 | F80: طابوق خالي 20 صم | X80: Hollow Block 20cm | AO80: M2 | AP80: M2 | AQ80: M2 | AR80: M2 | AS80: 1 | AW80: 1 | BA80: =AW80*AS80 -> 1
C81: D5 | F81: طابوق خالي 15صم | X81: Hollow Block 15cm | AO81: M2 | AP81: M2 | AQ81: M2 | AR81: M2 | AS81: 1 | AW81: 1 | BA81: =AW81*AS81 -> 1
C82: D6 | F82: طابوق خالي 10 صم | X82: Hollow Block 10cm | AO82: M2 | AP82: M2 | AQ82: M2 | AR82: M2 | AS82: 1 | AW82: 1 | BA82: =AW82*AS82 -> 1
C83: اجمالي الطابوق | AO83: =SUM(BA77:BD82) -> 6
B84: أولا : اعـــــمـــــــــال الـــــهــــيكــــــل | C84: E | F84: أعمال البلاستر
C85: E1 | F85: بلاستر داخلي عازل | X85: Internal Gypsum Plast | AO85: M2 | AP85: M2 | AQ85: M2 | AR85: M2 | AS85: 1 | AW85: 1 | BA85: =AW85*AS85 -> 1
C86: E2 | F86: اسمنت بلاستر داخلي | X86: Internal Plaster | AO86: M2 | AP86: M2 | AQ86: M2 | AR86: M2 | AS86: 1 | AW86: 1 | BA86: =AW86*AS86 -> 1
C87: E3 | F87: بلاستر خارجي | X87: External Plaster | AO87: M2 | AP87: M2 | AQ87: M2 | AR87: M2 | AS87: 1 | AW87: 1 | BA87: =AW87*AS87 -> 1
C88: 30 | F88: النعلة المخفية | X88: Hidden Skirting | AO88: M.L | AP88: M2 | AQ88: M2 | AR88: M2 | AS88: 1 | AW88: 1 | BA88: =AW88*AS88 -> 1
C89: إجمالي البلاستر | X89: Total Plaster | AO89: =SUM(BA85:BD88) -> 4
C90: F | F90: أعمال الطبقات العازلة
C91: F1 | F91: عزل ممبرين4 مم أسفل الجدران الخارجية | X91: Damp Proof membrane | AO91: LS | AP91: M2 | AQ91: M2 | AR91: M2 | AS91: 1 | AW91: 1 | BA91: =AW91*AS91 -> 1
C92: F2 | F92: عزل السطح ( كومبو 40مم) | X92: Combo Roof insulation 40mm | AO92: M2 | AP92: M2 | AQ92: M2 | AR92: M2 | AS92: 1 | AW92: 1 | BA92: =AW92*AS92 -> 1
C93: F3 | F93: عزل الاسقف antifungs | X93: insulation under celing | AO93: M2 | AP93: M2 | AQ93: M2 | AR93: M2 | AS93: 1 | AW93: 1 | BA93: =AW93*AS93 -> 1
C94: F4 | F94: عزل أرضية الحمامات (اسمنتي) | X94: Wet Area water proof (Cementous) | AO94: =AO95 -> M2 | AS94: 1 | AW94: 1 | BA94: =AW94*AS94 -> 1
C95: F5 | F95: عزل أرضية البلكونات (اسمنتي) | X95: Balcony water proof (Cementous) | AO95: M2 | AP95: M2 | AQ95: M2 | AR95: M2 | AS95: 1 | AW95: 1 | BA95: =AW95*AS95 -> 1
C96: إجمالي الطبقات العازلة | X96: Total Water proof | AO96: =SUM(BA91:BD95) -> 5
C97: G | F97: تركيب اكساءات الارضيات و الجدران | AO97: Floors and Walls Finishing
A98: على المقاول تزويد الموقع بالكوادر الفنية والعمالة اللازمة لتنفيذ المشروع بالمستوى المطلوب مع مراعاة مايلي : 1 – جميع عناصر الكادر الفني والعمالة الفنية يجب أن يكونوا من المؤهلين ومن ذوي الخبرة والكفاءة كلاً حسب اختصاصه وحسب متطلبات العمل والتنفيذ ( من حيث العدد والتوزيع ). 2- يتم اعتماد الكوادر الفنية من قبل الاستشاري قبل مباشرتهم للعمل، ويجب أن تكون الكوادر الفنية من ذوي الخبرة بأعمال مماثلة. 3 – يحق للإستشاري الطلب من المقاول إبعاد/استبدال أي شخص مستخدم من قبله إذا رأى الاستشاري أن ذلك الشخص ليس بالمستوى المطلوب من حيث السلوك أو الخبرة لتنفيذ الأعمال. 4 – على المقاول تقديم جدول بأعداد العمالة العادية والفنية العاملة في الموقع بشكل أسبوعي. 5 – يشتمل الكادر الفني (المطلوب من المقاول توفيره كحد أدنى) على : • مدير للمشروع. • مهندس موقع ( Site Engineer )مسؤول عن تنفيذ المشروع للتعامل مع الاستشاري • مراقب فني (Forman) لكل نوع من أنواع الأعمال. • أي كوادر فنية أخرى يطلبها الاستشاري ويرى أنها لازمة لتنفيذ المشروع بالمستوى المطلوب. • مقاول باطن اعمال الالكتروميكانيك يجب ان يكون معتمد من الاستشاري و الـ FEWA. | C98: G1 | F98: اكساءات ارضيات للمدخل الرئيسي للفيلا | X98: Flooring for main entrance | AO98: M2 | AP98: M2 | AQ98: M2 | AR98: M2 | AS98: 1 | AW98: 1 | BA98: =AW98*AS98 -> 1
C99: G2 | F99: أرضيات درج المدخل الرئيسي والرامب | X99: Steps of main entrance and Ramp | AO99: M2 | AP99: M2 | AQ99: M2 | AR99: M2 | AS99: 1 | AW99: 1 | BA99: =AW99*AS99 -> 1
C100: G3 | F100: أرضيات التيراس بالدور الاول ان وجد | X100: 1st floor balcony if any | AO100: M2 | AS100: 1 | AW100: 1 | BA100: =AW100*AS100 -> 1
C101: G4 | F101: اكساءات ارضيات الدور الاول و الارض | X101: Flooring for GF and 1st floor | AO101: M2 | AP101: M2 | AQ101: M2 | AR101: M2 | AS101: 1 | AW101: 1 | BA101: =AW101*AS101 -> 1
C102: G5 | F102: اكساء الدرج الداخلي للفيلا. | X102: internal steps | AO102: L.M | AP102: M2 | AQ102: M2 | AR102: M2 | AS102: 1 | AW102: 1 | BA102: =AW102*AS102 -> 1
C103: G6 | F103: اكساءات الحوائط | X103: Wall tiles | AO103: M2 | AP103: M2 | AQ103: M2 | AR103: M2 | AS103: 1 | AW103: 1 | BA103: =AW103*AS103 -> 1
C104: G7 | F104: النعلات حسب المواصافات | X104: Skirting | AO104: =AO102 -> L.M | AP104: M2 | AQ104: M2 | AR104: M2 | AS104: 1 | AW104: 1 | BA104: =AW104*AS104 -> 1
C105: G8 | F105: حماية من البلاستيك و الجبس للارضيات | X105: flooring protection | AO105: =AO115 -> L.S | AP105: M2 | AQ105: M2 | AR105: M2 | AS105: 1 | AW105: 1 | BA105: =AW105*AS105 -> 1
C106: إجمالي تركيب اكساءات الارضيات و الجدران | X106: Total of tile works flooring and walls | AO106: =SUM(BA98:BD105) -> 8
C107: اجمالي الاعمال الهيكل | X107: Total of main structure | AO107: =AO45+AO63+AO75+AO106+AO83+AO89+AO96 -> 49
B109: =$C$109 -> ثانيا : اعمال الالكتروميكانيكال | C109: ثانيا : اعمال الالكتروميكانيكال | AO109: Electromechanical Works
C110: H | F110: اعمال MEP حتي التسليم | AO110: MEP works till handing over
C111: H1 | F111: توريد وتركيب بايبات الصرف و التغذية | X111: supply and install drainage and water pipes | AO111: L.S | AS111: 1 | AW111: 1 | BA111: =AW111*AS111 -> 1
C112: H2 | F112: توريد وتركيب يايبات الكهرباء و الاتصالات | X112: Supply and install Electrical pipes | AO112: L.S | AS112: 1 | AW112: 1 | BA112: =AW112*AS112 -> 1
C113: H3 | F113: توريد وتركيب بايبات الشفط المركزي | X113: supply and install central vacuum pipes | AO113: L.S | AS113: 1 | AW113: 1 | BA113: =AW113*AS113 -> 1
C114: H4 | F114: تنفيذ الكلين اوت | X114: Drainage clean out works | AO114: L.S | AS114: 1 | AW114: 1 | BA114: =AW114*AS114 -> 1
C115: H5 | F115: انذار الحريق و انارة الطوارئ | X115: Fire alarm and emergency lights | AO115: L.S | AS115: 1 | AW115: 1 | BA115: =AW115*AS115 -> 1
C116: H6 | F116: تركيب خزانات المياه أعلى السطح | X116: Install tanks above roof | AO116: No | AP116: M2 | AQ116: M2 | AR116: M2 | AS116: 1 | AW116: 1 | BA116: =AW116*AS116 -> 1
C117: H7 | F117: تركيب خزان مياه تحت الأرض | X117: install underground water tank | AO117: No | AP117: M2 | AQ117: M2 | AR117: M2 | AS117: 1 | AW117: 1 | BA117: =AW117*AS117 -> 1
C118: H8 | F118: تركيب خزان استرجاع مياه التكييف | X118: install tank for AC water | AO118: No | AS118: 1 | AW118: 1 | BA118: =AW118*AS118 -> 1
C119: H9 | F119: تركيب السخان المركزي | X119: install central heater | AO119: No | AP119: M2 | AQ119: M2 | AR119: M2 | AS119: 2 | AW119: 1 | BA119: =AW119*AS119 -> 2
C120: H10 | F120: تركيب الأطقم الصحية | X120: install sanitary wares | AO120: L.S | AP120: M2 | AQ120: M2 | AR120: M2 | AS120: 1 | AW120: 1 | BA120: =AS120*AW120 -> 1
C121: H11 | F121: تأسيس 9 نقاط كاميرا | X121: Pipes for 6 no's Camera | AO121: L.S | AP121: M2 | AQ121: M2 | AR121: M2 | AS121: 1 | AW121: 1 | BA121: =AW121*AS121 -> 1
C122: H12 | F122: توريد وتركيب باقي أعمال حتي التسليم | X122: supply and install other works till authorities handing over | AO122: L.S | AP122: M2 | AQ122: M2 | AR122: M2 | AS122: 1 | AW122: 1 | BA122: =AW122*AS122 -> 1
...

Sheet اتفاق 01 (2)
B1: عقد اتفاق بين المالك و الاستشاري
B2: انه في يوم | D2: =المدخلات!$P$8 -> الاريعاء | E2: بتاريخ | F2: =المدخلات!$P$7 -> 0 | H2: حرر بين كل من: | J2: المنطقة | L2: =المدخلات!$P$11 -> الخران
B3: • | C3: الطرف الأول السيد | E3: =المدخلات!$P$3 -> احمد ابراهيم النعيمي | H3: القسيمة رقم | J3: =المدخلات!$P$12 -> 403100010 | L3: =المدخلات!$P$6 -> 0
B4: • | C4: لطرف الثاني: | E4: اشركة سافانا ديزاين للاستشارات الهندسية والتصميم الداخلي، رخصة رقم(48818)، وعنوانها مكتب رقم (407) بأبراج جلفار، في إمارة رأس الخيمة ، ويمثلها المدير / المهندس أيمن بن حمادي، وبعد أن أقر المتعاقدان بأهليتهما للتصرف والتعاقد اتفقا على ما يأتي:
B5: 1 | C5: قبل الطرف الثاني بموجب هذا العقد أن يقوم بأعمال التصميم الهندسي والإشراف عل مشروع الفيلا الخاصة بالطرف الأول، الوارد بياناتها في مقدمة هذا العقد، وذلك حسب المعايير والمواصفات المحددة من قبل الجهات المختصة.
B6: 2 | C6: يلتزم الطرف الأول بدفع مبلغ وقدره | H6: =المدخلات!$P$9 -> 0 | I6: درهم غير شامل الضريبة, للطرف الثاني مقابل أعمال التصاميم
B7: 3 | C7: يلتزم الطرف الأول بدفع كافة رسوم الجهات الحكومية أو الخاصة، والمطلوبة لفتح معاملات اعتماد المخططات والرسومات الهندسية، أو التعديل عليها.
B8: 4 | C8: لا يتحمل الطرف الثاني أي تأخير حاصل من قبل أي جهات أخرى، وتكون حدود مسؤوليته في العمل المنوط به فقط .
B9: 5 | C9: يقر الطرف الأول بأن كل الأفكار و المخططات والتصاميم المقدمة من الطرف الثاني تعتبر حق من حقوق ملكيته الفكرية، ولا يمكن نقلها لأي جهة مهما كانت أو التنازل عنها إلا بكتاب خطي موقع ومختوم من الطرف الثاني.
B10: 6 | C10: أي مبالغ مدفوعة في أي مرحلة من مراحل تصميم المشروع والإشراف عليه، تكون نظير للأفكار والجهد والوقت والخدمة المقدمة من قبل الطرف الثاني، ولا يعطي الحق للطرف الأول في المطالبة باسترجاع تلك المبالغ في حال عدم إكماله للمشروع.
B11: 7 | C11: يستحق الطرف الثاني نسبة من القيمة الإجمالية لعقد المقاولة ، يدفعه مقاول المشروع، أو الطرف الأول.
B12: 8 | C12: يلتزم الطرف الأول بدفع مبلغ مقابل إشراف | H12: =المدخلات!$P$10 -> 0 | I12: درهم،غير شامل الضريبة وتكون مستحقة بداية كل شهر ميلادي من بداية تنفيذ المشروع وحتى الانتهاء من إنجازه.
B13: 9 | C13: يلتزم الطرف الثاني بأن تكون الزيارات الإشرافية بمعدل أربع زيارات في الشهر تحسب بمعدل إجمالي طيلة فترة تنفيذ المشروع، وحسب ما يقتضيه تقدم الأشغال في الموقع، كما يقر الطرف الثاني أنه في حال توقف الأشغال لمدة ثلاثة أشهر أو أكثر لأي سبب كان، فأنه لا يحق له مطالبة الطرف الأول بدفع مبلغ الإشراف في فترة التوقف.
B14: 10 | C14: اذا وجد عائق من عوائق الارض ( ديفان , كابل كهرباء , تعديل تحت المنسوب….) فالطرف الاول من يتحمل تسوية الموضوع.
B15: 11 | C15: يلتزم المالك بدفع رسوم إضافية يحددها الاستشاري فب حال طلب المالك أي تعديل علي المخططات بعد البدء بتجهيز المخططات التنفيذية لاعتمادها من الجهات الحكومبة و ينطبق ذلك علي أي تعديلات لاحقة
B16: 12 | C16: يلتزم المالك بدفع رسوم معاملة ادخال الكهرباء و معاملة الإنجاز في اخر المشروع
B17: 13 | C17: يحق للطرف الثاني (الاستشاري) نشر صور وفيديوات للمشروع
B18: 14 | C18: يحق للطرف الأول تغيير الطرف الثاني (الاستشاري) أثناء تنفيذ مشروع البناء، وليس قبل ذلك بأي حال من الأحوال ،و في حال الطرف الاول قرر عدم مواصلة المشروع قبل مرحلة التنفيذ يلتزم بدفع باقي المبالغ المستحقة و يكون المبلغ المدفوع في البند 2 نظير اعمال التصاميم المبدئية فقط مع الاحتفاظ بحقوق التصميم.
B19: 15
B20: المالك | H20: الاستشاري
B21: =المدخلات!$P$3 -> احمد ابراهيم النعيمي | H21: سافانا ديزاين للاستشارات الهندسية والتصميم الداخلي

Sheet أسعار التوريد
B1: المالك | G1: =[1]المدخلات!P3 -> محمد ناصر المنصوري | S1: المنطفة | Y1: =[1]المدخلات!AR3 -> Awafi | AG1: القسيمة | AM1: =[1]المدخلات!AR4 -> 406131934 | AU1: المقاول | AY1: =[1]المدخلات!AR10 -> السفير
B2: ='[1]حساب الكميات'!AO277 -> 0
B3: اختيار الأنواع
J4: 1 | K4: السخان | R4: مركزي مع 2 سخان Ariston 200 L | AD4: 15- خزان استرجاع مياه التكييف | AT4: تحت الأرض
J5: 2 | K5: كراسي الحمامات | R5: عادي | AD5: 16- مكسرات المغاسل والحمامات | AT5: عادية
J6: 3 | K6: الشفط | R6: مركزي مخفي للسطح او للجدران الخارجية | AD6: 17- الصرف | AT6: كلين اوت
J7: 4 | K7: النعلة | R7: شامل النعلات - مخفية | AD7: 18-حبات السيراميك | AT7: متوسطة
P8: 5-الألمنيوم | R8: بروفايل فول امبريلا عادي | AD8: 19- سعة خزان المياه | AT8: 1000 جالون
P9: 6- خزان المياه | R9: فوق الأرض | AD9: 20- ارتفاعات الأبواب | AT9: 250 Cm
P10: 7-الباب الرئيسي كاست المنيوم | R10: دبل هايت | AD10: 21-نقاط مياه في السور: | AT10: عدد 4
P11: 8-نوع الصبغ: | R11: سانديكس | AD11: 22-نقاط كهرباء في السور: | AT11: 4
P12: 9-الماء الحار والبارد للشطاف : | R12: كامل حمامات البيت | AD12: 23- الحجر والبورسلان الخارجي: | AT12: 50
P13: 10-نقطة كهرباء سيارة: | R13: لا | AD13: 24- نقاط الكاميرا: | AT13: 6
P14: 11-نقاط اضاءة بالواجهة | R14: نعم | AD14: 25- سعر سيراميك الملاحق: | AT14: 30
P15: 12-نقطة صرف وتغذية للبانتري في الدور الأول: | R15: نعم | AD15: 26-أحواض الزراعة: | AT15: يوجد
P16: 13-نقطة مياه السطح: | R16: 1 | AD16: 27-نعلة مخفية للجبس بلاستر | AT16: يوجد
P17: 14-نقطة كهرباء في السطح: | R17: 1 | AD17: 28-مدة التعاقد | AT17: 16 شهر
B18: 03-الطابوق | R18: =[1]Sheet2!B126 -> راكنور | AD18: 02-الخرسانة | AT18: =[1]Sheet2!B130 -> الخليج
R19: =[1]Sheet2!B127 -> راس الخيمة | AT19: =[1]Sheet2!B131 -> النعيمي
AT20: =[1]Sheet2!B132 -> اوريميكس
B21: 31- تركيب تمديدات التغذية فوق السطح | R21: علي جدران البارابت | AD21: 32-صرف الحمامات الدور الاول | AT21: =[1]Sheet2!B141 -> داكت من تحت لفوق السطح
AT22: =[1]Sheet2!B142 -> تحت الاسقف الي داكت الارضي
B23: 33-نوعية بايبات و اسلاك الكهرباء | R23: ناشيونال | AD23: 34-نوعية تمديدات تغذية المياه | AT23: =[1]Sheet2!B147 -> اكواثرم
AT24: =[1]Sheet2!B148 -> راكثيرم
B25: 35-نوعية بايبات الصرف الصحي | R25: اطلس | AD25: 36-مراوح الشفاط المركزي | AT25: اعمال مدنية بايبات على المقاول
B26: 37-قواطع بانواعها | R26: شنايدر | AD26: 38-اللوحات و الصناديق | AT26: شنايدر
B27: 39-الايزوليتر | R27: شنايدر | AD27: 40-مفاتيح الانارة | AT27: ليجراند
B28: 41-اعمال مدنية للتكييف | R28: مركزي او سبليت علي المقاول | AD28: 42-تجويفات جدران الحمامات | AT28: جدار واحد حسب الديكور عمق 13 سنت
B29: 43-الدرج الامامي لمدخل الفيلا | R29: طاير مع اضاءة من تحت | AD29: 44-تركيب قروفات بالسور | AT29: توريد مالك تركيب مقاول
B30: 45-حماية الارضيات بعد تركيب البورسلان | R30: طبقة جبس مع بلاستيك | AD30: 46-توريد و تركيب رداد للكلين اوت | AT30: من ضمن السعر
B31: 47- جي اي بوكس للماخذ و المفاتيح | R31: الفنار | AD31: 01-الحديد | AT31: قطري
B33: المشرووع | S33: القسيممة | Y33: المنطقة | AG33: المقاول | AS33: المالك
B34: =المدخلات!$P$4 -> فيلا دور أرضي و اول وسور | S34: =المدخلات!$P$12 -> 403100010 | Y34: =المدخلات!$P$11 -> الخران | AG34: =المدخلات!$AR$3 -> 0 | AS34: =المدخلات!$P$3 -> احمد ابراهيم النعيمي
B37: أسعار توريد التشطيبات
B39: البند | AR39: الوحدة | AW39: سعر التوريد
B41: اسعار توريد السيراميك | R41: ='حساب الكميات'!F133 -> اكساءات ارضيات للمدخل الرئيسي للفيلا | AR41: M2 | AW41: 50
R42: ='حساب الكميات'!F134 -> أرضيات درج المدخل الرئيسي والرامب | AR42: M2 | AW42: 80
R43: ='حساب الكميات'!F135 -> أرضيات التيراس بالدور الاول ان وجد | AR43: M2 | AW43: 50
R44: ='حساب الكميات'!F136 -> اكساءات ارضيات الدور الاول و الارض | AR44: M2 | AW44: 35
R45: ='حساب الكميات'!F137 -> اكساء الدرج الداخلي للفيلا. | AR45: L.M | AW45: 250
B46: مجموع سعر التوريد | R46: ='حساب الكميات'!F138 -> اكساءات حوائط | AR46: =AR45 -> L.M | AW46: 50
B47: ='حساب الكميات'!AO140 -> 525 | R47: ='حساب الكميات'!F139 -> النعلات حسب المواصافات | AR47: =AR46 -> L.M | AW47: 10
R48: توريد اكساءات الواجهات | AR48: M2 | AW48: 90
B50: سعر توريد الأبواب الداخلية | R50: ="توريد الباب الرئيسي للفيلا "&TEXT(R114,0) -> توريد الباب الرئيسي للفيلا ارتفاع لسقف الأرضي | AE50: ارتفاع لسقف الأرضي | AR50: NO. | AW50: 45000
R51: ="توريد الباب الخارجي للمجلس - ارتفاع "&TEXT(R131,0) -> توريد الباب الخارجي للمجلس - ارتفاع 250 Cm | AR51: NO. | AW51: 0
R52: ="توريد أبواب الغرف والحمامات - ارتفاع "&TEXT(R131,0) -> توريد أبواب الغرف والحمامات - ارتفاع 250 Cm | AR52: NO. | AW52: 3000
B53: مجموع سعر التوريد | R53: ="توريد أبواب الغرف الخدمية - ارتفاع "&TEXT(R131,0) -> توريد أبواب الغرف الخدمية - ارتفاع 250 Cm | AR53: NO. | AW53: 1500
B54: ='حساب الكميات'!AO150 -> 49500 | R54: توريد بابى السور كاست الومنيوم باب كبير و صغير | AR54: NO. | AW54: 12000
B56: سعر توريد الألمينوم | R56: سعرتوريد الالمنيوم و الزجاج | AD56: CURTIN WALL | AR56: m2 | AW56: 600
B58: مجموع سعر التوريد | R58: هاندريل الدرج الزجاج و الدابل هايت ان وجد ارتفاع 1.70 | AR58: m2 | AW58: 1200
B59: ='حساب الكميات'!AO144 -> 1800
B61: توريد الاطقم الصحية | R61: ='حساب الكميات'!F156 -> الاطقم الصحية لحمام مغاسل الصالة والمجلس | AR61: الأطقم | AW61: 2500
AR62: الكرسي | AW62: 1500
AR63: الكاونتر | AW63: 2000
R64: ='حساب الكميات'!F157 -> الاطقم الصحية لحمام ومغاسل غرف النوم | AR64: الأطقم | AW64: 2500
AR65: الكرسي | AW65: 1500
AR66: الكاونتر | AW66: 2000
R67: ='حساب الكميات'!F158 -> الاطقم الصحية لحمام ومغاسل غرفة الشغالة | AR67: الأطقم | AW67: 500
AR68: الكرسي | AW68: 500
B69: مجموع سعر التوريد | AR69: المغسلة | AW69: 300
B70: ='حساب الكميات'!AO160 -> 13900 | R70: سعر توريد خلاط المطبخ | AR70: NO. | AW70: 500
B72: ملاحظات:
B73: اعمال البورسلان و السيراميك و الرخام و الانترلوك المحيطة بالفيلا او المسبح توريد تركيب المالك باستثناء المساحة بين الملحق و الفيلا توريد مالك وتركيب مقاول
B80: مواصفات مواد الهيكل
B82: الحديد | R82: قطري
B83: الخرسانة | D83: الخرسانة | F83: الخرسانة | H83: الخرسانة | J83: الخرسانة | L83: الخرسانة | N83: الخرسانة | P83: الخرسانة | R83: الخليج | AR83: اوريميكس
B84: الطابوق | D84: الطابوق | F84: الطابوق | H84: الطابوق | J84: الطابوق | L84: الطابوق | N84: الطابوق | P84: الطابوق | R84: راكنور | AR84: دبي
B85: الاعمدة | D85: الاعمدة | F85: الاعمدة | H85: الاعمدة | J85: الاعمدة | L85: الاعمدة | N85: الاعمدة | P85: الاعمدة | R85: خرسانة ذاتية الدمج
B86: الخشب | D86: الخشب | F86: الخشب | H86: الخشب | J86: الخشب | L86: الخشب | N86: الخشب | P86: الخشب | R86: من النوعية الجيدة إلى النوعية الجديدة
B88: مواصفات المواد الصحية
B90: نوعية تمديدات تغذية المياه | R90: اكواثرم | AC90: PIX PIBE | AR90: تركيب تحت الاسقف
B91: نوعية بايبات الصرف الصحي | R91: اطلس | AR91: ترين
B92: نوعية الخزان تحت الأرض | R92: من الياف الفايبر
B93: نوعية الخزان فوق الأرض | R93: من الياف الفايبر
B94: نوعية السخان المركزي | R94: ARISTON إيطالي
B95: نوعية مكاين الضغط | R95: اسباني/ ايطالي
B97: مواصفات المواد الكهرباية
A98: على المقاول تزويد الموقع بالكوادر الفنية والعمالة اللازمة لتنفيذ المشروع بالمستوى المطلوب مع مراعاة مايلي : 1 – جميع عناصر الكادر الفني والعمالة الفنية يجب أن يكونوا من المؤهلين ومن ذوي الخبرة والكفاءة كلاً حسب اختصاصه وحسب متطلبات العمل والتنفيذ ( من حيث العدد والتوزيع ). 2- يتم اعتماد الكوادر الفنية من قبل الاستشاري قبل مباشرتهم للعمل، ويجب أن تكون الكوادر الفنية من ذوي الخبرة بأعمال مماثلة. 3 – يحق للإستشاري الطلب من المقاول إبعاد/استبدال أي شخص مستخدم من قبله إذا رأى الاستشاري أن ذلك الشخص ليس بالمستوى المطلوب من حيث السلوك أو الخبرة لتنفيذ الأعمال. 4 – على المقاول تقديم جدول بأعداد العمالة العادية والفنية العاملة في الموقع بشكل أسبوعي. 5 – يشتمل الكادر الفني (المطلوب من المقاول توفيره كحد أدنى) على : • مدير للمشروع. • مهندس موقع ( Site Engineer )مسؤول عن تنفيذ المشروع للتعامل مع الاستشاري • مراقب فني (Forman) لكل نوع من أنواع الأعمال. • أي كوادر فنية أخرى يطلبها الاستشاري ويرى أنها لازمة لتنفيذ المشروع بالمستوى المطلوب. • مقاول باطن اعمال الالكتروميكانيك يجب ان يكون معتمد من الاستشاري و الـ FEWA.
B99: اللوحات و الصناديق | R99: شنايدر
B100: مفاتيح الانارة | D100: مفاتيح الانارة | F100: مفاتيح الانارة | H100: مفاتيح الانارة | J100: مفاتيح الانارة | L100: مفاتيح الانارة | N100: مفاتيح الانارة | P100: مفاتيح الانارة | R100: PANASONIC | T100: ليجراند | V100: ليجراند | X100: ليجراند | Z100: ليجراند | AB100: ليجراند | AD100: ليجراند | AF100: ليجراند | AH100: ليجراند | AJ100: ليجراند | AL100: ليجراند | AN100: ليجراند | AP100: ليجراند | AR100: مع تيوترال
B101: نوع بايبات و اسلاك الكهرباء | D101: نوع بايبات و اسلاك الكهرباء | F101: نوع بايبات و اسلاك الكهرباء | H101: نوع بايبات و اسلاك الكهرباء | J101: نوع بايبات و اسلاك الكهرباء | L101: نوع بايبات و اسلاك الكهرباء | N101: نوع بايبات و اسلاك الكهرباء | P101: نوع بايبات و اسلاك الكهرباء | R101: دوكاب | T101: دوكاب | V101: دوكاب | X101: دوكاب | Z101: دوكاب | AB101: دوكاب | AD101: دوكاب | AF101: دوكاب | AH101: دوكاب | AJ101: دوكاب | AL101: دوكاب | AN101: دوكاب | AP101: دوكاب
B102: قواطع رييسية | D102: قواطع رييسية | F102: قواطع رييسية | H102: قواطع رييسية | J102: قواطع رييسية | L102: قواطع رييسية | N102: قواطع رييسية | P102: قواطع رييسية | R102: DORMAN SWITSH | T102: شنايدر | V102: شنايدر | X102: شنايدر | Z102: شنايدر | AB102: شنايدر | AD102: شنايدر | AF102: شنايدر | AH102: شنايدر | AJ102: شنايدر | AL102: شنايدر | AN102: شنايدر | AP102: شنايدر | AR102: Abb
B103: الازوليتر | D103: الازوليتر | F103: الازوليتر | H103: الازوليتر | J103: الازوليتر | L103: الازوليتر | N103: الازوليتر | P103: الازوليتر | R103: شنايدر | T103: شنايدر | V103: شنايدر | X103: شنايدر | Z103: شنايدر | AB103: شنايدر | AD103: شنايدر | AF103: شنايدر | AH103: شنايدر | AJ103: شنايدر | AL103: شنايدر | AN103: شنايدر | AP103: شنايدر
B104: جي اي بوكس للماخذ ومفاتيح | D104: جي اي بوكس للماخذ و مفاتيح | F104: جي اي بوكس للماخذ و مفاتيح | H104: جي اي بوكس للماخذ و مفاتيح | J104: جي اي بوكس للماخذ و مفاتيح | L104: جي اي بوكس للماخذ و مفاتيح | N104: جي اي بوكس للماخذ و مفاتيح | P104: جي اي بوكس للماخذ و مفاتيح | R104: الفنار | T104: الفنار | V104: الفنار | X104: الفنار | Z104: الفنار | AB104: الفنار | AD104: الفنار | AF104: الفنار | AH104: الفنار | AJ104: الفنار | AL104: الفنار | AN104: الفنار | AP104: الفنار
B106: مواصفات من اختيار المالك
B108: السخان | R108: مركزي مع 2 سخان 200L كل واحد ARISTON
B109: كراسي الحمامات | D109: كراسي الحمامات | F109: كراسي الحمامات | H109: كراسي الحمامات | J109: كراسي الحمامات | L109: كراسي الحمامات | N109: كراسي الحمامات | P109: كراسي الحمامات | R109: معلق مع سماكة جدار 25 سنتم
B110: الشفط | D110: الشفط | F110: الشفط | H110: الشفط | J110: الشفط | L110: الشفط | N110: الشفط | P110: الشفط | R110: مركزي مخفي للسطح او للجدران الخارجية
B111: النعلة | D111: النعلة | F111: النعلة | H111: النعلة | J111: النعلة | L111: النعلة | N111: النعلة | P111: النعلة | R111: شامل النعلات - مخفية مع ستيل
B112: الألمنيوم | D112: الألمنيوم | F112: الألمنيوم | H112: الألمنيوم | J112: الألمنيوم | L112: الألمنيوم | N112: الألمنيوم | P112: الألمنيوم | R112: بروفايل كيرتين وول
B113: خزان المياه | D113: خزان المياه | F113: خزان المياه | H113: خزان المياه | J113: خزان المياه | L113: خزان المياه | N113: خزان المياه | P113: خزان المياه | R113: تحت الأرض مع غرفة
B114: الباب الرئيسي كاست المنيوم | D114: الباب الرئيسي كاست المنيوم | F114: الباب الرئيسي كاست المنيوم | H114: الباب الرئيسي كاست المنيوم | J114: الباب الرئيسي كاست المنيوم | L114: الباب الرئيسي كاست المنيوم | N114: الباب الرئيسي كاست المنيوم | P114: الباب الرئيسي كاست المنيوم | R114: =AE50 -> ارتفاع لسقف الأرضي
B115: نوع الصبغ | D115: نوع الصبغ | F115: نوع الصبغ | H115: نوع الصبغ | J115: نوع الصبغ | L115: نوع الصبغ | N115: نوع الصبغ | P115: نوع الصبغ | R115: جوتاشيلد جوتن
B116: الماء الحار والبارد للشطاف | D116: الماء الحار والبارد للشطاف | F116: الماء الحار والبارد للشطاف | H116: الماء الحار والبارد للشطاف | J116: الماء الحار والبارد للشطاف | L116: الماء الحار والبارد للشطاف | N116: الماء الحار والبارد للشطاف | P116: الماء الحار والبارد للشطاف | R116: لا
B117: نقطة كهرباء سيارة | D117: نقطة كهرباء سيارة | F117: نقطة كهرباء سيارة | H117: نقطة كهرباء سيارة | J117: نقطة كهرباء سيارة | L117: نقطة كهرباء سيارة | N117: نقطة كهرباء سيارة | P117: نقطة كهرباء سيارة | R117: نعم | AR117: 2 مع ازوليتر
B118: نقاط اضاءة بالواجهات | D118: نقاط اضاءة بالواجهة | F118: نقاط اضاءة بالواجهة | H118: نقاط اضاءة بالواجهة | J118: نقاط اضاءة بالواجهة | L118: نقاط اضاءة بالواجهة | N118: نقاط اضاءة بالواجهة | P118: نقاط اضاءة بالواجهة | R118: نعم
B119: صرف وتغذية للبانتري الدور الأول | D119: نقطة صرف وتغذية للبانتري في الدور الأول | F119: نقطة صرف وتغذية للبانتري في الدور الأول | H119: نقطة صرف وتغذية للبانتري في الدور الأول | J119: نقطة صرف وتغذية للبانتري في الدور الأول | L119: نقطة صرف وتغذية للبانتري في الدور الأول | N119: نقطة صرف وتغذية للبانتري في الدور الأول | P119: نقطة صرف وتغذية للبانتري في الدور الأول | R119: نعم
B120: نقطة كهرباء السطح | D120: نقطة مياه السطح | F120: نقطة مياه السطح | H120: نقطة مياه السطح | J120: نقطة مياه السطح | L120: نقطة مياه السطح | N120: نقطة مياه السطح | P120: نقطة مياه السطح | R120: 2
B121: نقطة مياه في السطح | D121: نقطة كهرباء في السطح | F121: نقطة كهرباء في السطح | H121: نقطة كهرباء في السطح | J121: نقطة كهرباء في السطح | L121: نقطة كهرباء في السطح | N121: نقطة كهرباء في السطح | P121: نقطة كهرباء في السطح | R121: 2
B122: تركيب تمديدات التغذية | D122: 31- تركيب تمديدات التغذية فوق السطح | F122: 31- تركيب تمديدات التغذية فوق السطح | H122: 31- تركيب تمديدات التغذية فوق السطح | J122: 31- تركيب تمديدات التغذية فوق السطح | L122: 31- تركيب تمديدات التغذية فوق السطح | N122: 31- تركيب تمديدات التغذية فوق السطح | P122: 31- تركيب تمديدات التغذية فوق السطح | R122: تحت الاسقف
...

Sheet المواصفات الفنية
A10: المواصفات الفنية والشروط العامة
A16: مشروع | Z16: =المدخلات!P4 -> فيلا دور أرضي و اول وسور
A18: عايدة للمالك | Z18: =المدخلات!P3 -> احمد ابراهيم النعيمي
M22: القسيمة | Z22: =المدخلات!$P$12 -> 403100010
M26: المنطقة | Z26: =المدخلات!$P$11 -> الخران
A34: فهرس دفتر الشروط الفنية الخاصة
A36: ( 1 ) المتطلبات العامة وأعمال تحضير الموقع
A37: ( 2 ) أعمال الحفر والرودبيس
A38: ( 3 ) أعمال الخرسانات
A39: ( 4 ) أعمال الطابوق
A40: ( 5 ) أعمال البلاستر
A41: ( 6 ) أعمال العزل
A42: ( 7 ) الأعمال الصحية
A43: ( 8 ) الأعمال الكهربائية
A44: ( 9 ) أعمال الهاندريل والألمنيوم والزجاج
A45: ( 10 ) جدول تشطيبات الأعمال الصحية
A46: ( 11 ) جدول تشطيبات الأعمال الكهربائية
... A65: 2.1.1- المشروع والموقع :
A66: ="1 – المطلوب إنشاؤه هو مشروع "&TEXT([2]المدخلات!P4,0)&" "&"على قطعة أرض رقم "&" "&TEXT([2]المدخلات!AR4,0)&" "&"في منطقة"&" "&TEXT([2]المدخلات!AR3,0) -> 1 – المطلوب إنشاؤه هو مشروع فيلا ارضي اول مع تعديل واجهة الملحق على قطعة أرض رقم 412030315 في منطقة مدينة خليفة بن زايد
A67: 2 – يتم تنفيذ جميع الأعمال طبقاً للرسومات والمواصفات المعدة لهذا الغرض من قبل الاستشاري، وكل ماورد في الرسومات أو المواصفات يعتبر مطلوباً من المقاول، وهو جزءاً لايتجزأ من العقد. 3 – على المقاول اتخاذ جميع الاحتياطات اللازمة فيما يتعلق باستخدام الطرق وتوفير عوامل السلامة العامة، ومراعاة أنظمة وتعليمات ومتطلبات الجهات الرسمية المعنية فيما يتعلق بذلك.
A71: 3.1.1- تدقيـق الأعمــال :
A72: على المقاول إعلام الاستشاري مسبقاً والتنسيق معه لأي عمل و/أو جزء من العمل يحتاج إلى تدقيق من الاستشاري قبل المباشرة بتنفيذ ما يتبعه من أعمال على أن يتم إعلام الاستشاري بذلك قبل (24) ساعة على الأقل من الموعد المفترض لتدقيق ذلك العمل.
A76: 4.1.1- الرسومات التنفيذية :
A77: 1 – على المقاول إعداد رسومات تنفيذية مفصلة حيثما ورد ذلك في المواصفات الخاصة لأي عمل من الأعمال، واعتماد تلك الرسومات من الاستشاري أولاً ومن الجهات الرسمية المعنية ( حيث يلزم ذلك ) خطيـاً قبل البدء في التنفيذ، ويتحمل المقاول مسؤولية أية أعمال و/أو مواد يقوم بتوريدها أو تركيبها قبل اعتماد تلك الرسومات. 2 – على المقاول تقديم ثلاث نسخ من الرسومات التنفيذية/الرسومات التنفيذية المعدلة للأعمال كما تم تنفيذها على أرض الواقـع (As Built Drawings) قبل موعد الاستلام الابتدائي للمشروع.
A83: 5.1.1- الخدمات القائمة :
A84: على المقاول المحافظة على سلامة الخدمات الموجودة داخل وحول الموقع والتي لاتقع ضمن دائرة الأعمال المطلوبة منه، ويتحمل المقاول المسؤولية والتكاليف المترتبة، عند الإخلال بذلك، لإعادة الوضع إلى ما كان عليه لتلك الخدمات واستبدال التالف منها بمثله دون المطالبة بأي تعويض نظير ذلك ( والتنسيق مع الجهات المعنية فيما يتعلق بتحويل تلك الخدمات )، بما يشمل وضع الطريق والأرصفة المحيطة.
A90: 5.1.1- الخدمات القائمة :
A91: على المقاول المحافظة على سلامة الخدمات الموجودة داخل وحول الموقع والتي لاتقع ضمن دائرة الأعمال المطلوبة منه، ويتحمل المقاول المسؤولية والتكاليف المترتبة، عند الإخلال بذلك، لإعادة الوضع إلى ما كان عليه لتلك الخدمات واستبدال التالف منها بمثله دون المطالبة بأي تعويض نظير ذلك ( والتنسيق مع الجهات المعنية فيما يتعلق بتحويل تلك الخدمات )، بما يشمل وضع الطريق والأرصفة المحيطة.
A96: 2.1-إدارة وتنظيم موقع العمل:
A97: 1.2.1- الكادر الفني وموظفو المقاول:
A98: على المقاول تزويد الموقع بالكوادر الفنية والعمالة اللازمة لتنفيذ المشروع بالمستوى المطلوب مع مراعاة مايلي : 1 – جميع عناصر الكادر الفني والعمالة الفنية يجب أن يكونوا من المؤهلين ومن ذوي الخبرة والكفاءة كلاً حسب اختصاصه وحسب متطلبات العمل والتنفيذ ( من حيث العدد والتوزيع ). 2- يتم اعتماد الكوادر الفنية من قبل الاستشاري قبل مباشرتهم للعمل، ويجب أن تكون الكوادر الفنية من ذوي الخبرة بأعمال مماثلة. 3 – يحق للإستشاري الطلب من المقاول إبعاد/استبدال أي شخص مستخدم من قبله إذا رأى الاستشاري أن ذلك الشخص ليس بالمستوى المطلوب من حيث السلوك أو الخبرة لتنفيذ الأعمال. 4 – على المقاول تقديم جدول بأعداد العمالة العادية والفنية العاملة في الموقع بشكل أسبوعي. 5 – يشتمل الكادر الفني (المطلوب من المقاول توفيره كحد أدنى) على : • مدير للمشروع. • مهندس موقع ( Site Engineer )مسؤول عن تنفيذ المشروع للتعامل مع الاستشاري • مراقب فني (Forman) لكل نوع من أنواع الأعمال. • أي كوادر فنية أخرى يطلبها الاستشاري ويرى أنها لازمة لتنفيذ المشروع بالمستوى المطلوب. • مقاول باطن اعمال الالكتروميكانيك يجب ان يكون معتمد من الاستشاري و الـ FEWA.
... A273: وعليه تم التوقيع والإتفاق
A275: المالك | S275: الاستشاري | AL275: المقاول
A276: =المدخلات!$P$3 -> احمد ابراهيم النعيمي | S276: سافانا ديزاين للاستشارات الهندسية | AL276: =المدخلات!$AR$3 -> 0

Sheet المواصفات الفنية2
A10: المواصفات الفنية والشروط العامة
A16: ="لمشروع :"&" "&TEXT(المدخلات!P4,0) -> لمشروع : فيلا دور أرضي و اول وسور
A18: ="عائدة للمالك : السيد /"&" "&TEXT(المدخلات!P3,0) -> عائدة للمالك : السيد / احمد ابراهيم النعيمي
A20: ="والكائن في إمارة"&" "&TEXT(المدخلات!AR6,0)&" في منطقة "&TEXT(المدخلات!AR3,0)&" "&"على القسيمة رقم"&" "&TEXT(المدخلات!AR4,0) -> والكائن في إمارة 0 في منطقة 0 على القسيمة رقم 0
A34: فهرس دفتر الشروط الفنية الخاصة
A36: ( 1 ) المتطلبات العامة وأعمال تحضير الموقع
A37: ( 2 ) أعمال الحفر والرودبيس
A38: ( 3 ) أعمال الخرسانات
A39: ( 4 ) أعمال الطابوق
A40: ( 5 ) أعمال البلاستر
A41: ( 6 ) أعمال العزل
A42: ( 7 ) الأعمال الصحية
A43: ( 8 ) الأعمال الكهربائية
A44: ( 9 ) أعمال الهاندريل والألمنيوم والزجاج
A45: ( 10 ) جدول تشطيبات الأعمال الصحية
A46: ( 11 ) جدول تشطيبات الأعمال الكهربائية
... A65: 2.1.1- المشروع والموقع :
A66: ="1 – المطلوب إنشاؤه هو مشروع "&TEXT(المدخلات!P4,0)&" "&"على قطعة أرض رقم "&" "&TEXT(المدخلات!AR4,0)&" "&"في منطقة"&" "&TEXT(المدخلات!AR3,0) -> 1 – المطلوب إنشاؤه هو مشروع فيلا دور أرضي و اول وسور على قطعة أرض رقم 0 في منطقة 0
A67: 2 – يتم تنفيذ جميع الأعمال طبقاً للرسومات والمواصفات المعدة لهذا الغرض من قبل الاستشاري، وكل ماورد في الرسومات أو المواصفات يعتبر مطلوباً من المقاول، وهو جزءاً لايتجزأ من العقد. 3 – على المقاول اتخاذ جميع الاحتياطات اللازمة فيما يتعلق باستخدام الطرق وتوفير عوامل السلامة العامة، ومراعاة أنظمة وتعليمات ومتطلبات الجهات الرسمية المعنية فيما يتعلق بذلك.
A71: 3.1.1- تدقيـق الأعمــال :
A72: على المقاول إعلام الاستشاري مسبقاً والتنسيق معه لأي عمل و/أو جزء من العمل يحتاج إلى تدقيق من الاستشاري قبل المباشرة بتنفيذ ما يتبعه من أعمال على أن يتم إعلام الاستشاري بذلك قبل (24) ساعة على الأقل من الموعد المفترض لتدقيق ذلك العمل.
A76: 4.1.1- الرسومات التنفيذية :
A77: 1 – على المقاول إعداد رسومات تنفيذية مفصلة حيثما ورد ذلك في المواصفات الخاصة لأي عمل من الأعمال، واعتماد تلك الرسومات من الاستشاري أولاً ومن الجهات الرسمية المعنية ( حيث يلزم ذلك ) خطيـاً قبل البدء في التنفيذ، ويتحمل المقاول مسؤولية أية أعمال و/أو مواد يقوم بتوريدها أو تركيبها قبل اعتماد تلك الرسومات. 2 – على المقاول تقديم ثلاث نسخ من الرسومات التنفيذية/الرسومات التنفيذية المعدلة للأعمال كما تم تنفيذها على أرض الواقـع (As Built Drawings) قبل موعد الاستلام الابتدائي للمشروع.
A83: 5.1.1- الخدمات القائمة :
A84: على المقاول المحافظة على سلامة الخدمات الموجودة داخل وحول الموقع والتي لاتقع ضمن دائرة الأعمال المطلوبة منه، ويتحمل المقاول المسؤولية والتكاليف المترتبة، عند الإخلال بذلك، لإعادة الوضع إلى ما كان عليه لتلك الخدمات واستبدال التالف منها بمثله دون المطالبة بأي تعويض نظير ذلك ( والتنسيق مع الجهات المعنية فيما يتعلق بتحويل تلك الخدمات )، بما يشمل وضع الطريق والأرصفة المحيطة.
A90: 5.1.1- الخدمات القائمة :
A91: على المقاول المحافظة على سلامة الخدمات الموجودة داخل وحول الموقع والتي لاتقع ضمن دائرة الأعمال المطلوبة منه، ويتحمل المقاول المسؤولية والتكاليف المترتبة، عند الإخلال بذلك، لإعادة الوضع إلى ما كان عليه لتلك الخدمات واستبدال التالف منها بمثله دون المطالبة بأي تعويض نظير ذلك ( والتنسيق مع الجهات المعنية فيما يتعلق بتحويل تلك الخدمات )، بما يشمل وضع الطريق والأرصفة المحيطة.
A96: 2.1-إدارة وتنظيم موقع العمل:
A97: 1.2.1- الكادر الفني وموظفو المقاول:
A98: على المقاول تزويد الموقع بالكوادر الفنية والعمالة اللازمة لتنفيذ المشروع بالمستوى المطلوب مع مراعاة مايلي : 1 – جميع عناصر الكادر الفني والعمالة الفنية يجب أن يكونوا من المؤهلين ومن ذوي الخبرة والكفاءة كلاً حسب اختصاصه وحسب متطلبات العمل والتنفيذ ( من حيث العدد والتوزيع ). 2- يتم اعتماد الكوادر الفنية من قبل الاستشاري قبل مباشرتهم للعمل، ويجب أن تكون الكوادر الفنية من ذوي الخبرة بأعمال مماثلة. 3 – يحق للإستشاري الطلب من المقاول إبعاد/استبدال أي شخص مستخدم من قبله إذا رأى الاستشاري أن ذلك الشخص ليس بالمستوى المطلوب من حيث السلوك أو الخبرة لتنفيذ الأعمال. 4 – على المقاول تقديم جدول بأعداد العمالة العادية والفنية العاملة في الموقع بشكل أسبوعي. 5 – يشتمل الكادر الفني (المطلوب من المقاول توفيره كحد أدنى) على : • مدير للمشروع. • مهندس موقع ( Site Engineer )مسؤول عن تنفيذ المشروع للتعامل مع الاستشاري • مراقب فني (Forman) لكل نوع من أنواع الأعمال. • أي كوادر فنية أخرى يطلبها الاستشاري ويرى أنها لازمة لتنفيذ المشروع بالمستوى المطلوب. • مقاول باطن اعمال الالكتروميكانيك يجب ان يكون معتمد من الاستشاري و الـ FEWA.
... A273: وعليه تم التوقيع والإتفاق
A275: المالك | S275: الاستشاري | AL275: المقاول
A276: =المدخلات!P3 -> احمد ابراهيم النعيمي | S276: سافانا ديزاين للاستشارات الهندسية | AL276: =المدخلات!$AR$10 -> 0

Sheet عقد جديد 
A1: عقد الاتفاق Agreement
A3: بإشرافنا نحن
A4: سافانا ديزاين للإستشارات الهندسية والتصميم الداخلي- رأس الخيمة
A6: مكتب 407 أبراج جلفار رأس الخيمة
A7: 525015080
A9: تم الاتفاق بين كل من
A10: الطرف الاول | B10: المالك | D10: =المدخلات!$P$3 -> احمد ابراهيم النعيمي
A11: الطرف الثاني | B11: =المدخلات!AD10 -> 0 | D11: =المدخلات!$AR$10 -> 0
A12: الطرف الثالث | B12: ( الاستشاري) | D12: سافانا ديزاين للاستشارات الهندسية
A14: المشروع
A15: وصف المشروع | D15: =المدخلات!$P$4 -> فيلا دور أرضي و اول وسور
A16: المنطقة | D16: =المدخلات!$AR$3 -> 0
A17: رقم القسيمة | D17: =المدخلات!AR4 -> 0
A19: ='[3]حساب الكميات'!AO270 -> سعر الفيلا مع السور(بدون الضريبة)
A21: يقوم الطرف الثاني بتنفيذ وانشاء وانجاز وصيانة المشروع المذكور اعلاه لقاء مبلغ وقدره
A22: اماراتي فقط بدون الضريبة مليون و مئة و ثمانون الف درهم
A23: و ذلك حسب المتفق عليه والمعتمد وفق للمناقصة التي جرت
A25: توقيع وختم المقاول | D25: توقيع وختم المالك | G25: توقيع وختم الاستشاري
A32: بنود العقد
A34: كافة مستندات المشروع و جميع متعلقاته متكاملة فيما بينها و تشمل المشروع ككل أي بحال عدم ذكر اي بند بالمواصفات او المخططات وتم ذكره بجدول الكميات او المخططات المعتمدة أو اي مستند اخر غير ذلك , والعكس صحيح على المقاول الالتزام به و العمل على تضمينه بأعمال المشروع اينما ذكر .علي المقاول ارجاع العقد موقع علي كل صفحة والمواصافات و المخططات وتوقيعه عليها يعتبر انه اطلع علي جميع تفاصيل المشروع
A36: 1 | B36: الاطلاع علي جميع مخططات المشروع | I36: =A36 -> 1
A37: على المقاول قبل توقيع العقد الاطلاع على المخططات و المواصفات و الشروط و التأكد من تطابق جميع المخططات الانشائية والمعمارية والخدمات و المناظير 3D وتنبيه الاستشاري لأي اختلاف في تطابق المخططات وذلك لتفادي التغيير و التعديل في الموقع قبل التنفيذ و في حالة عدم تنبيه الاستشاري بوجود اختلاف قبل الشروع في العمل يتحمل المقاول كامل المسؤولية في التعديلات المطلوبة و التاخير المترتب عن ذلك و اعتبار أن توقيعه عليها يعني موافقته على جميع ما ورد بها وتعتبر المناظير المقدمة من الاستشاري في ملف المناقصة هي المعتمدة من ناحية الشكل و التشطيبات في حال اختلاف مع المخططات المعتمدة .
B38: إصدار التعليمات, الرسوم | D38: إصدار التعليمات, الرسوم
A39: لا يحق للمالك اصدار اي تعليمات للمقاول تتعلق بتنفيذ المشروع الا عن طريق الاستشاري
A40: 2 | B40: مقاولي الباطن | G40: 2 | I40: =A40 -> 2
A41: يجوز للطرف الثاني اسناد جزء من الاعمال الى مقاولي الباطن المعتمدين والمسجلين لدى البلدية بموجب موافقة خطية من الاستشاري
A42: يكون المقاول مسؤول مسؤولية كاملة عن اعمال المقاول الباطن من حيث الجودة والتنفيذ واصول الصناعه والضمانات
A43: يتعهد الطرف الثاني بالتنسيق بين جميع المقاولين الباطن دون اي استثناء ودون اي احقية في المطالبة باي مبلغ اضافة نظير ذلك.
A45: 3 | B45: فسخ التعاقد | G45: 3 | I45: =A45 -> 3
A46: يحق للمهندس الاستشاري فسخ العقد في الحالات
A47: اذا تاخر المقاول عن بدء الاعمال بعد تسليم الموقع
A48: اذا تاخر المقاول في اتمام العمل وتسليمه في المواعيد المحدده لكل مرحلة في الجدول الزمني المعتمد
A49: اذا اظهر المقاول بطئا في سير العمل لدرجة يرى الاستشاري منها عدم قدرة الطرف الثاني على اتمام العمل في موعده على ان يقوم الاستشاري بتنبيه المقاول خطيا .
A50: اذا اخل المقاول ببرنامج العمل المحدد بشكل يؤثر على مستوى التنفيذ او الاخلال بالمواصفات المتفق عليها
A51: اذا انسحب المقاول عن العمل او تركه او افلس
A52: اذا اسند الطرف الثاني العمل لمقاول باطن دون اخطار الاستشاري
A53: في حال تاخير الطرف الاول عن سداد اي من مستحقات الطرف الثاني في موعد اقصاه 30 يوم فمن حق الطرف الثاني التوقف عن العمل وذلك بعد اخطار الاستشاري خطيا وتحسب فتره التاخير على المالك لصالح المقاول كمدة اضافية للمشروع.
A54: يحق للطرف الثاني الغاء التعاقد في حالة تاخير المالك باختيار التشطيبات مما يعود بالضرر علي المقاول
A55: 4 | B55: الاثار المترتبة على فسخ العقد | G55: 4 | I55: =A55 -> 4
A56: حساب غرامة التاخير على الطرف الثاني طبقا للعقد حتى تاريخ ابلاغ المقاول بقرار السحب.
A57: يتم تنفيذ الاعمال المتبقية كلها او بعضها على حساب المقاول على ان تطرح الاعمال المتبقية في مناقصة جديدة او يعهد بتنفيذها الى احد المقاولين بطريق الممارسة مع تحميل المقاول النتائج المترتبة عن هذا الاجراء
A58: حجز اي دفعات متبقيىة للمقاول وحجز الضمانات البنكية ومحجوزات الصيانة لحين الانتهاء من المشروع (تمويل خاص فقط).
A59: 5 | B59: حل النزاع | G59: =A59 -> 5 | I59: =A59 -> 5
A60: اي نزاع ينشا عن تطبيق احكام هذا العقد يكون الفصل فيه اختصاص محكم يتفق عليه الطرفان او ترشحة الجهات والدوائر المختصه.
A66: 6 | B66: محجوزات الصيانة | G66: =A66 -> 6 | I66: =A66 -> 6
A67: يستقطع 5% من قيمة الاعمال المنفذه بالدفعات الجارية او التي يتم صرفها بمعرفة المقرض كمحجوز صيانة وذلك ضمانا لحسن تنفيذ الاعمال وبعد الاستلام الابتدائي وحصر الاعمال نهائيا يتم صرف المستحقات الختامية للاعمال بعد استقطاع ما على المقاول من التزامات وما سبق صرفه كدفعات ويصرف له الباقي بعد حجز محجوز الصيانة من قيمة الاعمال المنفذة لمدة سنة من تاريخ الاستلام الابتدائي (تمويل خاص فقط) .
A68: 7 | B68: الإستلام الابتدائي للمشروع | G68: =A68 -> 7 | I68: =A68 -> 7
A69: يجب على المقاول اخطار الاستشاري باليوم الذي يتم فيه انهاء الاعمال على ان يكون هذا الاخطار قبل حلول هذا اليوم باسبوع على الاقل ليتم اخطار المالك والمقاول بموجب الاستلام الابتدائي يتم بحضور المقاول او مهندسه. وفي حاله عدم حضوره يقوم الاستشاري بعمله في غيابه فاذا ثبت ان الاعمال في حاله تسمح باستلامها يتم تحرير محضرا باستلام الاعمال استلاما مبدئيا في ذات اليوم, اما اذا ثبت عكس ذلك فللاستشاري الحق في عمل محضر اثبات حاله, وفي جميع الاحوال تكون المحاضر التي يحررها الاستشاري حجة على المقاول ولو لم يحضر او يوقع على المحضر ، لا يقوم الاستشاري باعادة المعاينة الا اذا اخطره المقاول بموعد انهاء الاعمال وقبل اسبوع من الحلول على الاقل وفي حال وجود ملاحظات على اعمال المشروع لا تمنع من الاستلاام الابتدائي يتم استلام المشروع ويعطى المقاول سبعه ايام لانهاء تلك الملاحظات وفي حال عدم انتهائه من هذه الملاحظات يعتبر محضر الاستلام الابتدائي لاغيا.
A70: 8 | B70: الاشراف الهندسي من قبل الاستشاري | G70: =A70 -> 8 | I70: =A70 -> 8
A71: يتم دفع رسوم شهرية مقابل الاشراف (700) درهم بدون الضريبة وذلك يتضمن الزيارات الاسبوعية والمتابعة بشكل عام في حال تجاوزت مدة انتهاء المشروع على المدة المتفق عليها , يتم دفع رسوم الاشراف من قبل الطرف المتسبب في التأخير ( المالك او المقاول ) في حال كان الطرفين متسببين في التأخير ف يتم دفع الرسوم المتبقية لأشراف مناصفة بين المالك والمقاول.
A72: يحق للإستشاري إيقاف المقاول عن العمل في حالة عدم التقيد بتعليمات الإستشاري ويسري هذا على المقاولين الذين يحضرهم المقاول الرئيسي أو المالك
A73: الطرف الثالث غير مسؤول إذا لم ينجز المشروع بالكامل خلال مدة التنفيذ المتعاقد عليها بين الطرف الاول والمقاول.
A74: في حال طلب المالك ايقاف الاشراف على المشروع وفسخ العقد بعد انتهاء مدة التنفيذ وقبل ان ينتهي انجاز المشروع بالكامل يجب ان يكون هذا الطلب خطيا قبل شهر على الاقل من انتهاء مدة التنفيذ وبعد موافقة الطرف الثالث فانه يحق للاستشاري تحصيل اتعاب اشراف ثلاثة اشهر اضافية على مدة العقد حسب ما هو مذكور في المادة السادسة عشر من هذا العقد وذلك كتعويض عن الضرر الذي يلحق بالاستشاري نتيجة فسخ العقد واخلاء الطرف.
A75: في حال طلب المالك إيقاف الاشراف خلال مدة التنفيذ دون مبرر فانه من حق الاستشاري تحصيل اتعابه كاملة حسب ما هو مذكور في هذا العقد قبل اخلاء الطرف وانهاء مهمة الاستشاري وبشرط الا يترتب على هذا الطلب اي ضرر على الطرف الثاني.
A76: الاستشاري غير ملزم بالاشراف على أي أعمال خارج التصميم المعماري والإنشائي (التكيف الديكور - المسابح -المصاعد- الحديقة).
A77: 9 | B77: الإستلام النهائي للمشروع | G77: =A77 -> 9 | I77: =A77 -> 9
A78: بعد انتهاء فترة ضمان الصيانة المحددة في العقد, يصدر الاستشاري شهادة الاستلام النهائي بعد معاينة المشروع شريطة ان يكون المقاول قد قام بكل ما يترتب عليه من التزامات خلال فترة الصيانة حيث لا يوجد اي عيوب في المشروع تمنع من اصدار هذه الشهادة من اجل صرف محجوز الضمان وقدره (5%) من قيمة العقد الاجمالية .ويلتزم المقاول بدفع مبلغ 2500 درهم كاتعاب للاستشاري نظير ذلك.
A79: 10 | B79: مدة الصيانة | G79: =A79 -> 10 | I79: =A79 -> 10
A80: علي المقاول متابعة ملاحظات المالك والاستشاري و صيانتها بعد الاستلام الابتدائي وحتي الاستلام النهائي للمشروع و في حال عدم تجاوب المقاول يحق للمالك عدم التوقيع على التسليم النهائي حتي تتم معالجة جميع الملاحظات . الطرف الثاني مسؤولا عن سلامة الهيكل الخرساني للمبنى المذكور اعلاه لمدة 10 سنوات (عشر سنوات) من تاريخ الاستلام الابتدائي.
A81: 11 | B81: الصيانة | G81: =A81 -> 11 | I81: =A81 -> 11
A82: تبدا اعمال الصيانة للمشروع لمدة عام كامل بعد تاريخ الاستلام الابتدائي للمشروع مباشرة.
A83: 12 | B83: انسحاب المقاول بدون سبب | G83: =A83 -> 12 | I83: =A83 -> 12
A84: اذا انسحب المقاول من العمل بالمشروع بدون سبب مقبول من الاستشاري يقوم بدفع ما قيمته 10% من العقد لصالح المالك ودفع رسوم رسو العطاء وارساء المناقصة ونسبتها (4%) من قيمة اجمالي عقد المقاولة كاملا.
A86: 13 | B86: امتناع المالك التسليم الابتدائي | G86: =A86 -> 13 | I86: =A86 -> 13
A87: في حالة امتناع المالك عن التوقيع على محضر الاستلام الابتدائي او النهائي سيتم اخطاره بضرورة بيان السبب خلال خمسة عشر يوما من تاريخ اخطاره، فان انتهت هذه المهلة دون بيان اسباب امتناعه او ان الاسباب التي ابداها غير مقنعه من وجهة نظر الاستشاري، فانه يجوز للاستشاري استلام المبنى وتسليم المقاول كافة مستحقاته ويعتبر المبنى في حوزة المالك وتحت مسؤوليته من تاريخ الاستلام.
A88: 14 | B88: فسخ عقد الاستشاري | G88: =A88 -> 14 | I88: =A88 -> 14
A89: في حالة رغبة المالك في فسخ العقد مع الاستشاري بعد اعتماد المخطط لدى البلدية فعليه دفع 2% من قيمة المشروع للاستشاري كتعويض وضياع فرصة و نظير اتعابه.
A90: 15 | B90: اتعاب الاستشاري | G90: =A90 -> 15 | I90: =A90 -> 15
A91: يلتزم الطرف الثاني دفع نسبة من قيمة عقد المقاولة كاملا مقابل المخططات المعتمدة و المناقصة كذلك الامر عن أي اعمال اضافية التي تضاف الى العقد لاحقا .
A92: 16 | B92: التاخير عن مراحل الجدول الزمني | G92: =A92 -> 16 | I92: =A92 -> 16
A93: الطرف الثاني ملزم بتقديم جدول زمني قبل توقيع العقد ويتم اعتماده من الطرف الثالث فقط ويتم تطبيق غرامة 2000 درهم للمالك ) في حال تأخر المقاول عن انجاز كل مرحلة على حدى في الجدول الزمني و دون سبب مقنع للتاخير.
A94: 17 | B94: توريد مواد خارجة عن المواصافات | G94: =A94 -> 17 | I94: =A94 -> 17
A95: يتم تغريم الطرف الثاني 2000 درهم ( للمالك ) في حال تم تركيب اي مادة او خامة مخالفة للمواصفات المعتمدة وغير مقبولة من الاستشاري .
A96: 18 | B96: اعتماد الامر التغييري | I96: =A96 -> 18
A97: في حال تم العمل على المخططات المعدلة من غير تقديم الامر التغييري من قبل الطرف الثاني للاستشاري و المالك لاعتماده فإن المقاول يتحمل مسؤوليته بذلك.
A98: على المقاول تزويد الموقع بالكوادر الفنية والعمالة اللازمة لتنفيذ المشروع بالمستوى المطلوب مع مراعاة مايلي : 1 – جميع عناصر الكادر الفني والعمالة الفنية يجب أن يكونوا من المؤهلين ومن ذوي الخبرة والكفاءة كلاً حسب اختصاصه وحسب متطلبات العمل والتنفيذ ( من حيث العدد والتوزيع ). 2- يتم اعتماد الكوادر الفنية من قبل الاستشاري قبل مباشرتهم للعمل، ويجب أن تكون الكوادر الفنية من ذوي الخبرة بأعمال مماثلة. 3 – يحق للإستشاري الطلب من المقاول إبعاد/استبدال أي شخص مستخدم من قبله إذا رأى الاستشاري أن ذلك الشخص ليس بالمستوى المطلوب من حيث السلوك أو الخبرة لتنفيذ الأعمال. 4 – على المقاول تقديم جدول بأعداد العمالة العادية والفنية العاملة في الموقع بشكل أسبوعي. 5 – يشتمل الكادر الفني (المطلوب من المقاول توفيره كحد أدنى) على : • مدير للمشروع. • مهندس موقع ( Site Engineer )مسؤول عن تنفيذ المشروع للتعامل مع الاستشاري • مراقب فني (Forman) لكل نوع من أنواع الأعمال. • أي كوادر فنية أخرى يطلبها الاستشاري ويرى أنها لازمة لتنفيذ المشروع بالمستوى المطلوب. • مقاول باطن اعمال الالكتروميكانيك يجب ان يكون معتمد من الاستشاري و الـ FEWA. | B98: تقرير شهري | G98: =A98 -> على المقاول تزويد الموقع بالكوادر الفنية والعمالة اللازمة لتنفيذ المشروع بالمستوى المطلوب مع مراعاة مايلي : 1 – جميع عناصر الكادر الفني والعمالة الفنية يجب أن يكونوا من المؤهلين ومن ذوي الخبرة والكفاءة كلاً حسب اختصاصه وحسب متطلبات العمل والتنفيذ ( من حيث العدد والتوزيع ). 2- يتم اعتماد الكوادر الفنية من قبل الاستشاري قبل مباشرتهم للعمل، ويجب أن تكون الكوادر الفنية من ذوي الخبرة بأعمال مماثلة. 3 – يحق للإستشاري الطلب من المقاول إبعاد/استبدال أي شخص مستخدم من قبله إذا رأى الاستشاري أن ذلك الشخص ليس بالمستوى المطلوب من حيث السلوك أو الخبرة لتنفيذ الأعمال. 4 – على المقاول تقديم جدول بأعداد العمالة العادية والفنية العاملة في الموقع بشكل أسبوعي. 5 – يشتمل الكادر الفني (المطلوب من المقاول توفيره كحد أدنى) على : • مدير للمشروع. • مهندس موقع ( Site Engineer )مسؤول عن تنفيذ المشروع للتعامل مع الاستشاري • مراقب فني (Forman) لكل نوع من أنواع الأعمال. • أي كوادر فنية أخرى يطلبها الاستشاري ويرى أنها لازمة لتنفيذ المشروع بالمستوى المطلوب. • مقاول باطن اعمال الالكتروميكانيك يجب ان يكون معتمد من الاستشاري و الـ FEWA. | I98: =A98 -> على المقاول تزويد الموقع بالكوادر الفنية والعمالة اللازمة لتنفيذ المشروع بالمستوى المطلوب مع مراعاة مايلي : 1 – جميع عناصر الكادر الفني والعمالة الفنية يجب أن يكونوا من المؤهلين ومن ذوي الخبرة والكفاءة كلاً حسب اختصاصه وحسب متطلبات العمل والتنفيذ ( من حيث العدد والتوزيع ). 2- يتم اعتماد الكوادر الفنية من قبل الاستشاري قبل مباشرتهم للعمل، ويجب أن تكون الكوادر الفنية من ذوي الخبرة بأعمال مماثلة. 3 – يحق للإستشاري الطلب من المقاول إبعاد/استبدال أي شخص مستخدم من قبله إذا رأى الاستشاري أن ذلك الشخص ليس بالمستوى المطلوب من حيث السلوك أو الخبرة لتنفيذ الأعمال. 4 – على المقاول تقديم جدول بأعداد العمالة العادية والفنية العاملة في الموقع بشكل أسبوعي. 5 – يشتمل الكادر الفني (المطلوب من المقاول توفيره كحد أدنى) على : • مدير للمشروع. • مهندس موقع ( Site Engineer )مسؤول عن تنفيذ المشروع للتعامل مع الاستشاري • مراقب فني (Forman) لكل نوع من أنواع الأعمال. • أي كوادر فنية أخرى يطلبها الاستشاري ويرى أنها لازمة لتنفيذ المشروع بالمستوى المطلوب. • مقاول باطن اعمال الالكتروميكانيك يجب ان يكون معتمد من الاستشاري و الـ FEWA.
A99: الطرف الثاني ملزم بتقديم تقرير شهري كتابي عن سير الاعمال في الموقع ويتم تغريمه درهم500 بحالة عدم الالتزام يدفعها للمالك او متابعة و تقرير يومي عن طريق مجموعة الواتساب الخاصة بالمشروع.
A101: 20 | B101: الدفعات الخاصة | G101: =A101 -> 20 | I101: =A101 -> 20
A102: الدفعات الخاصة تتم عن طريق الاستشاري فقط وفي حال تم دفع المالك الدفعة مباشرة للمقاول وبدون علم الاستشاري فإن المالك يتحمل مسؤوليته بذلك .
A103: 21 | B103: تقرير مع كل دفعة خاصة | G103: =A103 -> 21 | I103: =A103 -> 21
A104: يتم تقديم تقرير مفصل من قبل المقاول عند كل دفعة يتم تقديمها ويكون التقرير شامل لكافة الاعمال المنجزة والجارية وموضحة بالصور والتفاصيل اللازمة .
A105: 22 | B105: اختيار مواد التشطيب | G105: =A105 -> 22 | I105: =A105 -> 22
A106: يجب على المالك اختيار المواصفات المتعلقة به تجنبا للتأخير وذلك يتم بالتنسيق مع الاستشاري لكل مرحلة وبند على حدى , في حالة تأخير المالك فان المقاول لا يتحمل أي مسوولية.
A107: 23 | B107: المناقصة | G107: =A107 -> 23 | I107: =A107 -> 23
A108: يتم تقديم المناقصة من قبل المقاول للاستشاري بكامل تفاصيلها من حساب كميات والمخططات و 3D مع ختم وتوقيع على كل ورقة او مخطط يتم تقديمه معرفا بالتاريخ .
A109: 24 | B109: الدفعه الختامية | G109: =A109 -> 24 | I109: =A109 -> 24
A110: لا يتم اعتماد الدفعه الختامية وصرفها للمقاول الا بعد استيفاء الاتي:
A111: رخصة البناء الاصلية.
A112: مفاتيح المبنى الداخلية والخارجية.
A113: جدول الأحمال الخاص بتوصيل الكهرباء والماء
A114: عدم ممانعه من البلدية بتوصيل الكهرباء والماء
A115: خطاب ضمان الطبقات العازلة لمدة 10 سنوات
A116: خطاب ضمان اعمال الدهانات لمدة 3 سنوات
A117: خطاب ضمان خزانات المياه لمدة 3 سنوات
A118: خطاب ضمان الاجهزة (سخانات + مراوح شفط + المضخات) (اذا كانت من ضمن الأعمال المشمولة بعقده)
A121: 25 | B121: الالتزام بدفع الضريبة | G121: =A121 -> 25 | I121: =A121 -> 25
A122: يلتزم كل الأطراف المساهمون في هذا المشروع بمتطلبات المرسوم بقانون اتحادي رقم (08) لسنة 2018 .ولائحته التنفيذية المعلنة و اللذان ينظمان ضريبة القيمة المضافة ( VAT ) و تطبيقها في دولة الامارات حيث تحتسب نسبة 5% يلتزم المالك بسداد هذة النسبه للمقاول والاستشاري مع كل دفعة مستحقة .
A123: 26 | B123: شيك الضمان | G123: =A123 -> 26 | I123: =A123 -> 26
A124: على المقاول تحرير شيك ضمان باسم المالك بقيمة الدفعة الاولى يسلم لدى الاستشاري و يحفظ عند الاستشاري حتي التسليم الابتدائي .
A125: 27 | B125: مدة التنفيذ | G125: =A125 -> 27 | I125: =A125 -> 27
...

Sheet اتفاق  (2)
B1: عقد اتفاق بين المالك و الاستشاري
B2: انه في يوم | F2: =المدخلات!$P$8 -> الاريعاء | K2: بتاريخ | N2: =المدخلات!$P$7 -> 0 | U2: حرر بين كل من:
B4: • | C4: ="الطرف الأول السيد:"&" "&TEXT(المدخلات!P3,0)&" "&"مالك المشروع,قسيمة رقم :"&TEXT(المدخلات!AR4,0)&" منطقة "&TEXT(المدخلات!AR3,0)&" بإمارة رأس الخيمة" -> الطرف الأول السيد: احمد ابراهيم النعيمي مالك المشروع,قسيمة رقم :0 منطقة 0 بإمارة رأس الخيمة
B5: • | C5: الطرف الثاني: شركة سافانا ديزاين للاستشارات الهندسية والتصميم الداخلي، رخصة رقم(48818)، وعنوانها مكتب رقم (407) بأبراج جلفار، في إمارة رأس الخيمة ، ويمثلها المدير / المهندس أيمن بن حمادي، وبعد أن أقر المتعاقدان بأهليتهما للتصرف والتعاقد اتفقا على ما يأتي:
B8: 1 | C8: قبل الطرف الثاني بموجب هذا العقد أن يقوم بأعمال التصميم الهندسي والإشراف عل مشروع الفيلا الخاصة بالطرف الأول، الوارد بياناتها في مقدمة هذا العقد، وذلك حسب المعايير والمواصفات المحددة من قبل الجهات المختصة.
B10: 2 | C10: ="يلتزم الطرف الأول بدفع مبلغ وقدره "&" "&TEXT(المدخلات!P9,0)&" "&"درهم غير شامل الضريبة, للطرف الثاني مقابل أعمال التصاميم" -> يلتزم الطرف الأول بدفع مبلغ وقدره 0 درهم غير شامل الضريبة, للطرف الثاني مقابل أعمال التصاميم
B11: 3 | C11: يلتزم الطرف الأول بدفع كافة رسوم الجهات الحكومية أو الخاصة، والمطلوبة لفتح معاملات اعتماد المخططات والرسومات الهندسية، أو التعديل عليها.
B13: 4 | C13: لا يتحمل الطرف الثاني أي تأخير حاصل من قبل أي جهات أخرى، وتكون حدود مسؤوليته في العمل المنوط به فقط .
B14: 5 | C14: يقر الطرف الأول بأن كل الأفكار و المخططات والتصاميم المقدمة من الطرف الثاني تعتبر حق من حقوق ملكيته الفكرية، ولا يمكن نقلها لأي جهة مهما كانت أو التنازل عنها إلا بكتاب خطي موقع ومختوم من الطرف الثاني.
B16: 6 | C16: أي مبالغ مدفوعة في أي مرحلة من مراحل تصميم المشروع والإشراف عليه، تكون نظير للأفكار والجهد والوقت والخدمة المقدمة من قبل الطرف الثاني، ولا يعطي الحق للطرف الأول في المطالبة باسترجاع تلك المبالغ في حال عدم إكماله للمشروع.
B18: 7 | C18: يستحق الطرف الثاني نسبة من القيمة الإجمالية لعقد المقاولة ، يدفعه مقاول المشروع، أو الطرف الأول.
B19: 8 | C19: ="يلتزم الطرف الأول بدفع مبلغ مقابل إشراف الطرف الثاني على تنفيذ المشروع، وتدفع كمبلغ مقطوع و على دفعات ثابتة قيمتها" &" "&TEXT(المدخلات!P10,0)&"درهم،غير شامل الضريبة وتكون مستحقة بداية كل شهر ميلادي من بداية تنفيذ المشروع وحتى الانتهاء من إنجازه." -> يلتزم الطرف الأول بدفع مبلغ مقابل إشراف الطرف الثاني على تنفيذ المشروع، وتدفع كمبلغ مقطوع و على دفعات ثابتة قيمتها 0درهم،غير شامل الضريبة وتكون مستحقة بداية كل شهر ميلادي من بداية تنفيذ المشروع وحتى الانتهاء من إنجازه.
B22: 9 | C22: يلتزم الطرف الثاني بأن تكون الزيارات الإشرافية بمعدل أربع زيارات في الشهر تحسب بمعدل إجمالي طيلة فترة تنفيذ المشروع، وحسب ما يقتضيه تقدم الأشغال في الموقع، كما يقر الطرف الثاني أنه في حال توقف الأشغال لمدة ثلاثة أشهر أو أكثر لأي سبب كان، فأنه لا يحق له مطالبة الطرف الأول بدفع مبلغ الإشراف في فترة التوقف.
B24: 10 | C24: اذا وجد عائق من عوائق الارض ( ديفان , كابل كهرباء , تعديل تحت المنسوب….) فالطرف الاول من يتحمل تسوية الموضوع.
B25: 11 | C25: يلتزم المالك بدفع رسوم إضافية يحددها الاستشاري فب حال طلب المالك أي تعديل علي المخططات بعد البدء بتجهيز المخططات التنفيذية لاعتمادها من الجهات الحكومبة و ينطبق ذلك علي أي تعديلات لاحقة
B26: 12 | C26: يلتزم المالك بدفع رسوم معاملة ادخال الكهرباء و معاملة الإنجاز في اخر المشروع
B27: 13 | C27: يحق للطرف الثاني (الاستشاري) نشر صور وفيديوات للمشروع
B28: 14 | C28: يحق للطرف الأول تغيير الطرف الثاني (الاستشاري) أثناء تنفيذ مشروع البناء، وليس قبل ذلك بأي حال من الأحوال ،و في حال الطرف الاول قرر عدم مواصلة المشروع قبل مرحلة التنفيذ يلتزم بدفع باقي المبالغ المستحقة و يكون المبلغ المدفوع في البند 2 نظير اعمال التصاميم المبدئية فقط مع الاحتفاظ بحقوق التصميم.
A32: يقر الطرفان على اطلاعهما وموافقتهما على كل ما ورد في هذا العقد وعليه يوقعان
A35: المالك | Z35: الاستشاري
A36: =المدخلات!$P$3 -> احمد ابراهيم النعيمي | Z36: سافانا ديزاين للاستشارات الهندسية والتصميم الداخلي

Sheet حساب الكميات (2)
B2: حساب كميات المشروع
B3: معلومات المشروع
B4: المالك | K4: =المدخلات!$P$3 -> احمد ابراهيم النعيمي | AD4: المنطقة | AQ4: =المدخلات!$AR$3 -> 0
B5: وصف المشروع | K5: =المدخلات!$P$4 -> فيلا دور أرضي و اول وسور | AD5: رقم القسيمة | AQ5: =المدخلات!$AR$4 -> 0
B6: مساحة السور م.طولي | K6: =المدخلات!AR5 -> 118 | AD6: مساحة البناء بالقدم المربع | AQ6: =المدخلات!$AY$5 -> 5549
B7: #VALUE!
B24: بيانات المقاول
B25: اسم الشركة | F25: Contra name | K25: العزة لمقاولات البناء | AD25: المهندس | AI25: Engineer
B26: تاريخ | E26: Date | AD26: رقم الهاتف: | AI26: Phone No
B27: License number | AD27: مدة تنفيذ | AI27: Construction period | AQ27: =المدخلات!$AR$9 -> 14 شهر
B29: عرض السعر / Price OFFER | AQ29: ختم الشركة العارضة / Contractor Stamp
B30: تكلفة انشاء وانجاز الفيلا | P30: Total villa cost | AD30: =AO236 -> #VALUE! | AQ30: =المدخلات!AR10 -> 0
B31: تكلفة انشاء وإنجاز السور | P31: Total Boundary wall cost | AD31: =AY231 -> 0
B32: تكلفة انشاء وإنجاز الفيلا مع السور | P32: Total Villa and Boundary wall | AD32: =AD30+AD31 -> #VALUE!
B33: الضريبة | P33: VAT | AD33: =AD32*0.05 -> #VALUE!
B34: القيمة الاجمالية للمشروع شامل الضريبة | P34: Total project value with Vat | AD34: =AD32+AD33 -> #VALUE!
B36: السعر المقدم بعد دراسة جميع بنود العقد والمواصفات ومطابقة جميع المخططات ومناظير ال 3D والموافقة عليها | AI36: The prices should include all contract activities m specification , confirming all drawings with project 3d
B37: حساب الكميات يجب ان يكون دقيق وان لا تتعدا الكميات 5% | AI37: Bill of Quantities should be accurate and not pass 5%
B38: علي المقاول الاستفسار من الاستشاري عن كل بند لم يكن واضحا في المناقصة . | AI38: contractor should send queries to consultant for any item not clear in the tender
B40: أولا : اعـــــمـــــــــال الـــــهــــيكــــــل | C40: أولا : أعمال الهيكل | AI40: english
C41: A | F41: أعمال المياه الجوفية و إحلال التربة وتجهز الموقع
C42: A1 | F42: تجفيف المياه الجوفية | Y42: Dewatering | AO42: L.S | AP42: M2 | AQ42: M2 | AR42: M2 | AS42: 0 | AW42: 2 | BA42: =AW42*AS42 -> 0
C43: A2 | F43: إحلال التربة | Y43: Soil replacement | AO43: L.S | AP43: M2 | AQ43: M2 | AR43: M2 | AS43: 0 | AW43: 2 | BA43: =AW43*AS43 -> 0
C44: A3 | F44: تجهيز الموقع | Y44: Mobilization | AO44: L.S | AP44: M2 | AQ44: M2 | AR44: M2 | AS44: 1 | AW44: 15000 | BA44: =AW44*AS44 -> 15000
C45: المياه الجوفية و إحلال التربة وتجهز الموقع | Y45: dewatering , soil replacement and Mobilization | AO45: =SUM(BA42:BD44) -> 15000
C46: B | F46: أعمال تحت منسوب الأرض | AO46: substructure works
C47: B1 | F47: الحفر | X47: Excavation | AO47: M3 | AP47: M2 | AQ47: M2 | AR47: M2 | AS47: 700 | AW47: 9 | BA47: =AW47*AS47 -> 6300
C48: B2 | F48: الرودبيس | X48: Road base | AO48: M3 | AP48: M2 | AQ48: M2 | AR48: M2 | AS48: 130 | AW48: 30 | BA48: =AW48*AS48 -> 3900
C49: B3 | F49: خرسانة أسفل القواعد | X49: PCC under foundation | AO49: M3 | AP49: M2 | AQ49: M2 | AR49: M2 | AS49: 17 | AW49: 400 | BA49: =AW49*AS49 -> 6800
C50: B4 | F50: خرسانة للقواعد | X50: RCC Foundation | AO50: M3 | AP50: M2 | AQ50: M2 | AR50: M2 | AS50: 93 | AW50: 950 | BA50: =AW50*AS50 -> 88350
C51: B5 | F51: خرسانة مسلحة رقاب أعمدة | X51: Neck Columns | AO51: M3 | AP51: M2 | AQ51: M2 | AR51: M2 | AS51: 3 | AW51: 1300 | BA51: =AW51*AS51 -> 3900
C52: B6 | F52: طابوق مصمت أسفل الجسور الأرضية | X52: Solid block under tie beams | AO52: M2 | AS52: 135 | AW52: 85 | BA52: =AW52*AS52 -> 11475
C53: B7 | F53: الجسور الأرضية | X53: Tie beams | AO53: M3 | AS53: 19 | AW53: 950 | BA53: =AW53*AS53 -> 18050
C54: B8 | F54: عزل تحت منسوب الارض | X54: water proof for substructure | AO54: L.S | AS54: 1 | AW54: 5000 | BA54: =AW54*AS54 -> 5000
C55: B9 | F55: لوحات البولي ايثيلين | X55: Polythene sheet | AO55: L.S | AS55: 1 | AW55: 2500 | BA55: =AW55*AS55 -> 2500
C56: B10 | F56: الدفان والدمك | X56: back filling and compaction | AO56: M3 | AS56: 600 | AW56: 25 | BA56: =AW56*AS56 -> 15000
C57: B11 | F57: الخرسانة الأرضية | X57: Flooring | AO57: M3 | AS57: 27.5 | AW57: 425 | BA57: =AW57*AS57 -> 11687.5
C58: B12 | F58: معالجة النمل الأبيض (مرتين) | X58: Ant termite | AO58: L.S | AS58: 1 | AW58: 1700 | BA58: =AW58*AS58 -> 1700
C59: B13 | F59: غرفة المياه تحت الأرض | X59: Under ground water tank | AO59: L.S | AS59: 1 | AW59: 8000 | BA59: =AW59*AS59 -> 8000
C60: B14 | F60: غرفة استرجاع مياه التكييف تحت الأرض | X60: under ground tank for AC water | AO60: L.S | AS60: 1 | AW60: 8000 | BA60: =AW60*AS60 -> 8000
C61: B15 | F61: بالوعة الصرف الصحي | X61: septic tank | AO61: L.S | AP61: M2 | AQ61: M2 | AR61: M2 | AS61: 1 | AW61: 10000 | BA61: =AW61*AS61 -> 10000
C62: B16 | F62: توريد وتركيب اعمال المناهيل | X62: manhole works | AO62: No | AP62: M2 | AQ62: M2 | AR62: M2 | AS62: 1 | AW62: 5000 | BA62: =AW62*AS62 -> 5000
C63: أعمال تحت منسوب الأرض | X63: substructure works | AO63: GFGJK
C64: C | F64: أعمال فوق منسوب الأرض | AO64: Super Structure
C65: C1 | F65: خرسانة مسلحة للأعمدة الارضي | X65: GF Columns | AO65: M3 | AS65: 18 | AW65: 1300 | BA65: =AW65*AS65 -> 23400
C66: C2 | F66: خرسانة مسلحة للسقف الارضي | X66: GF Slab | AO66: M3 | AS66: 68 | AW66: 1200 | BA66: =AW66*AS66 -> 81600
C67: C3 | F67: خرسانة مسلحة اعمدة الدور الاول | X67: 1st floor Columns | AO67: M3 | AP67: M2 | AQ67: M2 | AR67: M2 | AS67: 16 | AW67: 1350 | BA67: =AW67*AS67 -> 21600
C68: C4 | F68: خرسانة مسلحة للسقف الاول | X68: 1st floor slab | AO68: M3 | AS68: 78 | AW68: 1200 | BA68: =AW68*AS68 -> 93600
C69: C5 | F69: خرسانة الروف | X69: Roof slab | AO69: M3 | AS69: 10 | AW69: 1000 | BA69: =AW69*AS69 -> 10000
C70: C6 | F70: خرسانة مسلحة السلالم الداخلية | X70: RCC for internal stairs | AO70: M3 | AS70: 5 | AW70: 1000 | BA70: =AW70*AS70 -> 5000
C71: C7 | F71: خرسانة مسلحة السلالم الخارجية | X71: RCC for external stairs | AO71: M3 | AS71: 5 | AW71: 1200 | BA71: =AW71*AS71 -> 6000
C72: C8 | F72: خرسانة الأعتاب والأقواس ولنتل | X72: Lintels | AO72: L.M | AS72: 3 | AW72: 1200 | BA72: =AW72*AS72 -> 3600
C73: C9 | F73: خرسانة مسلحة للباربيت | X73: RCC Parapet | AO73: M3 | AS73: 7 | AW73: 1200 | BA73: =AW73*AS73 -> 8400
C74: C10 | F74: خرسانة مسلحة للكورنيش | X74: Concrete for decoration | AO74: M3 | AS74: 0 | AW74: 1000 | BA74: =AW74*AS74 -> 0
C75: أعمال فوق منسوب الأرض | AO75: =SUM(BA65:BD74) -> 253200
C76: D | F76: أعمال الطابوق
C77: D1 | F77: طابوق خالي 25 صم | X77: Hollow Block 25cm | AO77: M2 | AP77: M2 | AQ77: M2 | AR77: M2 | AS77: 0 | AW77: 0 | BA77: =AW77*AS77 -> 0
C78: D2 | F78: طابوق معزول 25 صم | X78: Insulated Block 25 cm | AO78: M2 | AS78: 0 | AW78: 0 | BA78: =AW78*AS78 -> 0
C79: D3 | F79: طابوق 20 صم معزول | X79: Insulated Block 20 cm | AO79: M2 | AP79: M2 | AQ79: M2 | AR79: M2 | AS79: 550 | AW79: 85 | BA79: =AW79*AS79 -> 46750
C80: D4 | F80: طابوق خالي 20 صم | X80: Hollow Block 20cm | AO80: M2 | AP80: M2 | AQ80: M2 | AR80: M2 | AS80: 470 | AW80: 60 | BA80: =AW80*AS80 -> 28200
C81: D5 | F81: طابوق خالي 15صم | X81: Hollow Block 15cm | AO81: M2 | AP81: M2 | AQ81: M2 | AR81: M2 | AS81: 0 | AW81: 0 | BA81: =AW81*AS81 -> 0
C82: D6 | F82: طابوق خالي 10 صم | X82: Hollow Block 10cm | AO82: M2 | AP82: M2 | AQ82: M2 | AR82: M2 | AS82: 200 | AW82: 55 | BA82: =AW82*AS82 -> 11000
C83: اجمالي الطابوق | AO83: =SUM(BA77:BD82) -> 85950
B84: أولا : اعـــــمـــــــــال الـــــهــــيكــــــل | C84: E | F84: أعمال البلاستر
C85: E1 | F85: بلاستر داخلي عازل | X85: Internal Gypsum Plast | AO85: M2 | AP85: M2 | AQ85: M2 | AR85: M2 | AS85: 1100 | AW85: 40 | BA85: =AW85*AS85 -> 44000
C86: E2 | F86: اسمنت بلاستر داخلي | X86: Internal Plaster | AO86: M2 | AP86: M2 | AQ86: M2 | AR86: M2 | AS86: 336 | AW86: 35 | BA86: =AW86*AS86 -> 11760
C87: E3 | F87: بلاستر خارجي | X87: External Plaster | AO87: M2 | AP87: M2 | AQ87: M2 | AR87: M2 | AS87: 1300 | AW87: 45 | BA87: =AW87*AS87 -> 58500
C88: 30 | F88: النعلة المخفية | X88: Hidden Skirting | AO88: M.L | AP88: M2 | AQ88: M2 | AR88: M2 | AS88: 450 | AW88: 10 | BA88: =AW88*AS88 -> 4500
C89: إجمالي البلاستر | X89: Total Plaster | AO89: =SUM(BA85:BD88) -> 118760
C90: F | F90: أعمال الطبقات العازلة
C91: F1 | F91: عزل ممبرين4 مم أسفل الجدران الخارجية | X91: Damp Proof membrane | AO91: LS | AP91: M2 | AQ91: M2 | AR91: M2 | AS91: 1 | AW91: 4000 | BA91: =AW91*AS91 -> 4000
C92: F2 | F92: عزل السطح ( كومبو 40مم) | X92: Combo Roof insulation 40mm | AO92: M2 | AP92: M2 | AQ92: M2 | AR92: M2 | AS92: 340 | AW92: 90 | BA92: =AW92*AS92 -> 30600
C93: F3 | F93: عزل الاسقف antifungs | X93: insulation under celing | AO93: M2 | AP93: M2 | AQ93: M2 | AR93: M2 | AS93: 550 | AW93: 13 | BA93: =AW93*AS93 -> 7150
C94: F4 | F94: عزل أرضية الحمامات (اسمنتي) | X94: Wet Area water proof ( Cementous) | AO94: =AO95 -> M2 | AS94: 35 | AW94: 70 | BA94: =AW94*AS94 -> 2450
C95: F5 | F95: عزل أرضية البلكونات (اسمنتي) | X95: Balcony water proof ( Cementous) | AO95: M2 | AP95: M2 | AQ95: M2 | AR95: M2 | AS95: 16 | AW95: 90 | BA95: =AW95*AS95 -> 1440
C96: إجمالي الطبقات العازلة | X96: Total Water proof | AO96: =SUM(BA91:BD95) -> 45640
C97: G | F97: تركيب اكساءات الارضيات و الجدران | AO97: Floors and Walls Finishing
A98: على المقاول تزويد الموقع بالكوادر الفنية والعمالة اللازمة لتنفيذ المشروع بالمستوى المطلوب مع مراعاة مايلي : 1 – جميع عناصر الكادر الفني والعمالة الفنية يجب أن يكونوا من المؤهلين ومن ذوي الخبرة والكفاءة كلاً حسب اختصاصه وحسب متطلبات العمل والتنفيذ ( من حيث العدد والتوزيع ). 2- يتم اعتماد الكوادر الفنية من قبل الاستشاري قبل مباشرتهم للعمل، ويجب أن تكون الكوادر الفنية من ذوي الخبرة بأعمال مماثلة. 3 – يحق للإستشاري الطلب من المقاول إبعاد/استبدال أي شخص مستخدم من قبله إذا رأى الاستشاري أن ذلك الشخص ليس بالمستوى المطلوب من حيث السلوك أو الخبرة لتنفيذ الأعمال. 4 – على المقاول تقديم جدول بأعداد العمالة العادية والفنية العاملة في الموقع بشكل أسبوعي. 5 – يشتمل الكادر الفني (المطلوب من المقاول توفيره كحد أدنى) على : • مدير للمشروع. • مهندس موقع ( Site Engineer )مسؤول عن تنفيذ المشروع للتعامل مع الاستشاري • مراقب فني (Forman) لكل نوع من أنواع الأعمال. • أي كوادر فنية أخرى يطلبها الاستشاري ويرى أنها لازمة لتنفيذ المشروع بالمستوى المطلوب. • مقاول باطن اعمال الالكتروميكانيك يجب ان يكون معتمد من الاستشاري و الـ FEWA. | C98: G1 | F98: اكساءات ارضيات للمدخل الرئيسي للفيلا | X98: Flooring for main entrance | AO98: M2 | AP98: M2 | AQ98: M2 | AR98: M2 | AS98: 5 | AW98: 45 | BA98: =AW98*AS98 -> 225
C99: G2 | F99: أرضيات درج المدخل الرئيسي والرامب | X99: Steps of main entrance and Ramp | AO99: M2 | AP99: M2 | AQ99: M2 | AR99: M2 | AS99: 10 | AW99: 45 | BA99: =AW99*AS99 -> 450
C100: G3 | F100: أرضيات التيراس بالدور الاول ان وجد | X100: 1st floor balcony if any | AO100: M2 | AS100: 13 | AW100: 45 | BA100: =AW100*AS100 -> 585
C101: G4 | F101: اكساءات ارضيات الدور الاول و الارض | X101: Flooring for GF and 1st floor | AO101: M2 | AP101: M2 | AQ101: M2 | AR101: M2 | AS101: 450 | AW101: 45 | BA101: =AW101*AS101 -> 20250
C102: G5 | F102: اكساء الدرج الداخلي للفيلا. | X102: internal steps | AO102: L.M | AP102: M2 | AQ102: M2 | AR102: M2 | AS102: 30 | AW102: 80 | BA102: =AW102*AS102 -> 2400
C103: G6 | F103: اكساءات الحوائط | X103: Wall tiles | AO103: M2 | AP103: M2 | AQ103: M2 | AR103: M2 | AS103: 280 | AW103: 45 | BA103: =AW103*AS103 -> 12600
C104: G7 | F104: النعلات حسب المواصافات | X104: Skirting | AO104: =AO102 -> L.M | AP104: M2 | AQ104: M2 | AR104: M2 | AS104: 450 | AW104: 10 | BA104: =AW104*AS104 -> 4500
C105: G8 | F105: حماية من البلاستيك و الجبس للارضيات | X105: flooring protection | AO105: =AO115 -> L.S | AP105: M2 | AQ105: M2 | AR105: M2 | AS105: 1 | AW105: 3500 | BA105: =AW105*AS105 -> 3500
C106: إجمالي تركيب اكساءات الارضيات و الجدران | X106: Total of tile works flooring and walls | AO106: =SUM(BA98:BD105) -> 44510
C107: اجمالي الاعمال الهيكل | X107: Total of main structure | AO107: =AO45+AO63+AO75+AO106+AO83+AO89+AO96 -> #VALUE!
B109: =$C$109 -> ثانيا : اعمال الالكتروميكانيكال | C109: ثانيا : اعمال الالكتروميكانيكال | AO109: Electromechanical Works
C110: H | F110: اعمال MEP حتي التسليم | AO110: MEP works till handing over
C111: H1 | F111: توريد وتركيب بايبات الصرف و التغذية | X111: supply and install drainage and water pipes | AO111: L.S | AS111: 1 | AW111: 30000 | BA111: =AW111*AS111 -> 30000
C112: H2 | F112: توريد وتركيب يايبات الكهرباء و الاتصالات | X112: Supply and install Electrical pipes | AO112: L.S | AS112: 1 | AW112: 10000 | BA112: =AW112*AS112 -> 10000
C113: H3 | F113: توريد وتركيب بايبات الشفط المركزي | X113: supply and install central vacuum pipes | AO113: L.S | AS113: 1 | AW113: 3000 | BA113: =AW113*AS113 -> 3000
C114: H4 | F114: تنفيذ الكلين اوت | X114: Drainage clean out works | AO114: L.S | AS114: 1 | AW114: 17000 | BA114: =AW114*AS114 -> 17000
C115: H5 | F115: انذار الحريق و انارة الطوارئ | X115: Fire alarm and emergency lights | AO115: L.S | AS115: 1 | AW115: 2500 | BA115: =AW115*AS115 -> 2500
C116: H6 | F116: تركيب خزانات المياه أعلى السطح | X116: Install tanks above roof | AO116: No | AP116: M2 | AQ116: M2 | AR116: M2 | AS116: 2 | AW116: 2000 | BA116: =AW116*AS116 -> 4000
C117: H7 | F117: تركيب خزان مياه تحت الأرض | X117: install underground water tank | AO117: No | AP117: M2 | AQ117: M2 | AR117: M2 | AS117: 1 | AW117: 2000 | BA117: =AW117*AS117 -> 2000
C118: H8 | F118: تركيب خزان استرجاع مياه التكييف | X118: install tank for AC water | AO118: No | AS118: 1 | AW118: 2000 | BA118: =AW118*AS118 -> 2000
C119: H9 | F119: تركيب السخان المركزي | X119: install central heater | AO119: No | AP119: M2 | AQ119: M2 | AR119: M2 | AS119: 2 | AW119: 3000 | BA119: =AW119*AS119 -> 6000
C120: H10 | F120: تركيب الأطقم الصحية | X120: install sanitary wares | AO120: L.S | AP120: M2 | AQ120: M2 | AR120: M2 | AS120: 9 | AW120: 900 | BA120: =AS120*AW120 -> 8100
C121: H11 | F121: تأسيس 6 نقاط كاميرا | X121: Pipes for 6 no's Camera | AO121: L.S | AP121: M2 | AQ121: M2 | AR121: M2 | AS121: 1 | AW121: 3000 | BA121: =AW121*AS121 -> 3000
...

Sheet المواصفات الفنية (2)
A10: المواصفات الفنية والشروط العامة
A16: مشروع | Z16: =المدخلات!P4 -> فيلا دور أرضي و اول وسور
A18: عايدة للمالك | Z18: =المدخلات!P3 -> احمد ابراهيم النعيمي
M22: القسيمة | Z22: =المدخلات!AR4 -> 0
M26: المنطقة | Z26: =المدخلات!AR3 -> 0
A34: فهرس دفتر الشروط الفنية الخاصة
A36: ( 1 ) المتطلبات العامة وأعمال تحضير الموقع
A37: ( 2 ) أعمال الحفر والرودبيس
A38: ( 3 ) أعمال الخرسانات
A39: ( 4 ) أعمال الطابوق
A40: ( 5 ) أعمال البلاستر
A41: ( 6 ) أعمال العزل
A42: ( 7 ) الأعمال الصحية
A43: ( 8 ) الأعمال الكهربائية
A44: ( 9 ) أعمال الهاندريل والألمنيوم والزجاج
A45: ( 10 ) جدول تشطيبات الأعمال الصحية
A46: ( 11 ) جدول تشطيبات الأعمال الكهربائية
... A65: 2.1.1- المشروع والموقع :
A66: ="1 – المطلوب إنشاؤه هو مشروع "&TEXT([2]المدخلات!P4,0)&" "&"على قطعة أرض رقم "&" "&TEXT([2]المدخلات!AR4,0)&" "&"في منطقة"&" "&TEXT([2]المدخلات!AR3,0) -> 1 – المطلوب إنشاؤه هو مشروع فيلا ارضي اول مع تعديل واجهة الملحق على قطعة أرض رقم 412030315 في منطقة مدينة خليفة بن زايد
A67: 2 – يتم تنفيذ جميع الأعمال طبقاً للرسومات والمواصفات المعدة لهذا الغرض من قبل الاستشاري، وكل ماورد في الرسومات أو المواصفات يعتبر مطلوباً من المقاول، وهو جزءاً لايتجزأ من العقد. 3 – على المقاول اتخاذ جميع الاحتياطات اللازمة فيما يتعلق باستخدام الطرق وتوفير عوامل السلامة العامة، ومراعاة أنظمة وتعليمات ومتطلبات الجهات الرسمية المعنية فيما يتعلق بذلك.
A71: 3.1.1- تدقيـق الأعمــال :
A72: على المقاول إعلام الاستشاري مسبقاً والتنسيق معه لأي عمل و/أو جزء من العمل يحتاج إلى تدقيق من الاستشاري قبل المباشرة بتنفيذ ما يتبعه من أعمال على أن يتم إعلام الاستشاري بذلك قبل (24) ساعة على الأقل من الموعد المفترض لتدقيق ذلك العمل.
A76: 4.1.1- الرسومات التنفيذية :
A77: 1 – على المقاول إعداد رسومات تنفيذية مفصلة حيثما ورد ذلك في المواصفات الخاصة لأي عمل من الأعمال، واعتماد تلك الرسومات من الاستشاري أولاً ومن الجهات الرسمية المعنية ( حيث يلزم ذلك ) خطيـاً قبل البدء في التنفيذ، ويتحمل المقاول مسؤولية أية أعمال و/أو مواد يقوم بتوريدها أو تركيبها قبل اعتماد تلك الرسومات. 2 – على المقاول تقديم ثلاث نسخ من الرسومات التنفيذية/الرسومات التنفيذية المعدلة للأعمال كما تم تنفيذها على أرض الواقـع (As Built Drawings) قبل موعد الاستلام الابتدائي للمشروع.
A83: 5.1.1- الخدمات القائمة :
A84: على المقاول المحافظة على سلامة الخدمات الموجودة داخل وحول الموقع والتي لاتقع ضمن دائرة الأعمال المطلوبة منه، ويتحمل المقاول المسؤولية والتكاليف المترتبة، عند الإخلال بذلك، لإعادة الوضع إلى ما كان عليه لتلك الخدمات واستبدال التالف منها بمثله دون المطالبة بأي تعويض نظير ذلك ( والتنسيق مع الجهات المعنية فيما يتعلق بتحويل تلك الخدمات )، بما يشمل وضع الطريق والأرصفة المحيطة.
A90: 5.1.1- الخدمات القائمة :
A91: على المقاول المحافظة على سلامة الخدمات الموجودة داخل وحول الموقع والتي لاتقع ضمن دائرة الأعمال المطلوبة منه، ويتحمل المقاول المسؤولية والتكاليف المترتبة، عند الإخلال بذلك، لإعادة الوضع إلى ما كان عليه لتلك الخدمات واستبدال التالف منها بمثله دون المطالبة بأي تعويض نظير ذلك ( والتنسيق مع الجهات المعنية فيما يتعلق بتحويل تلك الخدمات )، بما يشمل وضع الطريق والأرصفة المحيطة.
A96: 2.1-إدارة وتنظيم موقع العمل:
A97: 1.2.1- الكادر الفني وموظفو المقاول:
A98: على المقاول تزويد الموقع بالكوادر الفنية والعمالة اللازمة لتنفيذ المشروع بالمستوى المطلوب مع مراعاة مايلي : 1 – جميع عناصر الكادر الفني والعمالة الفنية يجب أن يكونوا من المؤهلين ومن ذوي الخبرة والكفاءة كلاً حسب اختصاصه وحسب متطلبات العمل والتنفيذ ( من حيث العدد والتوزيع ). 2- يتم اعتماد الكوادر الفنية من قبل الاستشاري قبل مباشرتهم للعمل، ويجب أن تكون الكوادر الفنية من ذوي الخبرة بأعمال مماثلة. 3 – يحق للإستشاري الطلب من المقاول إبعاد/استبدال أي شخص مستخدم من قبله إذا رأى الاستشاري أن ذلك الشخص ليس بالمستوى المطلوب من حيث السلوك أو الخبرة لتنفيذ الأعمال. 4 – على المقاول تقديم جدول بأعداد العمالة العادية والفنية العاملة في الموقع بشكل أسبوعي. 5 – يشتمل الكادر الفني (المطلوب من المقاول توفيره كحد أدنى) على : • مدير للمشروع. • مهندس موقع ( Site Engineer )مسؤول عن تنفيذ المشروع للتعامل مع الاستشاري • مراقب فني (Forman) لكل نوع من أنواع الأعمال. • أي كوادر فنية أخرى يطلبها الاستشاري ويرى أنها لازمة لتنفيذ المشروع بالمستوى المطلوب. • مقاول باطن اعمال الالكتروميكانيك يجب ان يكون معتمد من الاستشاري و الـ FEWA.
... A273: وعليه تم التوقيع والإتفاق
A275: المالك | S275: الاستشاري | AL275: المقاول
A276: =[2]المدخلات!P3 -> فهد سليمان الشحي | S276: سافانا ديزاين للاستشارات الهندسية | AL276: =[2]المدخلات!$AR$10 -> القيصر لمقاولات البناء

Sheet أسعار التوريد (2)
B1: المالك | G1: =[1]المدخلات!P3 -> محمد ناصر المنصوري | S1: المنطفة | Y1: =[1]المدخلات!AR3 -> Awafi | AG1: القسيمة | AM1: =[1]المدخلات!AR4 -> 406131934 | AU1: المقاول | AY1: =[1]المدخلات!AR10 -> السفير
B2: ='[1]حساب الكميات'!AO277 -> 0
B3: اختيار الأنواع
J4: 1 | K4: السخان | R4: مركزي مع 2 سخان Ariston 200 L | AD4: 15- خزان استرجاع مياه التكييف | AT4: تحت الأرض
J5: 2 | K5: كراسي الحمامات | R5: عادي | AD5: 16- مكسرات المغاسل والحمامات | AT5: عادية
J6: 3 | K6: الشفط | R6: مركزي مخفي للسطح او للجدران الخارجية | AD6: 17- الصرف | AT6: كلين اوت
J7: 4 | K7: النعلة | R7: شامل النعلات - مخفية | AD7: 18-حبات السيراميك | AT7: متوسطة
P8: 5-الألمنيوم | R8: بروفايل فول امبريلا عادي | AD8: 19- سعة خزان المياه | AT8: 1000 جالون
P9: 6- خزان المياه | R9: فوق الأرض | AD9: 20- ارتفاعات الأبواب | AT9: 250 Cm
P10: 7-الباب الرئيسي كاست المنيوم | R10: دبل هايت | AD10: 21-نقاط مياه في السور: | AT10: عدد 4
P11: 8-نوع الصبغ: | R11: سانديكس | AD11: 22-نقاط كهرباء في السور: | AT11: 4
P12: 9-الماء الحار والبارد للشطاف : | R12: كامل حمامات البيت | AD12: 23- الحجر والبورسلان الخارجي: | AT12: 50
P13: 10-نقطة كهرباء سيارة: | R13: لا | AD13: 24- نقاط الكاميرا: | AT13: 6
P14: 11-نقاط اضاءة بالواجهة | R14: نعم | AD14: 25- سعر سيراميك الملاحق: | AT14: 30
P15: 12-نقطة صرف وتغذية للبانتري في الدور الأول: | R15: نعم | AD15: 26-أحواض الزراعة: | AT15: يوجد
P16: 13-نقطة مياه السطح: | R16: 1 | AD16: 27-نعلة مخفية للجبس بلاستر | AT16: يوجد
P17: 14-نقطة كهرباء في السطح: | R17: 1 | AD17: 28-مدة التعاقد | AT17: 16 شهر
B18: 03-الطابوق | R18: =[1]Sheet2!B126 -> راكنور | AD18: 02-الخرسانة | AT18: =[1]Sheet2!B130 -> الخليج
R19: =[1]Sheet2!B127 -> راس الخيمة | AT19: =[1]Sheet2!B131 -> النعيمي
AT20: =[1]Sheet2!B132 -> اوريميكس
B21: 31- تركيب تمديدات التغذية فوق السطح | R21: علي جدران البارابت | AD21: 32-صرف الحمامات الدور الاول | AT21: =[1]Sheet2!B141 -> داكت من تحت لفوق السطح
AT22: =[1]Sheet2!B142 -> تحت الاسقف الي داكت الارضي
B23: 33-نوعية بايبات و اسلاك الكهرباء | R23: ناشيونال | AD23: 34-نوعية تمديدات تغذية المياه | AT23: =[1]Sheet2!B147 -> اكواثرم
AT24: =[1]Sheet2!B148 -> راكثيرم
B25: 35-نوعية بايبات الصرف الصحي | R25: اطلس | AD25: 36-مراوح الشفاط المركزي | AT25: اعمال مدنية بايبات على المقاول
B26: 37-قواطع بانواعها | R26: شنايدر | AD26: 38-اللوحات و الصناديق | AT26: شنايدر
B27: 39-الايزوليتر | R27: شنايدر | AD27: 40-مفاتيح الانارة | AT27: ليجراند
B28: 41-اعمال مدنية للتكييف | R28: مركزي او سبليت علي المقاول | AD28: 42-تجويفات جدران الحمامات | AT28: جدار واحد حسب الديكور عمق 13 سنت
B29: 43-الدرج الامامي لمدخل الفيلا | R29: طاير مع اضاءة من تحت | AD29: 44-تركيب قروفات بالسور | AT29: توريد مالك تركيب مقاول
B30: 45-حماية الارضيات بعد تركيب البورسلان | R30: طبقة جبس مع بلاستيك | AD30: 46-توريد و تركيب رداد للكلين اوت | AT30: من ضمن السعر
B31: 47- جي اي بوكس للماخذ و المفاتيح | R31: الفنار | AD31: 01-الحديد | AT31: قطري
B33: المالك | G33: =المدخلات!$P$3 -> احمد ابراهيم النعيمي | S33: المنطفة | Y33: =المدخلات!$AR$3 -> 0 | AG33: القسيمة | AM33: =المدخلات!$AR$4 -> 0 | AU33: المقاول
AU34: =المدخلات!AR10 -> 0
B37: أسعار توريد التشطيبات
B39: البند | AR39: الوحدة | AW39: سعر التوريد
B41: اسعار توريد السيراميك | R41: ='حساب الكميات (2)'!F133 -> اكساءات ارضيات للمدخل الرئيسي للفيلا | AR41: M2 | AW41: 50
R42: ='حساب الكميات (2)'!F134 -> أرضيات درج المدخل الرئيسي والرامب | AR42: M2 | AW42: 80
R43: ='حساب الكميات (2)'!F135 -> أرضيات التيراس بالدور الاول ان وجد | AR43: M2 | AW43: 50
R44: ='حساب الكميات (2)'!F136 -> اكساءات ارضيات الدور الاول و الارض | AR44: M2 | AW44: 35
R45: ='حساب الكميات (2)'!F137 -> اكساء الدرج الداخلي للفيلا. | AR45: L.M | AW45: 250
B46: مجموع سعر التوريد | R46: ='حساب الكميات (2)'!F138 -> اكساءات حوائط | AR46: =AR45 -> L.M | AW46: 50
B47: ='حساب الكميات (2)'!AO140 -> 43450 | R47: ='حساب الكميات (2)'!F139 -> النعلات حسب المواصافات | AR47: =AR46 -> L.M | AW47: 10
R48: توريد اكساءات الواجهات | AR48: M2 | AW48: 90
B50: سعر توريد الأبواب الداخلية | R50: ="توريد الباب الرئيسي للفيلا "&TEXT(R114,0) -> توريد الباب الرئيسي للفيلا ارتفاع لسقف الأرضي | AE50: ارتفاع لسقف الأرضي | AR50: NO. | AW50: 45000
R51: ="توريد الباب الخارجي للمجلس - ارتفاع "&TEXT(R131,0) -> توريد الباب الخارجي للمجلس - ارتفاع 250 Cm | AR51: NO. | AW51: 0
R52: ="توريد أبواب الغرف والحمامات - ارتفاع "&TEXT(R131,0) -> توريد أبواب الغرف والحمامات - ارتفاع 250 Cm | AR52: NO. | AW52: 3000
B53: مجموع سعر التوريد | R53: ="توريد أبواب الغرف الخدمية - ارتفاع "&TEXT(R131,0) -> توريد أبواب الغرف الخدمية - ارتفاع 250 Cm | AR53: NO. | AW53: 1500
B54: ='حساب الكميات (2)'!AO150 -> 90000 | R54: توريد بابى السور كاست الومنيوم باب كبير و صغير | AR54: NO. | AW54: 12000
B56: سعر توريد الألمينوم | R56: سعرتوريد الالمنيوم و الزجاج | AD56: CURTIN WALL | AR56: m2 | AW56: 600
B58: مجموع سعر التوريد | R58: هاندريل الدرج الزجاج و الدابل هايت ان وجد ارتفاع 1.70 | AR58: m2 | AW58: 1200
B59: ='حساب الكميات (2)'!AO144 -> 145600
B61: توريد الاطقم الصحية | R61: ='حساب الكميات (2)'!F156 -> الاطقم الصحية لحمام مغاسل الصالة والمجلس | AR61: الأطقم | AW61: 2500
AR62: الكرسي | AW62: 1500
AR63: الكاونتر | AW63: 2000
R64: ='حساب الكميات (2)'!F157 -> الاطقم الصحية لحمام ومغاسل غرف النوم | AR64: الأطقم | AW64: 2500
AR65: الكرسي | AW65: 1500
AR66: الكاونتر | AW66: 2000
R67: ='حساب الكميات (2)'!F158 -> الاطقم الصحية لحمام ومغاسل غرفة الشغالة | AR67: الأطقم | AW67: 500
AR68: الكرسي | AW68: 500
B69: مجموع سعر التوريد | AR69: المغسلة | AW69: 300
B70: ='حساب الكميات (2)'!AO160 -> 49900 | R70: سعر توريد خلاط المطبخ | AR70: NO. | AW70: 500
B72: ملاحظات:
B73: اعمال البورسلان و السيراميك و الرخام و الانترلوك المحيطة بالفيلا او المسبح توريد تركيب المالك باستثناء المساحة المؤشر عليها بالمخطط توريد و تركيب و رفع منسوب علي المقاول
B80: مواصفات مواد الهيكل
B82: الحديد | R82: قطري
B83: الخرسانة | D83: الخرسانة | F83: الخرسانة | H83: الخرسانة | J83: الخرسانة | L83: الخرسانة | N83: الخرسانة | P83: الخرسانة | R83: الخليج | AW83: اوريميكس
B84: الطابوق | D84: الطابوق | F84: الطابوق | H84: الطابوق | J84: الطابوق | L84: الطابوق | N84: الطابوق | P84: الطابوق | R84: راكنور
B85: الاعمدة | D85: الاعمدة | F85: الاعمدة | H85: الاعمدة | J85: الاعمدة | L85: الاعمدة | N85: الاعمدة | P85: الاعمدة | R85: خرسانة ذاتية الدمج
B86: الخشب | D86: الخشب | F86: الخشب | H86: الخشب | J86: الخشب | L86: الخشب | N86: الخشب | P86: الخشب | R86: من النوعية الجيدة إلى النوعية الجديدة
B88: مواصفات المواد الصحية
B90: نوعية تمديدات تغذية المياه | R90: اكواثرم | AC90: PIX PIBE | AR90: تركيب تحت الاسقف
B91: نوعية بايبات الصرف الصحي | R91: اطلس
B92: نوعية الخزان تحت الأرض | R92: من الياف الفايبر
B93: نوعية الخزان فوق الأرض | R93: من الياف الفايبر
B94: نوعية السخان المركزي | R94: ARISTON إيطالي
B95: نوعية مكاين الضغط | R95: اسباني/ ايطالي
B97: مواصفات المواد الكهرباية
A98: على المقاول تزويد الموقع بالكوادر الفنية والعمالة اللازمة لتنفيذ المشروع بالمستوى المطلوب مع مراعاة مايلي : 1 – جميع عناصر الكادر الفني والعمالة الفنية يجب أن يكونوا من المؤهلين ومن ذوي الخبرة والكفاءة كلاً حسب اختصاصه وحسب متطلبات العمل والتنفيذ ( من حيث العدد والتوزيع ). 2- يتم اعتماد الكوادر الفنية من قبل الاستشاري قبل مباشرتهم للعمل، ويجب أن تكون الكوادر الفنية من ذوي الخبرة بأعمال مماثلة. 3 – يحق للإستشاري الطلب من المقاول إبعاد/استبدال أي شخص مستخدم من قبله إذا رأى الاستشاري أن ذلك الشخص ليس بالمستوى المطلوب من حيث السلوك أو الخبرة لتنفيذ الأعمال. 4 – على المقاول تقديم جدول بأعداد العمالة العادية والفنية العاملة في الموقع بشكل أسبوعي. 5 – يشتمل الكادر الفني (المطلوب من المقاول توفيره كحد أدنى) على : • مدير للمشروع. • مهندس موقع ( Site Engineer )مسؤول عن تنفيذ المشروع للتعامل مع الاستشاري • مراقب فني (Forman) لكل نوع من أنواع الأعمال. • أي كوادر فنية أخرى يطلبها الاستشاري ويرى أنها لازمة لتنفيذ المشروع بالمستوى المطلوب. • مقاول باطن اعمال الالكتروميكانيك يجب ان يكون معتمد من الاستشاري و الـ FEWA.
B99: اللوحات و الصناديق | R99: شنايدر
B100: مفاتيح الانارة | D100: مفاتيح الانارة | F100: مفاتيح الانارة | H100: مفاتيح الانارة | J100: مفاتيح الانارة | L100: مفاتيح الانارة | N100: مفاتيح الانارة | P100: مفاتيح الانارة | R100: PANASONIC | T100: ليجراند | V100: ليجراند | X100: ليجراند | Z100: ليجراند | AB100: ليجراند | AD100: ليجراند | AF100: ليجراند | AH100: ليجراند | AJ100: ليجراند | AL100: ليجراند | AN100: ليجراند | AP100: ليجراند | AR100: مع تيوترال
B101: نوع بايبات و اسلاك الكهرباء | D101: نوع بايبات و اسلاك الكهرباء | F101: نوع بايبات و اسلاك الكهرباء | H101: نوع بايبات و اسلاك الكهرباء | J101: نوع بايبات و اسلاك الكهرباء | L101: نوع بايبات و اسلاك الكهرباء | N101: نوع بايبات و اسلاك الكهرباء | P101: نوع بايبات و اسلاك الكهرباء | R101: دوكاب | T101: دوكاب | V101: دوكاب | X101: دوكاب | Z101: دوكاب | AB101: دوكاب | AD101: دوكاب | AF101: دوكاب | AH101: دوكاب | AJ101: دوكاب | AL101: دوكاب | AN101: دوكاب | AP101: دوكاب
B102: قواطع رييسية | D102: قواطع رييسية | F102: قواطع رييسية | H102: قواطع رييسية | J102: قواطع رييسية | L102: قواطع رييسية | N102: قواطع رييسية | P102: قواطع رييسية | R102: DORMAN SWITSH | T102: شنايدر | V102: شنايدر | X102: شنايدر | Z102: شنايدر | AB102: شنايدر | AD102: شنايدر | AF102: شنايدر | AH102: شنايدر | AJ102: شنايدر | AL102: شنايدر | AN102: شنايدر | AP102: شنايدر
B103: الازوليتر | D103: الازوليتر | F103: الازوليتر | H103: الازوليتر | J103: الازوليتر | L103: الازوليتر | N103: الازوليتر | P103: الازوليتر | R103: شنايدر | T103: شنايدر | V103: شنايدر | X103: شنايدر | Z103: شنايدر | AB103: شنايدر | AD103: شنايدر | AF103: شنايدر | AH103: شنايدر | AJ103: شنايدر | AL103: شنايدر | AN103: شنايدر | AP103: شنايدر
B104: جي اي بوكس للماخذ و مفاتيح | D104: جي اي بوكس للماخذ و مفاتيح | F104: جي اي بوكس للماخذ و مفاتيح | H104: جي اي بوكس للماخذ و مفاتيح | J104: جي اي بوكس للماخذ و مفاتيح | L104: جي اي بوكس للماخذ و مفاتيح | N104: جي اي بوكس للماخذ و مفاتيح | P104: جي اي بوكس للماخذ و مفاتيح | R104: الفنار | T104: الفنار | V104: الفنار | X104: الفنار | Z104: الفنار | AB104: الفنار | AD104: الفنار | AF104: الفنار | AH104: الفنار | AJ104: الفنار | AL104: الفنار | AN104: الفنار | AP104: الفنار
B106: مواصفات من اختيار المالك
B108: السخان | R108: مركزي مع 2 سخان 200L كل واحد ARISTON
B109: كراسي الحمامات | D109: كراسي الحمامات | F109: كراسي الحمامات | H109: كراسي الحمامات | J109: كراسي الحمامات | L109: كراسي الحمامات | N109: كراسي الحمامات | P109: كراسي الحمامات | R109: معلق مع سماكة جدار 25 سنتم
B110: الشفط | D110: الشفط | F110: الشفط | H110: الشفط | J110: الشفط | L110: الشفط | N110: الشفط | P110: الشفط | R110: مركزي مخفي للسطح او للجدران الخارجية
B111: النعلة | D111: النعلة | F111: النعلة | H111: النعلة | J111: النعلة | L111: النعلة | N111: النعلة | P111: النعلة | R111: شامل النعلات - مخفية مع ستيل
B112: الألمنيوم | D112: الألمنيوم | F112: الألمنيوم | H112: الألمنيوم | J112: الألمنيوم | L112: الألمنيوم | N112: الألمنيوم | P112: الألمنيوم | R112: بروفايل كيرتين وول
B113: خزان المياه | D113: خزان المياه | F113: خزان المياه | H113: خزان المياه | J113: خزان المياه | L113: خزان المياه | N113: خزان المياه | P113: خزان المياه | R113: تحت الأرض مع غرفة
B114: الباب الرئيسي كاست المنيوم | D114: الباب الرئيسي كاست المنيوم | F114: الباب الرئيسي كاست المنيوم | H114: الباب الرئيسي كاست المنيوم | J114: الباب الرئيسي كاست المنيوم | L114: الباب الرئيسي كاست المنيوم | N114: الباب الرئيسي كاست المنيوم | P114: الباب الرئيسي كاست المنيوم | R114: =AE50 -> ارتفاع لسقف الأرضي
B115: نوع الصبغ | D115: نوع الصبغ | F115: نوع الصبغ | H115: نوع الصبغ | J115: نوع الصبغ | L115: نوع الصبغ | N115: نوع الصبغ | P115: نوع الصبغ | R115: قرافيو ناسونال
B116: الماء الحار والبارد للشطاف | D116: الماء الحار والبارد للشطاف | F116: الماء الحار والبارد للشطاف | H116: الماء الحار والبارد للشطاف | J116: الماء الحار والبارد للشطاف | L116: الماء الحار والبارد للشطاف | N116: الماء الحار والبارد للشطاف | P116: الماء الحار والبارد للشطاف | R116: لا
B117: نقطة كهرباء سيارة | D117: نقطة كهرباء سيارة | F117: نقطة كهرباء سيارة | H117: نقطة كهرباء سيارة | J117: نقطة كهرباء سيارة | L117: نقطة كهرباء سيارة | N117: نقطة كهرباء سيارة | P117: نقطة كهرباء سيارة | R117: نعم | AR117: 2 مع ازوليتر
B118: نقاط اضاءة بالواجهات | D118: نقاط اضاءة بالواجهة | F118: نقاط اضاءة بالواجهة | H118: نقاط اضاءة بالواجهة | J118: نقاط اضاءة بالواجهة | L118: نقاط اضاءة بالواجهة | N118: نقاط اضاءة بالواجهة | P118: نقاط اضاءة بالواجهة | R118: نعم
B119: صرف وتغذية للبانتري الدور الأول | D119: نقطة صرف وتغذية للبانتري في الدور الأول | F119: نقطة صرف وتغذية للبانتري في الدور الأول | H119: نقطة صرف وتغذية للبانتري في الدور الأول | J119: نقطة صرف وتغذية للبانتري في الدور الأول | L119: نقطة صرف وتغذية للبانتري في الدور الأول | N119: نقطة صرف وتغذية للبانتري في الدور الأول | P119: نقطة صرف وتغذية للبانتري في الدور الأول | R119: نعم
B120: نقطة كهرباء السطح | D120: نقطة مياه السطح | F120: نقطة مياه السطح | H120: نقطة مياه السطح | J120: نقطة مياه السطح | L120: نقطة مياه السطح | N120: نقطة مياه السطح | P120: نقطة مياه السطح | R120: 2
B121: نقطة مياه في السطح | D121: نقطة كهرباء في السطح | F121: نقطة كهرباء في السطح | H121: نقطة كهرباء في السطح | J121: نقطة كهرباء في السطح | L121: نقطة كهرباء في السطح | N121: نقطة كهرباء في السطح | P121: نقطة كهرباء في السطح | R121: 2
B122: تركيب تمديدات التغذية | D122: 31- تركيب تمديدات التغذية فوق السطح | F122: 31- تركيب تمديدات التغذية فوق السطح | H122: 31- تركيب تمديدات التغذية فوق السطح | J122: 31- تركيب تمديدات التغذية فوق السطح | L122: 31- تركيب تمديدات التغذية فوق السطح | N122: 31- تركيب تمديدات التغذية فوق السطح | P122: 31- تركيب تمديدات التغذية فوق السطح | R122: تحت الاسقف
...

Sheet عقد اساسي
A1: عقد الاتفاق Agreement
A3: بإشرافنا نحن
A4: سافانا ديزاين للإستشارات الهندسية والتصميم الداخلي- رأس الخيمة
A6: مكتب 407 أبراج جلفار رأس الخيمة
A7: 525015080
A9: تم الاتفاق بين كل من
A10: الطرف الاول | B10: المالك | D10: =المدخلات!$P$3 -> احمد ابراهيم النعيمي
A11: الطرف الثاني | B11: المقاول | D11: =المدخلات!$AR$3 -> 0
A12: الطرف الثالث | B12: ( الاستشاري) | D12: سافانا ديزاين للاستشارات الهندسية
A14: المشروع
A15: وصف المشروع | D15: =المدخلات!$P$4 -> فيلا دور أرضي و اول وسور
A16: المنطقة | D16: =المدخلات!$P$11 -> الخران
A17: رقم القسيمة | D17: =المدخلات!$P$12 -> 403100010
A19: ='[3]حساب الكميات'!AO270 -> سعر الفيلا مع السور(بدون الضريبة) | E19: ='حساب الكميات'!$AO$241 -> 67665
A21: يقوم الطرف الثاني بتنفيذ وانشاء وانجاز وصيانة المشروع المذكور اعلاه لقاء مبلغ وقدره
A22: =المدخلات!$AD$13 -> 0 | I22: درهم اماراتي
A23: و ذلك حسب المتفق عليه والمعتمد وفق للمناقصة التي جرت
A25: توقيع وختم المقاول | D25: توقيع وختم المالك | G25: توقيع وختم الاستشاري
A32: بنود العقد
A34: كافة مستندات المشروع و جميع متعلقاته متكاملة فيما بينها و تشمل المشروع ككل أي بحال عدم ذكر اي بند بالمواصفات او المخططات وتم ذكره بجدول الكميات او المخططات المعتمدة أو اي مستند اخر غير ذلك , والعكس صحيح على المقاول الالتزام به و العمل على تضمينه بأعمال المشروع اينما ذكر .علي المقاول ارجاع العقد موقع علي كل صفحة والمواصافات و المخططات وتوقيعه عليها يعتبر انه اطلع علي جميع تفاصيل المشروع
A36: 1 | B36: الاطلاع علي جميع مخططات المشروع | I36: =A36 -> 1
A37: على المقاول قبل توقيع العقد الاطلاع على المخططات و المواصفات و الشروط و التأكد من تطابق جميع المخططات الانشائية والمعمارية والخدمات و المناظير 3D وتنبيه الاستشاري لأي اختلاف في تطابق المخططات وذلك لتفادي التغيير و التعديل في الموقع قبل التنفيذ و في حالة عدم تنبيه الاستشاري بوجود اختلاف قبل الشروع في العمل يتحمل المقاول كامل المسؤولية في التعديلات المطلوبة و التاخير المترتب عن ذلك و اعتبار أن توقيعه عليها يعني موافقته على جميع ما ورد بها وتعتبر المناظير المقدمة من الاستشاري في ملف المناقصة هي المعتمدة من ناحية الشكل و التشطيبات في حال اختلاف مع المخططات المعتمدة .
B38: إصدار التعليمات, الرسوم | D38: إصدار التعليمات, الرسوم
A39: لا يحق للمالك اصدار اي تعليمات للمقاول تتعلق بتنفيذ المشروع الا عن طريق الاستشاري
A40: 2 | B40: مقاولي الباطن | G40: 2 | I40: =A40 -> 2
A41: يجوز للطرف الثاني اسناد جزء من الاعمال الى مقاولي الباطن المعتمدين والمسجلين لدى البلدية بموجب موافقة خطية من الاستشاري
A42: يكون المقاول مسؤول مسؤولية كاملة عن اعمال المقاول الباطن من حيث الجودة والتنفيذ واصول الصناعه والضمانات
A43: يتعهد الطرف الثاني بالتنسيق بين جميع المقاولين الباطن دون اي استثناء ودون اي احقية في المطالبة باي مبلغ اضافة نظير ذلك.
A45: 3 | B45: فسخ التعاقد | G45: 3 | I45: =A45 -> 3
A46: يحق للمهندس الاستشاري فسخ العقد في الحالات
A47: اذا تاخر المقاول عن بدء الاعمال بعد تسليم الموقع
A48: اذا تاخر المقاول في اتمام العمل وتسليمه في المواعيد المحدده لكل مرحلة في الجدول الزمني المعتمد
A49: اذا اظهر المقاول بطئا في سير العمل لدرجة يرى الاستشاري منها عدم قدرة الطرف الثاني على اتمام العمل في موعده على ان يقوم الاستشاري بتنبيه المقاول خطيا .
A50: اذا اخل المقاول ببرنامج العمل المحدد بشكل يؤثر على مستوى التنفيذ او الاخلال بالمواصفات المتفق عليها
A51: اذا انسحب المقاول عن العمل او تركه او افلس
A52: اذا اسند الطرف الثاني العمل لمقاول باطن دون اخطار الاستشاري
A53: في حال تاخير الطرف الاول عن سداد اي من مستحقات الطرف الثاني في موعد اقصاه 30 يوم فمن حق الطرف الثاني التوقف عن العمل وذلك بعد اخطار الاستشاري خطيا وتحسب فتره التاخير على المالك لصالح المقاول كمدة اضافية للمشروع.
A54: يحق للطرف الثاني الغاء التعاقد في حالة تاخير المالك باختيار التشطيبات مما يعود بالضرر علي المقاول
A55: 4 | B55: الاثار المترتبة على فسخ العقد | G55: 4 | I55: =A55 -> 4
A56: حساب غرامة التاخير على الطرف الثاني طبقا للعقد حتى تاريخ ابلاغ المقاول بقرار السحب.
A57: يتم تنفيذ الاعمال المتبقية كلها او بعضها على حساب المقاول على ان تطرح الاعمال المتبقية في مناقصة جديدة او يعهد بتنفيذها الى احد المقاولين بطريق الممارسة مع تحميل المقاول النتائج المترتبة عن هذا الاجراء
A58: حجز اي دفعات متبقيىة للمقاول وحجز الضمانات البنكية ومحجوزات الصيانة لحين الانتهاء من المشروع (تمويل خاص فقط).
A59: 5 | B59: حل النزاع | G59: =A59 -> 5 | I59: =A59 -> 5
A60: اي نزاع ينشا عن تطبيق احكام هذا العقد يكون الفصل فيه اختصاص محكم يتفق عليه الطرفان او ترشحة الجهات والدوائر المختصه.
A66: 6 | B66: محجوزات الصيانة | G66: =A66 -> 6 | I66: =A66 -> 6
A67: يستقطع 5% من قيمة الاعمال المنفذه بالدفعات الجارية او التي يتم صرفها بمعرفة المقرض كمحجوز صيانة وذلك ضمانا لحسن تنفيذ الاعمال وبعد الاستلام الابتدائي وحصر الاعمال نهائيا يتم صرف المستحقات الختامية للاعمال بعد استقطاع ما على المقاول من التزامات وما سبق صرفه كدفعات ويصرف له الباقي بعد حجز محجوز الصيانة من قيمة الاعمال المنفذة لمدة سنة من تاريخ الاستلام الابتدائي (تمويل خاص فقط) .
A68: 7 | B68: الإستلام الابتدائي للمشروع | G68: =A68 -> 7 | I68: =A68 -> 7
A69: يجب على المقاول اخطار الاستشاري باليوم الذي يتم فيه انهاء الاعمال على ان يكون هذا الاخطار قبل حلول هذا اليوم باسبوع على الاقل ليتم اخطار المالك والمقاول بموجب الاستلام الابتدائي يتم بحضور المقاول او مهندسه. وفي حاله عدم حضوره يقوم الاستشاري بعمله في غيابه فاذا ثبت ان الاعمال في حاله تسمح باستلامها يتم تحرير محضرا باستلام الاعمال استلاما مبدئيا في ذات اليوم, اما اذا ثبت عكس ذلك فللاستشاري الحق في عمل محضر اثبات حاله, وفي جميع الاحوال تكون المحاضر التي يحررها الاستشاري حجة على المقاول ولو لم يحضر او يوقع على المحضر ، لا يقوم الاستشاري باعادة المعاينة الا اذا اخطره المقاول بموعد انهاء الاعمال وقبل اسبوع من الحلول على الاقل وفي حال وجود ملاحظات على اعمال المشروع لا تمنع من الاستلاام الابتدائي يتم استلام المشروع ويعطى المقاول سبعه ايام لانهاء تلك الملاحظات وفي حال عدم انتهائه من هذه الملاحظات يعتبر محضر الاستلام الابتدائي لاغيا.
A70: 8 | B70: الاشراف الهندسي من قبل الاستشاري | G70: =A70 -> 8 | I70: =A70 -> 8
A71: يتم دفع رسوم شهرية مقابل الاشراف (600) درهم بدون الضريبة وذلك يتضمن الزيارات الاسبوعية والمتابعة بشكل عام في حال تجاوزت مدة انتهاء المشروع على المدة المتفق عليها , يتم دفع رسوم الاشراف من قبل الطرف المتسبب في التأخير ( المالك او المقاول ) في حال كان الطرفين متسببين في التأخير ف يتم دفع الرسوم المتبقية لأشراف مناصفة بين المالك والمقاول.
A72: يحق للإستشاري إيقاف المقاول عن العمل في حالة عدم التقيد بتعليمات الإستشاري ويسري هذا على المقاولين الذين يحضرهم المقاول الرئيسي أو المالك
A73: الطرف الثالث غير مسؤول إذا لم ينجز المشروع بالكامل خلال مدة التنفيذ المتعاقد عليها بين الطرف الاول والمقاول.
A74: في حال طلب المالك ايقاف الاشراف على المشروع وفسخ العقد بعد انتهاء مدة التنفيذ وقبل ان ينتهي انجاز المشروع بالكامل يجب ان يكون هذا الطلب خطيا قبل شهر على الاقل من انتهاء مدة التنفيذ وبعد موافقة الطرف الثالث فانه يحق للاستشاري تحصيل اتعاب اشراف ثلاثة اشهر اضافية على مدة العقد حسب ما هو مذكور في المادة السادسة عشر من هذا العقد وذلك كتعويض عن الضرر الذي يلحق بالاستشاري نتيجة فسخ العقد واخلاء الطرف.
A75: في حال طلب المالك إيقاف الاشراف خلال مدة التنفيذ دون مبرر فانه من حق الاستشاري تحصيل اتعابه كاملة حسب ما هو مذكور في هذا العقد قبل اخلاء الطرف وانهاء مهمة الاستشاري وبشرط الا يترتب على هذا الطلب اي ضرر على الطرف الثاني.
A76: الاستشاري غير ملزم بالاشراف على أي أعمال خارج التصميم المعماري والإنشائي (التكيف الديكور - المسابح -المصاعد- الحديقة).
A77: 9 | B77: الإستلام النهائي للمشروع | G77: =A77 -> 9 | I77: =A77 -> 9
A78: بعد انتهاء فترة ضمان الصيانة المحددة في العقد, يصدر الاستشاري شهادة الاستلام النهائي بعد معاينة المشروع شريطة ان يكون المقاول قد قام بكل ما يترتب عليه من التزامات خلال فترة الصيانة حيث لا يوجد اي عيوب في المشروع تمنع من اصدار هذه الشهادة من اجل صرف محجوز الضمان وقدره (5%) من قيمة العقد الاجمالية .ويلتزم المقاول بدفع مبلغ 2500 درهم كاتعاب للاستشاري نظير ذلك.
A79: 10 | B79: مدة الصيانة | G79: =A79 -> 10 | I79: =A79 -> 10
A80: علي المقاول متابعة ملاحظات المالك والاستشاري و صيانتها بعد الاستلام الابتدائي وحتي الاستلام النهائي للمشروع و في حال عدم تجاوب المقاول يحق للمالك عدم التوقيع على التسليم النهائي حتي تتم معالجة جميع الملاحظات . الطرف الثاني مسؤولا عن سلامة الهيكل الخرساني للمبنى المذكور اعلاه لمدة 20 سنة (عشرين سنة) من تاريخ الاستلام الابتدائي.
A81: 11 | B81: الصيانة | G81: =A81 -> 11 | I81: =A81 -> 11
A82: تبدا اعمال الصيانة للمشروع لمدة عام كامل بعد تاريخ الاستلام الابتدائي للمشروع مباشرة.
A83: 12 | B83: انسحاب المقاول بدون سبب | G83: =A83 -> 12 | I83: =A83 -> 12
A84: اذا انسحب المقاول من العمل بالمشروع بدون سبب مقبول من الاستشاري يقوم بدفع ما قيمته 10% من العقد لصالح المالك ودفع رسوم رسو العطاء وارساء المناقصة ونسبتها (4%) من قيمة اجمالي عقد المقاولة كاملا.
A86: 13 | B86: امتناع المالك التسليم الابتدائي | G86: =A86 -> 13 | I86: =A86 -> 13
A87: في حالة امتناع المالك عن التوقيع على محضر الاستلام الابتدائي او النهائي سيتم اخطاره بضرورة بيان السبب خلال خمسة عشر يوما من تاريخ اخطاره، فان انتهت هذه المهلة دون بيان اسباب امتناعه او ان الاسباب التي ابداها غير مقنعه من وجهة نظر الاستشاري، فانه يجوز للاستشاري استلام المبنى وتسليم المقاول كافة مستحقاته ويعتبر المبنى في حوزة المالك وتحت مسؤوليته من تاريخ الاستلام.
A88: 14 | B88: فسخ عقد الاستشاري | G88: =A88 -> 14 | I88: =A88 -> 14
A89: في حالة رغبة المالك في فسخ العقد مع الاستشاري بعد اعتماد المخطط لدى البلدية فعليه دفع 2% من قيمة المشروع للاستشاري كتعويض وضياع فرصة و نظير اتعابه.
A90: 15 | B90: اتعاب الاستشاري | G90: =A90 -> 15 | I90: =A90 -> 15
A91: يلتزم الطرف الثاني دفع نسبة من قيمة عقد المقاولة كاملا مقابل المخططات المعتمدة و المناقصة كذلك الامر عن أي اعمال اضافية التي تضاف الى العقد لاحقا .
A92: 16 | B92: التاخير عن مراحل الجدول الزمني | G92: =A92 -> 16 | I92: =A92 -> 16
A93: الطرف الثاني ملزم بتقديم جدول زمني قبل توقيع العقد ويتم اعتماده من الطرف الثالث فقط ويتم تطبيق غرامة 2000 درهم للمالك في حال تأخر المقاول عن انجاز كل مرحلة على حده في الجدول الزمني و دون سبب مقنع للتاخير وتلغي الغرامة في حال اجاز المشروع حسب المدة المتفق عليها .
A94: 17 | B94: توريد مواد خارجة عن المواصافات | G94: =A94 -> 17 | I94: =A94 -> 17
A95: يتم تغريم الطرف الثاني 2000 درهم ( للمالك ) في حال تم تركيب اي مادة او خامة مخالفة للمواصفات المعتمدة وغير مقبولة من الاستشاري .
A96: 18 | B96: اعتماد الامر التغييري | I96: =A96 -> 18
A97: في حال تم العمل على المخططات المعدلة من غير تقديم الامر التغييري من قبل الطرف الثاني للاستشاري و المالك لاعتماده فإن المقاول يتحمل مسؤوليته بذلك.
A98: 19 | B98: تقرير شهري | G98: =A98 -> 19 | I98: 19
A99: الطرف الثاني ملزم بتقديم تقرير شهري كتابي عن سير الاعمال في الموقع ويتم تغريمه درهم500 بحالة عدم الالتزام يدفعها للمالك او متابعة و تقرير يومي عن طريق مجموعة الواتساب الخاصة بالمشروع.
A101: 20 | B101: الدفعات الخاصة | G101: =A101 -> 20 | I101: =A101 -> 20
A102: الدفعات الخاصة تتم عن طريق الاستشاري فقط وفي حال تم دفع المالك الدفعة مباشرة للمقاول وبدون علم الاستشاري فإن المالك يتحمل مسؤوليته بذلك .
A103: 21 | B103: تقرير مع كل دفعة خاصة | G103: =A103 -> 21 | I103: =A103 -> 21
A104: يتم تقديم تقرير مفصل من قبل المقاول عند كل دفعة يتم تقديمها ويكون التقرير شامل لكافة الاعمال المنجزة والجارية وموضحة بالصور والتفاصيل اللازمة .
A105: 22 | B105: اختيار مواد التشطيب | G105: =A105 -> 22 | I105: =A105 -> 22
A106: يجب على المالك اختيار المواصفات المتعلقة به تجنبا للتأخير وذلك يتم بالتنسيق مع الاستشاري لكل مرحلة وبند على حدى , في حالة تأخير المالك فان المقاول لا يتحمل أي مسوولية.
A107: 23 | B107: المناقصة | G107: =A107 -> 23 | I107: =A107 -> 23
A108: يتم تقديم المناقصة من قبل المقاول للاستشاري بكامل تفاصيلها من حساب كميات والمخططات و 3D مع ختم وتوقيع على كل ورقة او مخطط يتم تقديمه معرفا بالتاريخ .
A109: 24 | B109: الدفعه الختامية | G109: =A109 -> 24 | I109: =A109 -> 24
A110: لا يتم اعتماد الدفعه الختامية وصرفها للمقاول الا بعد استيفاء الاتي:
A111: رخصة البناء الاصلية.
A112: مفاتيح المبنى الداخلية والخارجية.
A113: جدول الأحمال الخاص بتوصيل الكهرباء والماء
A114: عدم ممانعه من البلدية بتوصيل الكهرباء والماء
A115: خطاب ضمان الطبقات العازلة لمدة 25 سنوات
A116: خطاب ضمان اعمال الدهانات لمدة 3 سنوات
A117: خطاب ضمان خزانات المياه لمدة 3 سنوات
A118: خطاب ضمان الاجهزة (سخانات + مراوح شفط + المضخات) (اذا كانت من ضمن الأعمال المشمولة بعقده)
A119: ضمان البلاستر الداخلي العازل 10 سنوات
A121: 25 | B121: الالتزام بدفع الضريبة | G121: =A121 -> 25 | I121: =A121 -> 25
A122: يلتزم كل الأطراف المساهمون في هذا المشروع بمتطلبات المرسوم بقانون اتحادي رقم (08) لسنة 2018 .ولائحته التنفيذية المعلنة و اللذان ينظمان ضريبة القيمة المضافة ( VAT ) و تطبيقها في دولة الامارات حيث تحتسب نسبة 5% يلتزم المالك بسداد هذة النسبه للمقاول والاستشاري مع كل دفعة مستحقة .
A123: 26 | B123: شيك الضمان | G123: =A123 -> 26 | I123: =A123 -> 26
A124: على المقاول تحرير شيك ضمان باسم المالك بقيمة الدفعة الاولى يسلم لدى الاستشاري و يحفظ عند الاستشاري حتي التسليم الابتدائي .
...

Sheet جدوا زمني
A1: سافانا للإستــــشارات الهــــندسية
A3: مشروع انشاء وانجاز | N3: =المدخلات!P4 -> فيلا دور أرضي و اول وسور
A5: المالك: | N5: =المدخلات!P3 -> احمد ابراهيم النعيمي
A6: المقاول: | N6: =المدخلات!AR10 -> 0
A7: على القسيمة رقم | G7: =المدخلات!AR4 -> 0 | P7: في منطقة | T7: =المدخلات!AR3 -> 0 | Z7: بإمارة | AD7: =[4]INPUT!C7 -> راس الخيمة
A8: قيمة العقد كامل مع ضريبة | Z8: ='حساب الكميات'!$AO$243 -> 71048.25
A10: دفعة خاصة بالمالك | Z10: =Z8-800000 -> -728951.75
B12: التاريخ | G12: =المدخلات!$AR$7 -> 46021 | N12: جدول الدفعات | AA12: دفعة رقم | AH12: 1
A13: الرقم | C13: بيان الاعمال | V13: النسبة الدفعة | X13: نسبة الانجاز | AB13: المدة الزمنية | AG13: الدفعة مع الضريبة
A14: 1 | C14: دفعة مقدمة | N14: مقدم | S14: =AG14/Z8 -> -3.8987824 | V14: 0.38 | AG14: =Z10*V14 -> -277001.66
A15: 2 | C15: تجهيز الموقع | V15: 0 | AB15: 15 | AG15: =Z8*V15 -> 0 | BK15: 800000
A16: 3 | C16: الحفر | V16: 0 | AB16: 5 | AG16: 0
A17: 4 | C17: صب القواعد | V17: 0 | AB17: 20 | AG17: 0
A18: 5 | C18: صب الجسور الارضية | L18: بعد صب الجسور يتم تقديم دفعة بنك | V18: 0 | AB18: 20 | AG18: 0 | AY18: دفغات الاسكان
A19: 6 | C19: صب سقف الدور الارضي | V19: 0.06 | AB19: 48 | AG19: =Z10*V19 -> -43737.105
A20: 7 | C20: صب سقف الدور الاول | L20: بعد صب سقف الاول يتم تقديم دفعة بنك | V20: 0.06 | AB20: 48 | AG20: =Z10*V20 -> -43737.105 | AY20: صبية نظافة | BG20: 0.18 | BM20: =BG20*BK15 -> 144000
A21: 8 | C21: تنفيد اعمال الطابوق الارضي | V21: 0.02 | AB21: 30 | AG21: =Z10*V21 -> -14579.035 | AY21: سقف اارضي | BG21: 0.1 | BM21: =BG21*BK15 -> 80000
A22: 9 | C22: تنفيد اعمال الطابوق الاول | L22: بعد انتهاء مناعمال الطابوق يتم تقديم دفعة بنك | V22: 0.02 | AB22: 30 | AG22: =Z10*V22 -> -14579.035 | AY22: سقف اول | BG22: 0.12 | BM22: =BG22*BK15 -> 96000
A23: 10 | C23: تجهيز التمديدات الكهربايىة والصحية في الجدران | V23: 0.02 | AB23: 30 | AG23: =Z10*V23 -> -14579.035 | AY23: طابوق | BG23: 0.02 | BM23: =BG23*BK15 -> 16000
A24: 12 | C24: اعمال البلاستر الخارجي | V24: 0.02 | AB24: 45 | AG24: =Z10*V24 -> -14579.035 | AY24: بلاستر | BG24: 0.03 | BM24: =BG24*BK15 -> 24000
A25: 13 | C25: اعمال سيراميك جدران الحمامات | V25: 0.02 | AB25: 25 | AG25: =Z10*V25 -> -14579.035 | AY25: بلاستر | BG25: 0 | BM25: =BG25*BK15 -> 0
A26: 14 | C26: اعمال البلاسترالعازل الداخلي | V26: 0.02 | AB26: 30 | AG26: =Z10*V26 -> -14579.035 | AY26: مجموع | BG26: =SUM(BG20:BL25) -> 0.45 | BM26: =SUM(BM20:BT25) -> 360000
A27: 0 | V27: =V26+V25+V24+V23+V22+V21+V20+V19+V18+V17+V16+V15+V14 -> 0.62 | AB27: =SUM(AB17:AF26) -> 326 | AG27: =SUM(AG14:AI26) -> -451950.08 | AY27: برنامج | BM27: =BM26-80000 -> 280000
A28: 15 | C28: تجهيز التمديدات الكهربايىة والصحية في الارضيات | V28: 0.05 | AB28: 20 | AG28: =V28*Z10 -> -36447.588
A29: 16 | C29: أعمال العزل للحمامات و السطح | V29: 0.05 | AB29: 15 | AG29: =V29*Z10 -> -36447.588 | AY29: خاص | BM29: =AG27 -> -451950.08
A30: 17 | C30: تركيب سيراميك الارضي | V30: 0.04 | AB30: 35 | AG30: =V30*Z10 -> -29158.07
A31: 18 | C31: تركيب سيراميك الاول | V31: 0.03 | AB31: 35 | AG31: =V31*Z10 -> -21868.552 | AY31: مجموع | BM31: =BM27+BM29 -> -171950.08
A32: 19 | C32: الانتهاء من تركيب الحجر في الواجهات | V32: 0.08 | AB32: 50 | AG32: =V32*Z10 -> -58316.14
A33: 20 | C33: الانتهاء الالومنيوم والزجاج | V33: 0.04 | AB33: 25 | AG33: =V33*Z10 -> -29158.07 | AY33: المبلغ المفترض يكون مدفوع | BM33: =CA37-CA39 -> 41
A34: 21 | C34: الانتهاء من الاعمال الكهربائية للتسليم | V34: 0.04 | AB34: 20 | AG34: =V34*Z10 -> -29158.07
A35: 22 | C35: الانتهاء من الصبغ الخارجي | V35: 0.04 | AB35: 20 | AG35: =V35*Z10 -> -29158.07 | AY35: الفرق | BM35: =BM31-BM33 -> -171991.08
A36: 23 | C36: تركيب الاطقم الصحية | V36: 0.01 | AB36: 5 | AG36: =V36*Z10 -> -7289.5175
A37: 24 | C37: اعمال الملحق تبدا مع اعمال سيراميك الفيلا | V37: 0 | AB37: 0 | AG37: =V37*Z10 -> 0 | CA37: ='حساب الكميات'!$AO$107 -> 49
A38: 25
A39: قيمة الدفعات | V39: =SUM(V27:W38) -> 1 | AB39: =SUM(AB27:AF38) -> 551 | CA39: ='حساب الكميات'!$AO$106 -> 8
A40: قيمة الضريبة | AB40: =AB39/30 -> 18.366667 | AG40: =SUM(AG27:AI39) -> -728951.75
A41: المجموع الكامل
A42: المالك | M42: الاستشاري | Z42: المقاول
R308: .

Sheet جدول دفعات
A1: سافانا للإستــــشارات الهــــندسية
A3: مشروع انشاء وانجاز | N3: =المدخلات!P4 -> فيلا دور أرضي و اول وسور
A5: المالك: | N5: =المدخلات!P3 -> احمد ابراهيم النعيمي
A6: المقاول: | N6: =المدخلات!AR10 -> 0
A7: على القسيمة رقم | G7: =المدخلات!AR4 -> 0 | P7: في منطقة | T7: =المدخلات!AR3 -> 0 | Z7: بإمارة | AD7: =[4]INPUT!C7 -> راس الخيمة
A8: قيمة العقد كامل بدون ضريبة | Z8: ='حساب الكميات'!AY232 -> 67665
A10: قيمة الضريبة | Z10: =Z8*0.05 -> 3383.25
B12: التاريخ | G12: =المدخلات!P14 -> 0 | N12: جدول الدفعات
A13: الرقم | C13: بيان الاعمال | V13: النسبة | X13: دفعة العقد | AG13: الضريبة
A14: 1 | C14: دفعه مقدمة | V14: 0.15 | X14: =Z8*V14 -> 10149.75 | AG14: =0.05*(AB14+X14) -> 507.4875
A15: 2 | C15: دفعة بعد صب الجسور الأرضية و صبة النظافة الدور الأرضي | V15: 0.08 | X15: =$Z$8*V15 -> 5413.2 | AG15: =0.05*(AB15+X15) -> 270.66
A16: 3 | C16: دفعة بعد صب اعمدة الدور الأرضي | V16: 0.07 | X16: =$Z$8*V16 -> 4736.55 | AG16: =0.05*(AB16+X16) -> 236.8275
A17: 4 | C17: دفعة بعد صب سقف الدور الارضي | V17: 0.08 | X17: =$Z$8*V17 -> 5413.2 | AG17: =0.05*(AB17+X17) -> 270.66
A18: 5 | C18: دفعة بعد صب أعمدة وسقف الدور الأول | V18: 0.1 | X18: =$Z$8*V18 -> 6766.5 | AG18: =0.05*(AB18+X18) -> 338.325
A19: 6 | C19: دفعة بعد الانتهاء من تنفيد اعمال الطابوق | V19: 0.07 | X19: =$Z$8*V19 -> 4736.55 | AG19: =0.05*(AB19+X19) -> 236.8275
A20: 7 | C20: دفعة بعد الانتهاء من اعمال البلاستر الداخلي للارضي | V20: 0.04 | X20: =$Z$8*V20 -> 2706.6 | AG20: =0.05*(AB20+X20) -> 135.33 | AM20: =V22=V21=V20=V19=V18=V17=V16=V15=V14 -> FALSE
A21: 8 | C21: دفعة بعد الانتهاء من اعمال البلاستر الداخلي للاول | V21: 0.04 | X21: =$Z$8*V21 -> 2706.6 | AG21: =0.05*(AB21+X21) -> 135.33
A22: 9 | C22: دفعة بعد الانتهاء من البلاستر الخارجي | V22: 0.06 | X22: =$Z$8*V22 -> 4059.9 | AG22: =0.05*(AB22+X22) -> 202.995
A23: 10 | C23: دفعة بعد الانتهاء من أعمال العزل | V23: 0.08 | X23: =$Z$8*V23 -> 5413.2 | AG23: =0.05*(AB23+X23) -> 270.66
A24: 11 | C24: دفعة بعد الانتهاء من تركيب سيراميك الارضي | V24: 0.02 | X24: =$Z$8*V24 -> 1353.3 | AG24: =0.05*(AB24+X24) -> 67.665
A25: 12 | C25: دفعة بعد الانتهاء من تركيب سيراميك الاول | V25: 0.02 | X25: =$Z$8*V25 -> 1353.3 | AG25: =0.05*(AB25+X25) -> 67.665
A26: 13 | C26: دفعة بعد الانتهاء الالومنيوم والزجاج | V26: 0 | X26: =$Z$8*V26 -> 0 | AG26: =0.05*(AB26+X26) -> 0
A27: 14 | C27: دفعة بعد تركيب الاعمال الصحية | V27: 0.02 | X27: =$Z$8*V27 -> 1353.3 | AG27: =0.05*(AB27+X27) -> 67.665
A28: 15 | C28: دفعة بعد الانتهاء من الاعمال الكهربائية | V28: 0.08 | X28: =$Z$8*V28 -> 5413.2 | AG28: =0.05*(AB28+X28) -> 270.66
A29: 16 | C29: دفعة بعد الانتهاء من الصبغ الخارجي | V29: 0 | X29: =$Z$8*V29 -> 0 | AG29: =0.05*(AB29+X29) -> 0
A30: 17 | C30: دفعة بعد الانتهاء من الاعمال تحت ارضية للسور | V30: 0.04 | X30: =$Z$8*V30 -> 2706.6 | AG30: =0.05*(AB30+X30) -> 135.33
A31: 18 | C31: دفعة بعد الانتهاء من الاعمال فوق ارضية للسور | V31: 0.04 | X31: =$Z$8*V31 -> 2706.6 | AG31: =0.05*(AB31+X31) -> 135.33
A32: 19 | C32: دفعة بعد الانتهاء من تنظيف الموقع | V32: 0.01 | X32: =$Z$8*V32 -> 676.65 | AG32: =0.05*(AB32+X32) -> 33.8325
A33: قيمة الدفعات | V33: =SUM(V14:W32) -> 1 | X33: =SUM(X14:AA32) -> 67665 | AG33: =0.05*(AB33+X33) -> 3383.25
A34: قيمة الضريبة | V34: 0.05 | X34: =X33*V34 -> 3383.25 | AB34: =AB33*V34 -> 0
A35: المجموع الكامل | P35: =X33+X34+AB33+AB34 -> 71048.25
A36: المالك | M36: الاستشاري | Z36: المقاول
R302: .

Sheet  اكميات بنك بدون سور 
B2: حساب كميات المشروع
B3: معلومات المشروع
B4: المالك | O4: =المدخلات!$P$3 -> احمد ابراهيم النعيمي | AC4: المنطقة | AQ4: =المدخلات!$P$11 -> الخران
B5: وصف المشروع | O5: =المدخلات!$P$4 -> فيلا دور أرضي و اول وسور | AC5: رقم القسيمة | AQ5: =المدخلات!$P$12 -> 403100010
B6: مساحة البناء بالمتر المربع | O6: =المدخلات!$AR$5 -> 118 | AC6: مساحة البناء بالقدم المربع | AQ6: =المدخلات!$AY$5 -> 5549
B25: بيانات المقاول
B26: اسم الشركة: | O26: =المدخلات!$AR$3 -> 0 | AC26: المهندس المسؤول: | AQ26: =المدخلات!$AR$6 -> 0
B27: تاريخ المناقصة: | O27: =المدخلات!$AR$7 -> 46021 | AC27: رقم الهاتف: | AQ27: =المدخلات!$AR$11 -> 0
B28: رقم رخصة المقاول: | O28: =المدخلات!$AR$4 -> 0 | AC28: مدة تنفيذ المشروع: | AQ28: =المدخلات!$AR$9 -> 14 شهر
B30: عرض السعر | AQ30: ختم الشركة العارضة
B31: تكلفة انشاء وانجاز الفيلا | AC31: =AO202+AO210 -> 704000
B32: تكلفة انشاء وإنجاز السور | AC32: =AO213 -> 0
B33: تكلفة انشاء وإنجاز الفيلا مع السور | AC33: =AO220 -> 704000
B38: أولا : أعمال الهيكل
B39: (A) أعمال المياه الجوفية والتربة
B40: الرقم | E40: البند | AO40: الوحدة | AS40: الكمية | AW40: السعر | BA40: الإجمالي
B41: A1 | C41: B1 | D41: B1 | E41: أعمال تجفيف المياه الجوفية إن وجدت حسب فحص التربة | F41: عزل الأسقف نوعية ألتك يسعر الفرق فقط | G41: عزل الأسقف نوعية ألتك يسعر الفرق فقط | H41: عزل الأسقف نوعية ألتك يسعر الفرق فقط | I41: عزل الأسقف نوعية ألتك يسعر الفرق فقط | J41: عزل الأسقف نوعية ألتك يسعر الفرق فقط | K41: عزل الأسقف نوعية ألتك يسعر الفرق فقط | L41: عزل الأسقف نوعية ألتك يسعر الفرق فقط | M41: عزل الأسقف نوعية ألتك يسعر الفرق فقط | N41: عزل الأسقف نوعية ألتك يسعر الفرق فقط | O41: عزل الأسقف نوعية ألتك يسعر الفرق فقط | P41: عزل الأسقف نوعية ألتك يسعر الفرق فقط | Q41: عزل الأسقف نوعية ألتك يسعر الفرق فقط | R41: عزل الأسقف نوعية ألتك يسعر الفرق فقط | S41: عزل الأسقف نوعية ألتك يسعر الفرق فقط | T41: عزل الأسقف نوعية ألتك يسعر الفرق فقط | U41: عزل الأسقف نوعية ألتك يسعر الفرق فقط | V41: عزل الأسقف نوعية ألتك يسعر الفرق فقط | W41: عزل الأسقف نوعية ألتك يسعر الفرق فقط | X41: عزل الأسقف نوعية ألتك يسعر الفرق فقط | Y41: عزل الأسقف نوعية ألتك يسعر الفرق فقط | Z41: عزل الأسقف نوعية ألتك يسعر الفرق فقط | AA41: عزل الأسقف نوعية ألتك يسعر الفرق فقط | AB41: عزل الأسقف نوعية ألتك يسعر الفرق فقط | AC41: عزل الأسقف نوعية ألتك يسعر الفرق فقط | AD41: عزل الأسقف نوعية ألتك يسعر الفرق فقط | AE41: عزل الأسقف نوعية ألتك يسعر الفرق فقط | AF41: عزل الأسقف نوعية ألتك يسعر الفرق فقط | AG41: عزل الأسقف نوعية ألتك يسعر الفرق فقط | AH41: عزل الأسقف نوعية ألتك يسعر الفرق فقط | AI41: عزل الأسقف نوعية ألتك يسعر الفرق فقط | AJ41: عزل الأسقف نوعية ألتك يسعر الفرق فقط | AK41: عزل الأسقف نوعية ألتك يسعر الفرق فقط | AL41: عزل الأسقف نوعية ألتك يسعر الفرق فقط | AM41: عزل الأسقف نوعية ألتك يسعر الفرق فقط | AN41: عزل الأسقف نوعية ألتك يسعر الفرق فقط | AO41: L.S | AP41: M2 | AQ41: M2 | AR41: M2 | AS41: 0 | AW41: 0 | BA41: =AW41*AS41 -> 0
B42: A2 | C42: B2 | D42: B2 | E42: أعمال إحلال التربة إن وجدت حسب فحص التربة | F42: الأسمنت بلاستر للحوائط الداخلية. | G42: الأسمنت بلاستر للحوائط الداخلية. | H42: الأسمنت بلاستر للحوائط الداخلية. | I42: الأسمنت بلاستر للحوائط الداخلية. | J42: الأسمنت بلاستر للحوائط الداخلية. | K42: الأسمنت بلاستر للحوائط الداخلية. | L42: الأسمنت بلاستر للحوائط الداخلية. | M42: الأسمنت بلاستر للحوائط الداخلية. | N42: الأسمنت بلاستر للحوائط الداخلية. | O42: الأسمنت بلاستر للحوائط الداخلية. | P42: الأسمنت بلاستر للحوائط الداخلية. | Q42: الأسمنت بلاستر للحوائط الداخلية. | R42: الأسمنت بلاستر للحوائط الداخلية. | S42: الأسمنت بلاستر للحوائط الداخلية. | T42: الأسمنت بلاستر للحوائط الداخلية. | U42: الأسمنت بلاستر للحوائط الداخلية. | V42: الأسمنت بلاستر للحوائط الداخلية. | W42: الأسمنت بلاستر للحوائط الداخلية. | X42: الأسمنت بلاستر للحوائط الداخلية. | Y42: الأسمنت بلاستر للحوائط الداخلية. | Z42: الأسمنت بلاستر للحوائط الداخلية. | AA42: الأسمنت بلاستر للحوائط الداخلية. | AB42: الأسمنت بلاستر للحوائط الداخلية. | AC42: الأسمنت بلاستر للحوائط الداخلية. | AD42: الأسمنت بلاستر للحوائط الداخلية. | AE42: الأسمنت بلاستر للحوائط الداخلية. | AF42: الأسمنت بلاستر للحوائط الداخلية. | AG42: الأسمنت بلاستر للحوائط الداخلية. | AH42: الأسمنت بلاستر للحوائط الداخلية. | AI42: الأسمنت بلاستر للحوائط الداخلية. | AJ42: الأسمنت بلاستر للحوائط الداخلية. | AK42: الأسمنت بلاستر للحوائط الداخلية. | AL42: الأسمنت بلاستر للحوائط الداخلية. | AM42: الأسمنت بلاستر للحوائط الداخلية. | AN42: الأسمنت بلاستر للحوائط الداخلية. | AO42: L.S | AP42: M2 | AQ42: M2 | AR42: M2 | AS42: 0 | AW42: 0 | BA42: =AW42*AS42 -> 0
B43: (A) إجمالي سعر أعمال المياه الجوفية والتربة | AO43: =SUM(BA41:BD42) -> 0
B45: (B) أعمال تحضير وتجهيز الموقع
B46: الرقم | E46: البند | AO46: الوحدة | AS46: الكمية | AW46: السعر | BA46: الإجمالي
B47: B1 | C47: B1 | D47: B1 | E47: تجهيز الموقع السور المؤقت | F47: عزل الأسقف نوعية ألتك يسعر الفرق فقط | G47: عزل الأسقف نوعية ألتك يسعر الفرق فقط | H47: عزل الأسقف نوعية ألتك يسعر الفرق فقط | I47: عزل الأسقف نوعية ألتك يسعر الفرق فقط | J47: عزل الأسقف نوعية ألتك يسعر الفرق فقط | K47: عزل الأسقف نوعية ألتك يسعر الفرق فقط | L47: عزل الأسقف نوعية ألتك يسعر الفرق فقط | M47: عزل الأسقف نوعية ألتك يسعر الفرق فقط | N47: عزل الأسقف نوعية ألتك يسعر الفرق فقط | O47: عزل الأسقف نوعية ألتك يسعر الفرق فقط | P47: عزل الأسقف نوعية ألتك يسعر الفرق فقط | Q47: عزل الأسقف نوعية ألتك يسعر الفرق فقط | R47: عزل الأسقف نوعية ألتك يسعر الفرق فقط | S47: عزل الأسقف نوعية ألتك يسعر الفرق فقط | T47: عزل الأسقف نوعية ألتك يسعر الفرق فقط | U47: عزل الأسقف نوعية ألتك يسعر الفرق فقط | V47: عزل الأسقف نوعية ألتك يسعر الفرق فقط | W47: عزل الأسقف نوعية ألتك يسعر الفرق فقط | X47: عزل الأسقف نوعية ألتك يسعر الفرق فقط | Y47: عزل الأسقف نوعية ألتك يسعر الفرق فقط | Z47: عزل الأسقف نوعية ألتك يسعر الفرق فقط | AA47: عزل الأسقف نوعية ألتك يسعر الفرق فقط | AB47: عزل الأسقف نوعية ألتك يسعر الفرق فقط | AC47: عزل الأسقف نوعية ألتك يسعر الفرق فقط | AD47: عزل الأسقف نوعية ألتك يسعر الفرق فقط | AE47: عزل الأسقف نوعية ألتك يسعر الفرق فقط | AF47: عزل الأسقف نوعية ألتك يسعر الفرق فقط | AG47: عزل الأسقف نوعية ألتك يسعر الفرق فقط | AH47: عزل الأسقف نوعية ألتك يسعر الفرق فقط | AI47: عزل الأسقف نوعية ألتك يسعر الفرق فقط | AJ47: عزل الأسقف نوعية ألتك يسعر الفرق فقط | AK47: عزل الأسقف نوعية ألتك يسعر الفرق فقط | AL47: عزل الأسقف نوعية ألتك يسعر الفرق فقط | AM47: عزل الأسقف نوعية ألتك يسعر الفرق فقط | AN47: عزل الأسقف نوعية ألتك يسعر الفرق فقط | AO47: مقطوغ | AP47: M2 | AQ47: M2 | AR47: M2 | AS47: - | AW47: - | BA47: -
B48: B2 | C48: B1 | D48: B1 | E48: اللوحة الخارجية (بيانات المشروع) | F48: عزل الأسقف نوعية ألتك يسعر الفرق فقط | G48: عزل الأسقف نوعية ألتك يسعر الفرق فقط | H48: عزل الأسقف نوعية ألتك يسعر الفرق فقط | I48: عزل الأسقف نوعية ألتك يسعر الفرق فقط | J48: عزل الأسقف نوعية ألتك يسعر الفرق فقط | K48: عزل الأسقف نوعية ألتك يسعر الفرق فقط | L48: عزل الأسقف نوعية ألتك يسعر الفرق فقط | M48: عزل الأسقف نوعية ألتك يسعر الفرق فقط | N48: عزل الأسقف نوعية ألتك يسعر الفرق فقط | O48: عزل الأسقف نوعية ألتك يسعر الفرق فقط | P48: عزل الأسقف نوعية ألتك يسعر الفرق فقط | Q48: عزل الأسقف نوعية ألتك يسعر الفرق فقط | R48: عزل الأسقف نوعية ألتك يسعر الفرق فقط | S48: عزل الأسقف نوعية ألتك يسعر الفرق فقط | T48: عزل الأسقف نوعية ألتك يسعر الفرق فقط | U48: عزل الأسقف نوعية ألتك يسعر الفرق فقط | V48: عزل الأسقف نوعية ألتك يسعر الفرق فقط | W48: عزل الأسقف نوعية ألتك يسعر الفرق فقط | X48: عزل الأسقف نوعية ألتك يسعر الفرق فقط | Y48: عزل الأسقف نوعية ألتك يسعر الفرق فقط | Z48: عزل الأسقف نوعية ألتك يسعر الفرق فقط | AA48: عزل الأسقف نوعية ألتك يسعر الفرق فقط | AB48: عزل الأسقف نوعية ألتك يسعر الفرق فقط | AC48: عزل الأسقف نوعية ألتك يسعر الفرق فقط | AD48: عزل الأسقف نوعية ألتك يسعر الفرق فقط | AE48: عزل الأسقف نوعية ألتك يسعر الفرق فقط | AF48: عزل الأسقف نوعية ألتك يسعر الفرق فقط | AG48: عزل الأسقف نوعية ألتك يسعر الفرق فقط | AH48: عزل الأسقف نوعية ألتك يسعر الفرق فقط | AI48: عزل الأسقف نوعية ألتك يسعر الفرق فقط | AJ48: عزل الأسقف نوعية ألتك يسعر الفرق فقط | AK48: عزل الأسقف نوعية ألتك يسعر الفرق فقط | AL48: عزل الأسقف نوعية ألتك يسعر الفرق فقط | AM48: عزل الأسقف نوعية ألتك يسعر الفرق فقط | AN48: عزل الأسقف نوعية ألتك يسعر الفرق فقط | AO48: مقطوغ | AP48: M2 | AQ48: M2 | AR48: M2 | AS48: - | AW48: - | BA48: -
B49: B3 | C49: B1 | D49: B1 | E49: إزالة المباني القديمة (ان وجدت) | F49: عزل الأسقف نوعية ألتك يسعر الفرق فقط | G49: عزل الأسقف نوعية ألتك يسعر الفرق فقط | H49: عزل الأسقف نوعية ألتك يسعر الفرق فقط | I49: عزل الأسقف نوعية ألتك يسعر الفرق فقط | J49: عزل الأسقف نوعية ألتك يسعر الفرق فقط | K49: عزل الأسقف نوعية ألتك يسعر الفرق فقط | L49: عزل الأسقف نوعية ألتك يسعر الفرق فقط | M49: عزل الأسقف نوعية ألتك يسعر الفرق فقط | N49: عزل الأسقف نوعية ألتك يسعر الفرق فقط | O49: عزل الأسقف نوعية ألتك يسعر الفرق فقط | P49: عزل الأسقف نوعية ألتك يسعر الفرق فقط | Q49: عزل الأسقف نوعية ألتك يسعر الفرق فقط | R49: عزل الأسقف نوعية ألتك يسعر الفرق فقط | S49: عزل الأسقف نوعية ألتك يسعر الفرق فقط | T49: عزل الأسقف نوعية ألتك يسعر الفرق فقط | U49: عزل الأسقف نوعية ألتك يسعر الفرق فقط | V49: عزل الأسقف نوعية ألتك يسعر الفرق فقط | W49: عزل الأسقف نوعية ألتك يسعر الفرق فقط | X49: عزل الأسقف نوعية ألتك يسعر الفرق فقط | Y49: عزل الأسقف نوعية ألتك يسعر الفرق فقط | Z49: عزل الأسقف نوعية ألتك يسعر الفرق فقط | AA49: عزل الأسقف نوعية ألتك يسعر الفرق فقط | AB49: عزل الأسقف نوعية ألتك يسعر الفرق فقط | AC49: عزل الأسقف نوعية ألتك يسعر الفرق فقط | AD49: عزل الأسقف نوعية ألتك يسعر الفرق فقط | AE49: عزل الأسقف نوعية ألتك يسعر الفرق فقط | AF49: عزل الأسقف نوعية ألتك يسعر الفرق فقط | AG49: عزل الأسقف نوعية ألتك يسعر الفرق فقط | AH49: عزل الأسقف نوعية ألتك يسعر الفرق فقط | AI49: عزل الأسقف نوعية ألتك يسعر الفرق فقط | AJ49: عزل الأسقف نوعية ألتك يسعر الفرق فقط | AK49: عزل الأسقف نوعية ألتك يسعر الفرق فقط | AL49: عزل الأسقف نوعية ألتك يسعر الفرق فقط | AM49: عزل الأسقف نوعية ألتك يسعر الفرق فقط | AN49: عزل الأسقف نوعية ألتك يسعر الفرق فقط | AO49: مقطوغ | AP49: M2 | AQ49: M2 | AR49: M2 | AS49: - | AW49: - | BA49: -
B50: B4 | C50: B1 | D50: B1 | E50: الخدمات المؤقته (كهرباء , ماء , الخ) | F50: عزل الأسقف نوعية ألتك يسعر الفرق فقط | G50: عزل الأسقف نوعية ألتك يسعر الفرق فقط | H50: عزل الأسقف نوعية ألتك يسعر الفرق فقط | I50: عزل الأسقف نوعية ألتك يسعر الفرق فقط | J50: عزل الأسقف نوعية ألتك يسعر الفرق فقط | K50: عزل الأسقف نوعية ألتك يسعر الفرق فقط | L50: عزل الأسقف نوعية ألتك يسعر الفرق فقط | M50: عزل الأسقف نوعية ألتك يسعر الفرق فقط | N50: عزل الأسقف نوعية ألتك يسعر الفرق فقط | O50: عزل الأسقف نوعية ألتك يسعر الفرق فقط | P50: عزل الأسقف نوعية ألتك يسعر الفرق فقط | Q50: عزل الأسقف نوعية ألتك يسعر الفرق فقط | R50: عزل الأسقف نوعية ألتك يسعر الفرق فقط | S50: عزل الأسقف نوعية ألتك يسعر الفرق فقط | T50: عزل الأسقف نوعية ألتك يسعر الفرق فقط | U50: عزل الأسقف نوعية ألتك يسعر الفرق فقط | V50: عزل الأسقف نوعية ألتك يسعر الفرق فقط | W50: عزل الأسقف نوعية ألتك يسعر الفرق فقط | X50: عزل الأسقف نوعية ألتك يسعر الفرق فقط | Y50: عزل الأسقف نوعية ألتك يسعر الفرق فقط | Z50: عزل الأسقف نوعية ألتك يسعر الفرق فقط | AA50: عزل الأسقف نوعية ألتك يسعر الفرق فقط | AB50: عزل الأسقف نوعية ألتك يسعر الفرق فقط | AC50: عزل الأسقف نوعية ألتك يسعر الفرق فقط | AD50: عزل الأسقف نوعية ألتك يسعر الفرق فقط | AE50: عزل الأسقف نوعية ألتك يسعر الفرق فقط | AF50: عزل الأسقف نوعية ألتك يسعر الفرق فقط | AG50: عزل الأسقف نوعية ألتك يسعر الفرق فقط | AH50: عزل الأسقف نوعية ألتك يسعر الفرق فقط | AI50: عزل الأسقف نوعية ألتك يسعر الفرق فقط | AJ50: عزل الأسقف نوعية ألتك يسعر الفرق فقط | AK50: عزل الأسقف نوعية ألتك يسعر الفرق فقط | AL50: عزل الأسقف نوعية ألتك يسعر الفرق فقط | AM50: عزل الأسقف نوعية ألتك يسعر الفرق فقط | AN50: عزل الأسقف نوعية ألتك يسعر الفرق فقط | AO50: مقطوغ | AP50: M2 | AQ50: M2 | AR50: M2 | AS50: - | AW50: - | BA50: -
B51: B5 | C51: B1 | D51: B1 | E51: اعمال فحص التربة (حسب المواصفات) | F51: عزل الأسقف نوعية ألتك يسعر الفرق فقط | G51: عزل الأسقف نوعية ألتك يسعر الفرق فقط | H51: عزل الأسقف نوعية ألتك يسعر الفرق فقط | I51: عزل الأسقف نوعية ألتك يسعر الفرق فقط | J51: عزل الأسقف نوعية ألتك يسعر الفرق فقط | K51: عزل الأسقف نوعية ألتك يسعر الفرق فقط | L51: عزل الأسقف نوعية ألتك يسعر الفرق فقط | M51: عزل الأسقف نوعية ألتك يسعر الفرق فقط | N51: عزل الأسقف نوعية ألتك يسعر الفرق فقط | O51: عزل الأسقف نوعية ألتك يسعر الفرق فقط | P51: عزل الأسقف نوعية ألتك يسعر الفرق فقط | Q51: عزل الأسقف نوعية ألتك يسعر الفرق فقط | R51: عزل الأسقف نوعية ألتك يسعر الفرق فقط | S51: عزل الأسقف نوعية ألتك يسعر الفرق فقط | T51: عزل الأسقف نوعية ألتك يسعر الفرق فقط | U51: عزل الأسقف نوعية ألتك يسعر الفرق فقط | V51: عزل الأسقف نوعية ألتك يسعر الفرق فقط | W51: عزل الأسقف نوعية ألتك يسعر الفرق فقط | X51: عزل الأسقف نوعية ألتك يسعر الفرق فقط | Y51: عزل الأسقف نوعية ألتك يسعر الفرق فقط | Z51: عزل الأسقف نوعية ألتك يسعر الفرق فقط | AA51: عزل الأسقف نوعية ألتك يسعر الفرق فقط | AB51: عزل الأسقف نوعية ألتك يسعر الفرق فقط | AC51: عزل الأسقف نوعية ألتك يسعر الفرق فقط | AD51: عزل الأسقف نوعية ألتك يسعر الفرق فقط | AE51: عزل الأسقف نوعية ألتك يسعر الفرق فقط | AF51: عزل الأسقف نوعية ألتك يسعر الفرق فقط | AG51: عزل الأسقف نوعية ألتك يسعر الفرق فقط | AH51: عزل الأسقف نوعية ألتك يسعر الفرق فقط | AI51: عزل الأسقف نوعية ألتك يسعر الفرق فقط | AJ51: عزل الأسقف نوعية ألتك يسعر الفرق فقط | AK51: عزل الأسقف نوعية ألتك يسعر الفرق فقط | AL51: عزل الأسقف نوعية ألتك يسعر الفرق فقط | AM51: عزل الأسقف نوعية ألتك يسعر الفرق فقط | AN51: عزل الأسقف نوعية ألتك يسعر الفرق فقط | AO51: مقطوغ | AP51: M2 | AQ51: M2 | AR51: M2 | AS51: - | AW51: - | BA51: -
B52: B6 | C52: B1 | D52: B1 | E52: الاختبارات واعتماد المواد حسب المواصفات | F52: عزل الأسقف نوعية ألتك يسعر الفرق فقط | G52: عزل الأسقف نوعية ألتك يسعر الفرق فقط | H52: عزل الأسقف نوعية ألتك يسعر الفرق فقط | I52: عزل الأسقف نوعية ألتك يسعر الفرق فقط | J52: عزل الأسقف نوعية ألتك يسعر الفرق فقط | K52: عزل الأسقف نوعية ألتك يسعر الفرق فقط | L52: عزل الأسقف نوعية ألتك يسعر الفرق فقط | M52: عزل الأسقف نوعية ألتك يسعر الفرق فقط | N52: عزل الأسقف نوعية ألتك يسعر الفرق فقط | O52: عزل الأسقف نوعية ألتك يسعر الفرق فقط | P52: عزل الأسقف نوعية ألتك يسعر الفرق فقط | Q52: عزل الأسقف نوعية ألتك يسعر الفرق فقط | R52: عزل الأسقف نوعية ألتك يسعر الفرق فقط | S52: عزل الأسقف نوعية ألتك يسعر الفرق فقط | T52: عزل الأسقف نوعية ألتك يسعر الفرق فقط | U52: عزل الأسقف نوعية ألتك يسعر الفرق فقط | V52: عزل الأسقف نوعية ألتك يسعر الفرق فقط | W52: عزل الأسقف نوعية ألتك يسعر الفرق فقط | X52: عزل الأسقف نوعية ألتك يسعر الفرق فقط | Y52: عزل الأسقف نوعية ألتك يسعر الفرق فقط | Z52: عزل الأسقف نوعية ألتك يسعر الفرق فقط | AA52: عزل الأسقف نوعية ألتك يسعر الفرق فقط | AB52: عزل الأسقف نوعية ألتك يسعر الفرق فقط | AC52: عزل الأسقف نوعية ألتك يسعر الفرق فقط | AD52: عزل الأسقف نوعية ألتك يسعر الفرق فقط | AE52: عزل الأسقف نوعية ألتك يسعر الفرق فقط | AF52: عزل الأسقف نوعية ألتك يسعر الفرق فقط | AG52: عزل الأسقف نوعية ألتك يسعر الفرق فقط | AH52: عزل الأسقف نوعية ألتك يسعر الفرق فقط | AI52: عزل الأسقف نوعية ألتك يسعر الفرق فقط | AJ52: عزل الأسقف نوعية ألتك يسعر الفرق فقط | AK52: عزل الأسقف نوعية ألتك يسعر الفرق فقط | AL52: عزل الأسقف نوعية ألتك يسعر الفرق فقط | AM52: عزل الأسقف نوعية ألتك يسعر الفرق فقط | AN52: عزل الأسقف نوعية ألتك يسعر الفرق فقط | AO52: مقطوغ | AP52: M2 | AQ52: M2 | AR52: M2 | AS52: - | AW52: - | BA52: -
B53: B7 | C53: B1 | D53: B1 | E53: المخططات التنفيذية لاعمال الخدمات | F53: عزل الأسقف نوعية ألتك يسعر الفرق فقط | G53: عزل الأسقف نوعية ألتك يسعر الفرق فقط | H53: عزل الأسقف نوعية ألتك يسعر الفرق فقط | I53: عزل الأسقف نوعية ألتك يسعر الفرق فقط | J53: عزل الأسقف نوعية ألتك يسعر الفرق فقط | K53: عزل الأسقف نوعية ألتك يسعر الفرق فقط | L53: عزل الأسقف نوعية ألتك يسعر الفرق فقط | M53: عزل الأسقف نوعية ألتك يسعر الفرق فقط | N53: عزل الأسقف نوعية ألتك يسعر الفرق فقط | O53: عزل الأسقف نوعية ألتك يسعر الفرق فقط | P53: عزل الأسقف نوعية ألتك يسعر الفرق فقط | Q53: عزل الأسقف نوعية ألتك يسعر الفرق فقط | R53: عزل الأسقف نوعية ألتك يسعر الفرق فقط | S53: عزل الأسقف نوعية ألتك يسعر الفرق فقط | T53: عزل الأسقف نوعية ألتك يسعر الفرق فقط | U53: عزل الأسقف نوعية ألتك يسعر الفرق فقط | V53: عزل الأسقف نوعية ألتك يسعر الفرق فقط | W53: عزل الأسقف نوعية ألتك يسعر الفرق فقط | X53: عزل الأسقف نوعية ألتك يسعر الفرق فقط | Y53: عزل الأسقف نوعية ألتك يسعر الفرق فقط | Z53: عزل الأسقف نوعية ألتك يسعر الفرق فقط | AA53: عزل الأسقف نوعية ألتك يسعر الفرق فقط | AB53: عزل الأسقف نوعية ألتك يسعر الفرق فقط | AC53: عزل الأسقف نوعية ألتك يسعر الفرق فقط | AD53: عزل الأسقف نوعية ألتك يسعر الفرق فقط | AE53: عزل الأسقف نوعية ألتك يسعر الفرق فقط | AF53: عزل الأسقف نوعية ألتك يسعر الفرق فقط | AG53: عزل الأسقف نوعية ألتك يسعر الفرق فقط | AH53: عزل الأسقف نوعية ألتك يسعر الفرق فقط | AI53: عزل الأسقف نوعية ألتك يسعر الفرق فقط | AJ53: عزل الأسقف نوعية ألتك يسعر الفرق فقط | AK53: عزل الأسقف نوعية ألتك يسعر الفرق فقط | AL53: عزل الأسقف نوعية ألتك يسعر الفرق فقط | AM53: عزل الأسقف نوعية ألتك يسعر الفرق فقط | AN53: عزل الأسقف نوعية ألتك يسعر الفرق فقط | AO53: مقطوغ | AP53: M2 | AQ53: M2 | AR53: M2 | AS53: - | AW53: - | BA53: -
B54: B8 | C54: B1 | D54: B1 | E54: المخططات الواقعية بعد التنفيذ | F54: عزل الأسقف نوعية ألتك يسعر الفرق فقط | G54: عزل الأسقف نوعية ألتك يسعر الفرق فقط | H54: عزل الأسقف نوعية ألتك يسعر الفرق فقط | I54: عزل الأسقف نوعية ألتك يسعر الفرق فقط | J54: عزل الأسقف نوعية ألتك يسعر الفرق فقط | K54: عزل الأسقف نوعية ألتك يسعر الفرق فقط | L54: عزل الأسقف نوعية ألتك يسعر الفرق فقط | M54: عزل الأسقف نوعية ألتك يسعر الفرق فقط | N54: عزل الأسقف نوعية ألتك يسعر الفرق فقط | O54: عزل الأسقف نوعية ألتك يسعر الفرق فقط | P54: عزل الأسقف نوعية ألتك يسعر الفرق فقط | Q54: عزل الأسقف نوعية ألتك يسعر الفرق فقط | R54: عزل الأسقف نوعية ألتك يسعر الفرق فقط | S54: عزل الأسقف نوعية ألتك يسعر الفرق فقط | T54: عزل الأسقف نوعية ألتك يسعر الفرق فقط | U54: عزل الأسقف نوعية ألتك يسعر الفرق فقط | V54: عزل الأسقف نوعية ألتك يسعر الفرق فقط | W54: عزل الأسقف نوعية ألتك يسعر الفرق فقط | X54: عزل الأسقف نوعية ألتك يسعر الفرق فقط | Y54: عزل الأسقف نوعية ألتك يسعر الفرق فقط | Z54: عزل الأسقف نوعية ألتك يسعر الفرق فقط | AA54: عزل الأسقف نوعية ألتك يسعر الفرق فقط | AB54: عزل الأسقف نوعية ألتك يسعر الفرق فقط | AC54: عزل الأسقف نوعية ألتك يسعر الفرق فقط | AD54: عزل الأسقف نوعية ألتك يسعر الفرق فقط | AE54: عزل الأسقف نوعية ألتك يسعر الفرق فقط | AF54: عزل الأسقف نوعية ألتك يسعر الفرق فقط | AG54: عزل الأسقف نوعية ألتك يسعر الفرق فقط | AH54: عزل الأسقف نوعية ألتك يسعر الفرق فقط | AI54: عزل الأسقف نوعية ألتك يسعر الفرق فقط | AJ54: عزل الأسقف نوعية ألتك يسعر الفرق فقط | AK54: عزل الأسقف نوعية ألتك يسعر الفرق فقط | AL54: عزل الأسقف نوعية ألتك يسعر الفرق فقط | AM54: عزل الأسقف نوعية ألتك يسعر الفرق فقط | AN54: عزل الأسقف نوعية ألتك يسعر الفرق فقط | AO54: مقطوغ | AP54: M2 | AQ54: M2 | AR54: M2 | AS54: - | AW54: - | BA54: -
B55: B9 | C55: B1 | D55: B1 | E55: تنسيق و تنظيف الموقع بعد نهاية العمل | F55: عزل الأسقف نوعية ألتك يسعر الفرق فقط | G55: عزل الأسقف نوعية ألتك يسعر الفرق فقط | H55: عزل الأسقف نوعية ألتك يسعر الفرق فقط | I55: عزل الأسقف نوعية ألتك يسعر الفرق فقط | J55: عزل الأسقف نوعية ألتك يسعر الفرق فقط | K55: عزل الأسقف نوعية ألتك يسعر الفرق فقط | L55: عزل الأسقف نوعية ألتك يسعر الفرق فقط | M55: عزل الأسقف نوعية ألتك يسعر الفرق فقط | N55: عزل الأسقف نوعية ألتك يسعر الفرق فقط | O55: عزل الأسقف نوعية ألتك يسعر الفرق فقط | P55: عزل الأسقف نوعية ألتك يسعر الفرق فقط | Q55: عزل الأسقف نوعية ألتك يسعر الفرق فقط | R55: عزل الأسقف نوعية ألتك يسعر الفرق فقط | S55: عزل الأسقف نوعية ألتك يسعر الفرق فقط | T55: عزل الأسقف نوعية ألتك يسعر الفرق فقط | U55: عزل الأسقف نوعية ألتك يسعر الفرق فقط | V55: عزل الأسقف نوعية ألتك يسعر الفرق فقط | W55: عزل الأسقف نوعية ألتك يسعر الفرق فقط | X55: عزل الأسقف نوعية ألتك يسعر الفرق فقط | Y55: عزل الأسقف نوعية ألتك يسعر الفرق فقط | Z55: عزل الأسقف نوعية ألتك يسعر الفرق فقط | AA55: عزل الأسقف نوعية ألتك يسعر الفرق فقط | AB55: عزل الأسقف نوعية ألتك يسعر الفرق فقط | AC55: عزل الأسقف نوعية ألتك يسعر الفرق فقط | AD55: عزل الأسقف نوعية ألتك يسعر الفرق فقط | AE55: عزل الأسقف نوعية ألتك يسعر الفرق فقط | AF55: عزل الأسقف نوعية ألتك يسعر الفرق فقط | AG55: عزل الأسقف نوعية ألتك يسعر الفرق فقط | AH55: عزل الأسقف نوعية ألتك يسعر الفرق فقط | AI55: عزل الأسقف نوعية ألتك يسعر الفرق فقط | AJ55: عزل الأسقف نوعية ألتك يسعر الفرق فقط | AK55: عزل الأسقف نوعية ألتك يسعر الفرق فقط | AL55: عزل الأسقف نوعية ألتك يسعر الفرق فقط | AM55: عزل الأسقف نوعية ألتك يسعر الفرق فقط | AN55: عزل الأسقف نوعية ألتك يسعر الفرق فقط | AO55: مقطوغ | AP55: M2 | AQ55: M2 | AR55: M2 | AS55: - | AW55: - | BA55: -
B56: (B) إجمالي سعر أعمال تحضير وتجهيز الموقع | AO56: 40000
B58: (C) أعمال تحت منسوب الأرض
B59: الرقم | E59: البند | AO59: الوحدة | AS59: الكمية | AW59: السعر | BA59: الإجمالي
B60: C1 | C60: B1 | D60: B1 | E60: أعمال الحفر | AO60: M3 | AP60: M2 | AQ60: M2 | AR60: M2 | AS60: 100 | AW60: 15 | BA60: =AW60*AS60 -> 1500
B61: C2 | C61: B1 | D61: B1 | E61: أعمال خرسانة عادية للفيلا و الدرج الخارجي و الرامب | AO61: M3 | AP61: M2 | AQ61: M2 | AR61: M2 | AS61: 25 | AW61: 1000 | BA61: =AW61*AS61 -> 25000
B62: C3 | C62: B1 | D62: B1 | E62: أعمال خرسانة مسلحة للفيلا و الدرج الخارجي | AO62: M3 | AP62: M2 | AQ62: M2 | AR62: M2 | AS62: 15 | AW62: 1500 | BA62: =AW62*AS62 -> 22500
B63: C4 | C63: B1 | D63: B1 | E63: أعمال طابوق مصمت أسفل الجسور الأرضية | AO63: M2 | AS63: 60 | AW63: 75 | BA63: =AW63*AS63 -> 4500
B64: C5 | C64: B1 | D64: B1 | E64: أعمال الجسور الأرضية السفلية للفيلا | AO64: M3 | AS64: 20 | AW64: 1000 | BA64: =AW64*AS64 -> 20000
B65: C6 | C65: B1 | D65: B1 | E65: أعمال الدفان والدمك | AO65: M3 | AS65: 100 | AW65: 21 | BA65: =AW65*AS65 -> 2100
B66: C7 | C66: B1 | D66: B1 | E66: أعمال الخرسانة الأرضية | AO66: M3 | AS66: 37 | AW66: 700 | BA66: =AW66*AS66 -> 25900
B67: C8 | C67: B1 | D67: B1 | E67: أعمال معالجة النمل الأبيض (مرتين) | AO67: L.S | AS67: 250 | AW67: 10 | BA67: =AW67*AS67 -> 2500
B68: (C) إجمالي سعر أعمال تحت منسوب الأرض | AO68: =SUM(BA60:BD67) -> 104000
B70: (D) أعمال فوق منسوب الأرض
B71: الرقم | E71: البند | AO71: الوحدة | AS71: الكمية | AW71: السعر | BA71: الإجمالي
B72: D1 | E72: أعمال خرسانة مسلحة للأعمدة | AO72: M3 | AS72: 15 | AW72: 1200 | BA72: =AW72*AS72 -> 18000
B73: D2 | E73: أعمال خرسانة مسلحة للسقف الارضي | AO73: M3 | AS73: 100 | AW73: 1000 | BA73: =AW73*AS73 -> 100000
B74: D3 | E74: أعمال خرسانة مسلحة للجسور و الكمرات | AO74: M3 | AP74: M2 | AQ74: M2 | AR74: M2 | AS74: 25 | AW74: 1200 | BA74: =AW74*AS74 -> 30000
B75: D4 | E75: أعمال خرسانة السلالم الداخلية | AO75: M3 | AS75: 5 | AW75: 900 | BA75: =AW75*AS75 -> 4500
B76: D5 | E76: أعمال خرسانة السلالم الخارجية | AO76: M3 | AS76: 3 | AW76: 600 | BA76: =AW76*AS76 -> 1800
B77: D6 | E77: أعمال خرسانة الأعتاب والأقواس ولنتل و الديكورات و الأبواب و اعتاب تركيب الزجاج و الهاندريل | AO77: مقطوع | AS77: 1 | AW77: 5950 | BA77: =AW77*AS77 -> 5950
B78: D7 | E78: خرسانة مسلحة للباربيت حسب المخطط | AO78: M3 | AS78: 3 | AW78: 600 | BA78: =AW78*AS78 -> 1800
B79: D8 | E79: خرسانة لقواعد الخزانات و التكييف | AO79: مقطوع | AS79: 1 | AW79: 5950 | BA79: =AW79*AS79 -> 5950
B80: (D) إجمالي سعر أعمال فوق منسوب الأرض | AO80: =SUM(BA72:BD79) -> 168000
B82: (E) أعمال الطابوق
B83: الرقم | E83: البند | AO83: الوحدة | AS83: الكمية | AW83: السعر | BA83: الإجمالي
B84: E1 | C84: B1 | D84: B1 | E84: توريد وتركيب طابوق 20 سم معزول حسب المخططات | AO84: M2 | AP84: M2 | AQ84: M2 | AR84: M2 | AS84: 300 | AW84: 55 | BA84: =AW84*AS84 -> 16500
B85: E2 | C85: B1 | D85: B1 | E85: توريد وتركيب طابوق خالي 20 سم حسب المخططات | AO85: M2 | AP85: M2 | AQ85: M2 | AR85: M2 | AS85: 500 | AW85: 60 | BA85: =AW85*AS85 -> 30000
B86: E3 | C86: B1 | D86: B1 | E86: توريد وتركيب طابوق خالي 10 سم حسب المخططات | AO86: M2 | AP86: M2 | AQ86: M2 | AR86: M2 | AS86: 25 | AW86: 60 | BA86: =AW86*AS86 -> 1500
B87: (E) إجمالي سعر أعمال الطابوق | AO87: =SUM(BA84:BD86) -> 48000
B90: اجمالي أولا : أعمال الهيكل | AO90: =$AO$87+$AO$80+$AO$68+$AO$56+$AO$43 -> 360000
B92: ثانيا : أعمال التشطيبات والاكساء
B94: (F) أعمال الطبقات العازلة
B95: الرقم | E95: البند | AO95: الوحدة | AS95: الكمية | AW95: السعر | BA95: الإجمالي
B96: H1 | C96: B1 | D96: B1 | E96: الاساسات | AO96: مقطوع | AP96: M2 | AQ96: M2 | AR96: M2 | AS96: 1 | AW96: 7500 | BA96: =AW96*AS96 -> 7500
B97: H2 | C97: B1 | D97: B1 | E97: الحمامات و التواليتات | AO97: M2 | AP97: M2 | AQ97: M2 | AR97: M2 | AS97: 25 | AW97: 60 | BA97: =AW97*AS97 -> 1500
B98: H3 | C98: B1 | D98: B1 | E98: نعلات الحمامات و التواليتات و المطابخ | AO98: M.L | AP98: M2 | AQ98: M2 | AR98: M2 | AS98: 20 | AW98: 50 | BA98: =AW98*AS98 -> 1000
B99: H4 | C99: B1 | D99: B1 | E99: الاسطح | AO99: M2 | AP99: M2 | AQ99: M2 | AR99: M2 | AS99: 200 | AW99: 120 | BA99: =AW99*AS99 -> 24000
B100: H5 | C100: B1 | D100: B1 | E100: نعلات عند حواف الاسطح | AO100: M.L | AP100: M2 | AQ100: M2 | AR100: M2 | AS100: 200 | AW100: 30 | BA100: =AW100*AS100 -> 6000
B101: (F) أعمال الطبقات العازلة | AO101: =SUM(BA96:BD100) -> 40000
B103: (I) أعمال الأصباغ للفيلا
B109: (G) اعمال التشطيبات
B110: الرقم | E110: البند | AO110: الوحدة | AS110: الكمية | AW110: السعر | BA110: الإجمالي
B111: J1 | E111: جميع ارضيات الفيلا سيراميك | AO111: M2 | AS111: 250 | AW111: 70 | BA111: =AW111*AS111 -> 17500
B112: J2 | E112: ارضيات رخام لبسطات الدرج الداخلي | AO112: M2 | AS112: 13 | AW112: 150 | BA112: =AW112*AS112 -> 1950
B113: J3 | E113: درجات قائمة و نايمة رخام للدرج الداخلي | AO113: L.M | AS113: 500 | AW113: 60 | BA113: =AW113*AS113 -> 30000
B114: J4 | E114: البراطيش | AO114: L.M | AS114: 21.25 | AW114: 40 | BA114: =AW114*AS114 -> 850
B115: J5 | E115: نعلات جميع ارضيات الفيلا | AO115: L.M | AS115: 100 | AW115: 20 | BA115: =AW115*AS115 -> 2000
B116: J6 | E116: نعلات الادراج الداخلية للرخام | AO116: L.M | AS116: 20 | AW116: 60 | BA116: =AW116*AS116 -> 1200
B117: J7 | E117: نعلات الادراج الخارجية غرانيت | AO117: L.M | AS117: 10 | AW117: 50 | BA117: =AW117*AS117 -> 500
B118: J8 | E118: بلاستر داخلي للجدران | AO118: M2 | AS118: 500 | AW118: 35 | BA118: =AW118*AS118 -> 17500
B119: J9 | E119: صبغ الجدران الداخلية | AO119: M2 | AS119: 500 | AW119: 25 | BA119: =AW119*AS119 -> 12500
B120: J10 | E120: سيراميك للحمامات و المطابخ و المغاسل | AO120: M2 | AS120: 100 | AW120: 40 | BA120: =AW120*AS120 -> 4000
B121: J11 | E121: بلاستر الاسقف برايمر+ صبغ | AO121: M2 | AS121: 200 | AW121: 25 | BA121: =AW121*AS121 -> 5000
B122: J12 | E122: الاسقف المستعارة جبس بورد لتغطية دكتات التكييف | AO122: M2 | AS122: 25 | AW122: 40 | BA122: =AW122*AS122 -> 1000
B123: J13 | E123: واجهات الفيلا الخارجية [المحارة و البلاستر] مع صبغ | AO123: M2 | AS123: 300 | AW123: 60 | BA123: =AW123*AS123 -> 18000
B124: (G) اعمال التشطيبات الداخلية | AO124: =AVERAGE(BA120+BA116+BA115+BA114+BA113+BA112+BA111+BA117+BA118+BA119+BA121+BA122+BA123) -> 112000
B126: (H) الأعمال الصحية
B127: الرقم | E127: البند | AO127: الوحدة | AS127: الكمية | AW127: السعر | BA127: الإجمالي
B128: L1 | C128: B1 | D128: B1 | E128: الانابيب و قطع التوصيل الخارجية | AO128: مقطوع | AP128: M2 | AQ128: M2 | AR128: M2 | AS128: - | AW128: - | BA128: -
B129: L2 | C129: B1 | D129: B1 | E129: الانابيب و قطع التوصيل الداخلية | AO129: مقطوع | AP129: M2 | AQ129: M2 | AR129: M2 | AS129: - | AW129: - | BA129: -
B130: L3 | C130: B1 | D130: B1 | E130: الخلاطات و اكسسوارات الحمامات و التواليتات | AO130: مقطوع | AP130: M2 | AQ130: M2 | AR130: M2 | AS130: - | AW130: - | BA130: -
B131: L4 | C131: B1 | D131: B1 | E131: المضخات | AO131: مقطوع | AP131: M2 | AQ131: M2 | AR131: M2 | AS131: - | AW131: - | BA131: -
B132: L5 | C132: B1 | D132: B1 | E132: خزانات المياه العلوية | AO132: مقطوع | AP132: M2 | AQ132: M2 | AR132: M2 | AS132: - | AW132: - | BA132: -
B133: L6 | C133: B1 | D133: B1 | E133: رسوم توصيل الخدمه ( المياه ) | AO133: مقطوع | AP133: M2 | AQ133: M2 | AR133: M2 | AS133: - | AW133: - | BA133: -
B134: L7 | C134: B1 | D134: B1 | E134: الانابيب ( المواسير ) والقطع الخاصه - خارجى | AO134: مقطوع | AP134: M2 | AQ134: M2 | AR134: M2 | AS134: - | AW134: - | BA134: -
B135: L8 | C135: B1 | D135: B1 | E135: الانابيب ( المواسير ) والقطع الخاصه - داخلى | AO135: مقطوع | AP135: M2 | AQ135: M2 | AR135: M2 | AS135: - | AW135: - | BA135: -
B136: L9 | C136: B1 | D136: B1 | E136: جميع اطقم حمامات غرف النوم وغرفه الطعام | AO136: مقطوع | AP136: M2 | AQ136: M2 | AR136: M2 | AS136: - | AW136: - | BA136: -
B137: L10 | C137: B1 | D137: B1 | E137: الجلى تراب والمنهولات | AO137: مقطوع | AP137: M2 | AQ137: M2 | AR137: M2 | AS137: - | AW137: - | BA137: -
B138: L11 | C138: B1 | D138: B1 | E138: رسوم توصيل الخدمه ( الصرف ) | AO138: مقطوع | AP138: M2 | AQ138: M2 | AR138: M2 | AS138: - | AW138: - | BA138: -
B139: (H) الأعمال الصحية | AO139: 48000
...

Sheet اتفاق 
A1: عقد اتفاق بين المالك و الاستشاري
A2: انه في يوم | E2: =المدخلات!$P$8 -> الاريعاء | J2: بتاريخ | M2: =TODAY() -> 46021 | T2: حرر بين كل من:
A4: • | B4: ="الطرف الأول السيد:"&" "&TEXT(المدخلات!P3,0)&" "&"مالك المشروع,قسيمة رقم :"&TEXT(المدخلات!P12,0)&" منطقة "&TEXT(المدخلات!P11,0)&" بإمارة رأس الخيمة" -> الطرف الأول السيد: احمد ابراهيم النعيمي مالك المشروع,قسيمة رقم :403100010 منطقة الخران بإمارة رأس الخيمة
A5: • | B5: الطرف الثاني: شركة سافانا ديزاين للاستشارات الهندسية والتصميم الداخلي، رخصة رقم(48818)، وعنوانها مكتب رقم (407) بأبراج جلفار، في إمارة رأس الخيمة ، ويمثلها المدير / المهندس أيمن بن حمادي، وبعد أن أقر المتعاقدان بأهليتهما للتصرف والتعاقد اتفقا على ما يأتي:
A8: 1 | B8: قبل الطرف الثاني بموجب هذا العقد أن يقوم بأعمال التصميم الهندسي والإشراف عل مشروع الفيلا الخاصة بالطرف الأول، الوارد بياناتها في مقدمة هذا العقد، وذلك حسب المعايير والمواصفات المحددة من قبل الجهات المختصة.
A10: 2 | B10: ="يلتزم الطرف الأول بدفع مبلغ وقدره "&" "&TEXT(المدخلات!P9,0)&" "&"درهم غير شامل الضريبة, للطرف الثاني مقابل أعمال التصاميم" -> يلتزم الطرف الأول بدفع مبلغ وقدره 0 درهم غير شامل الضريبة, للطرف الثاني مقابل أعمال التصاميم
A11: 3 | B11: يلتزم الطرف الأول بدفع كافة رسوم الجهات الحكومية أو الخاصة، والمطلوبة لفتح معاملات اعتماد المخططات والرسومات الهندسية، أو التعديل عليها.
A13: 4 | B13: لا يتحمل الطرف الثاني أي تأخير حاصل من قبل أي جهات أخرى، وتكون حدود مسؤوليته في العمل المنوط به فقط .
A14: 5 | B14: يقر الطرف الأول بأن كل الأفكار و المخططات والتصاميم المقدمة من الطرف الثاني تعتبر حق من حقوق ملكيته الفكرية، ولا يمكن نقلها لأي جهة مهما كانت أو التنازل عنها إلا بكتاب خطي موقع ومختوم من الطرف الثاني.
A16: 6 | B16: أي مبالغ مدفوعة في أي مرحلة من مراحل تصميم المشروع والإشراف عليه، تكون نظير للأفكار والجهد والوقت والخدمة المقدمة من قبل الطرف الثاني، ولا يعطي الحق للطرف الأول في المطالبة باسترجاع تلك المبالغ في حال عدم إكماله للمشروع.
A18: 7 | B18: يستحق الطرف الثاني نسبة من القيمة الإجمالية لعقد المقاولة ، يدفعه مقاول المشروع، أو الطرف الأول.
A19: 8 | B19: ="يلتزم الطرف الأول بدفع مبلغ مقابل إشراف الطرف الثاني على تنفيذ المشروع، وتدفع كمبلغ مقطوع و على دفعات ثابتة قيمتها" &" "&TEXT(المدخلات!P10,0)&"درهم،غير شامل الضريبة وتكون مستحقة بداية كل شهر ميلادي من بداية تنفيذ المشروع وحتى الانتهاء من إنجازه." -> يلتزم الطرف الأول بدفع مبلغ مقابل إشراف الطرف الثاني على تنفيذ المشروع، وتدفع كمبلغ مقطوع و على دفعات ثابتة قيمتها 0درهم،غير شامل الضريبة وتكون مستحقة بداية كل شهر ميلادي من بداية تنفيذ المشروع وحتى الانتهاء من إنجازه.
A22: 9 | B22: يلتزم الطرف الثاني بأن تكون الزيارات الإشرافية بمعدل أربع زيارات في الشهر تحسب بمعدل إجمالي طيلة فترة تنفيذ المشروع، وحسب ما يقتضيه تقدم الأشغال في الموقع، كما يقر الطرف الثاني أنه في حال توقف الأشغال لمدة ثلاثة أشهر أو أكثر لأي سبب كان، فأنه لا يحق له مطالبة الطرف الأول بدفع مبلغ الإشراف في فترة التوقف.
A24: 10 | B24: اذا وجد عائق من عوائق الارض ( دفان , كابل كهرباء , تعديل تحت المنسوب….) فالطرف الاول من يتحمل تسوية الموضوع.
A25: 11 | B25: يلتزم المالك بدفع رسوم إضافية يحددها الاستشاري فب حال طلب المالك أي تعديل علي المخططات بعد البدء بتجهيز المخططات التنفيذية لاعتمادها من الجهات الحكومبة و ينطبق ذلك علي أي تعديلات لاحقة
A26: 12 | B26: يلتزم المالك بدفع رسوم معاملة ادخال الكهرباء و معاملة الإنجاز في اخر المشروع
A27: 13 | B27: يحق للطرف الثاني (الاستشاري) نشر صور وفيديوات للمشروع
A28: 14 | B28: يحق للطرف الأول تغيير الطرف الثاني (الاستشاري) أثناء تنفيذ مشروع البناء، وليس قبل ذلك بأي حال من الأحوال ،و في حال الطرف الاول قرر عدم مواصلة المشروع قبل مرحلة التنفيذ يلتزم بدفع باقي المبالغ المستحقة و يكون المبلغ المدفوع في البند 2 نظير اعمال التصاميم المبدئية فقط مع الاحتفاظ بحقوق التصميم.
Y35: الاستشاري
Y36: سافانا ديزاين للاستشارات الهندسية والتصميم الداخلي

Sheet تكليف
A1: الموضوع:تكليف
B3: التاريخ: | G3: =TODAY() -> 46021
A5: يسرنا الموفع ادناه | J5: =المدخلات!$P$3 -> احمد ابراهيم النعيمي | AC5: بصفتي مالك المشروع علي القسيمة رقم | AX5: =المدخلات!$P$12 -> 403100010
A6: منطقة | E6: =المدخلات!$P$11 -> الخران | Q6: وهو عبارة عن | X6: =المدخلات!$P$4 -> فيلا دور أرضي و اول وسور | AQ6: تكليف مكتب سافانا ديزاين
A7: للاستشارات الهندسة باعمال التصميم والاشراف حتي استخراج شهادة الانجاز و ارساء المناقصة علي المقاول
C9: المرحلة الاولى: دراسة الموقع , حركة الشمس , مخططات مبدئية المقترحة من الاستشاري
C11: المرحلة الثانية: بعد اعتماد المرحلة الاولى يتم تجهيز المخططات التنفيذية للمشروع مخططات معماري مع جميع التفاصيل
E12: • مخططات الانشائي مع التفاصيل • مخططات الكهرباء • مخططات الماء • مخططات الصرف الصحي • مخططات اتصالات
C18: المرحلة الثالثة: تقديم المخططات التنفيذية للمشروع للبلدية.
C20: المرحلة الرابعة: تحضير الشروط والمواصفات بالتشاورمع المالك وطرح المشروع للمناقصة وتجهيز العقود.
C22: المرحلة الخامسة: الاشراف علي تنفيذ المشروع في الموقع حتي الإنجاز.
E24: • كل الأفكار والمخططات والتصاميم المقدمة من سافانا ديزاين تعتبر حق من حقوق ملكيتها الفكرية، ولا يمكن نقلها لأي جهة مهما كانت أو التنازل عنها إلا بكتاب خطي موقع ومختوم من سافانا ديزاين. • يتحمل مالك المشروع كافة الرسوم المتعلقة بالمشروع رسوم الدوائر الحكومية مع رسوم الرخصة تحدد لاحقا بعد الموافقة على المخططات. • یسـتحق الاستشاري بعد اعتماد المرحلة الاولي نسبة مـن الـقیمة الإجـمالـیة لـعقد المـقاولـة یـدفـعه المـقاول المـنفذ للمشـروع أو المالك في بعض الحالات .
A30: اسم و توقيع المالك | AC30: الاستشاري
A31: =المدخلات!P3 -> احمد ابراهيم النعيمي | AC31: سافانا ديزاين للاستشارات الهندسية والتصميم الداخلي

Sheet عقد ابنك
B1: عقد الاتفاق Agreement
B2: بإشرافنا نحن: سافانا ديزاين للإستشارات الهندسية والتصميم الداخلي- رأس الخيمة تم الاتفاق بين كل من:
B3: =[5]المدخلات!B4 -> وصف المشروع | G3: =المدخلات!$P$4 -> فيلا دور أرضي و اول وسور | O3: =[5]المدخلات!AD4 -> رقم القسيمة | T3: =المدخلات!$P$12 -> 403100010 | Y3: =[5]المدخلات!AD3 -> المنطقة | AE3: =المدخلات!$P$11 -> الخران
B4: الطرف الاول : السادة الملاك | O4: =المدخلات!$P$3 -> احمد ابراهيم النعيمي | AB4: رقم الهاتف:
B5: التوقيع: | AB5: =المدخلات!$P$6 -> 0
AB6: العنوان:
AB7: =[5]المدخلات!AR6 -> راس الخيمة
B9: الطرف الثاني المقاول : | O9: =المدخلات!$AR$3 -> 0 | AB9: رقم الهاتف:
B10: التوقيع مع ختم: | AB10: =المدخلات!$AR$11 -> 0
AB11: =[5]المدخلات!AD12 -> رقم رخصة المقاول
AB12: =المدخلات!$AR$4 -> 0
B14: الطرف الثالث الاستشاري : | O14: سافانا للاستشارات الهندسية | AB14: رقم الهاتف:
B15: التوقيع مع ختم: | AB15: 0525015080
AB16: العنوان:
AB17: مكتب 407 - أبراج جلفار - رأس الخيمة
B20: ="لما كان الطرف الأول راغبا في الحصول على تنفيذ وانشاء وانجاز"&" "&"( "&TEXT(#REF!,0)&" )"&" فقد وقع الاتفاق بين الاطراف الثلاثة على ما يلي:" -> #REF! | C20: ='[5]حساب الكميات'!AO267 -> سعر الفيلا مع السور(بدون الضريبة) | W20: ='[5]حساب الكميات بنك'!AC33 -> 800000
B22: يقوم الطرف الثاني بتنفيذ وانشاء وصياتة المشروع المذكور اعلاه لقاء مبلغ وقدره | W22: ='[5]حساب الكميات بنك'!AC33 -> 800000 | Z22: درهم اماراتي فقط
B23: ثمان مائة الف درهم اماراتي لاغير بدون ضريبة
B26: بنود العقد
B27: 1 | D27: مقدمة | AI27: 1
B28: كافة مستندات المشروع و جميع متعلقاته متكاملة فيما بينها و تشمل المشروع ككل أي بحال عدم ذكر اي بند بالمواصفات او المخططات وتم ذكره بجدول الكميات او المخططات المعتمدة أو اي مستند اخر غير ذلك , والعكس صحيح على المقاول الالتزام به و العمل على تضمينه بأعمال المشروع اينما ذكر .علي المقاول ارجاع العقد موقع علي كل صفحة والمواصافات و المخططات وتوقيعه عليها يعتبر انه اطلع علي جميع تفاصيل المشروع
B35: 2 | D35: إصدار التعليمات, الرسوم | AI35: 2
B36: لا يحق للمالك اصدار اي تعليمات للمقاول تتعلق بتنفيذ المشروع الا عن طريق الاستشاري
B43: 3 | D43: مقاولي الباطن | AI43: 3
B44: 1. يجوز للطرف الثاني اسناد جزء من الاعمال الى مقاولي الباطن المعتمدين والمسجلين لدى البلدية. بموجب موافقة خطية من الاستشاري 2. يكون المقاول مسؤول مسؤولية كاملة عن اعمال المقاول الباطن من حيث الجودة والتنفيذ واصول الصناعه والضمانات 3. يتعهد الطرف الثاني بالتنسيق بين جميع المقاولين الباطن دون اي استثناء ودون اي احقية في المطالبة باي مبلغ اضافة نظير ذلك. 4. في حال اسناد المالك بعض الاعمال لمقاولي الباطن يكون عن طريق المقاول الرئيسي.
B50: 4 | D50: فسخ التعاقد : يحق للمهندس الاستشاري فسخ العقد في الحالات | AI50: =B50 -> 4
B51: 1. اذا تاخر المقاول عن بدء الاعمال بعد تسليم الموقع 2. اذا تاخر المقاول في اتمام العمل وتسليمه في المواعيد المحدده لكل مرحلة في الجدول الزمني المعتمد. 3. اذا اظهر المقاول بطئا في سير العمل لدرجة يرى الاستشاري منها عدم قدرة الطرف الثاني على اتمام العمل في موعده على ان يقوم الاستشاري بكتابة ذلك خطيا للمقاول. 4. اذا اخل المقاول ببرنامج العمل المحدد بشكل يؤثر على مستوى التنفيذ او الاخلال بالمواصفات المتفق عليها. 5. اذا انسحب المقاول عن العمل او تركه او افلس. 6. اذا اسند الطرف الثاني العمل لمقاول باطن دون اخطار الاستشاري. 7. في حال تاخير الطرف الاول عن سداد اي من مستحقات الطرف الثاني في موعد اقصاه شهر فمن حق الطرف الثاني التوقف عن العمل وذلك بعد اخطار الاستشاري خطيا وتحسب فتره التاخير على المالك لصالح المقاول كمدة اضافية للمشروع. 8. يحق للطرف الثاني الغاء التعاقد في حالة تاخير المالك بسداد الدفعات المستحقة عليه او اخلال المالك بالتزاماته.
B58: 5 | D58: (الاثار المترتبة على فسخ العقد) | AI58: =B58 -> 5
B59: 1. حساب غرامة التاخير على الطرف الثاني طبقا للعقد حتى تاريخ ابلاغ المقاول بقرار السحب. 2. يتم تنفيذ الاعمال المتبقية كلها او بعضها على حساب المقاول على ان تطرح الاعمال المتبقية في مناقصة جديدة او يعهد بتنفيذها الى احد المقاولين بطريق الممارسة مع تحميل المقاول النتائج المترتبة عن هذا الاجراء. 3. حجز اي دفعات متبقيىة للمقاول وحجز الضمانات البنكية ومحجوزات الصيانة لحين الانتهاء من المشروع (تمويل خاص فقط).
B66: 6 | D66: حل النزاع | AI66: =B66 -> 6
B67: اي نزاع ينشا عن تطبيق احكام هذا العقد يكون الفصل فيه اختصاص محكم يتفق عليه الطرفان او ترشحة الجهات والدوائر المختصه.
B74: 7 | D74: محجوزات الصيانة | AI74: =B74 -> 7
B75: يستقطع 5% من قيمة الاعمال المنفذه بالدفعات الجارية او التي يتم صرفها بمعرفة المقرض كمحجوز صيانة وذلك ضمانا لحسن تنفيذ الاعمال وبعد الاستلام الابتدائي وحصر الاعمال نهائيا يتم صرف المستحقات الختامية للاعمال بعد استقطاع ما على المقاول من التزامات وما سبق صرفه كدفعات ويصرف له الباقي بعد حجز محجوز الصيانة من قيمة الاعمال المنفذة لمدة سنة من تاريخ الاستلام الابتدائي (تمويل خاص فقط) .
B82: 8 | D82: الإستلام الابتدائي للمشروع | AI82: =B82 -> 8
B83: يجب على المقاول اخطار الاستشاري باليوم الذي يتم فيه انهاء الاعمال على ان يكون هذا الاخطار قبل حلول هذا اليوم باسبوع على الاقل ليتم اخطار المالك والمقاول بموجب الاستلام الابتدائي يتم بحضور المقاول او مهندسه. وفي حاله عدم حضوره يقوم الاستشاري بعمله في غيابه فاذا ثبت ان الاعمال في حاله تسمح باستلامها يتم تحرير محضرا باستلام الاعمال استلاما مبدئيا في ذات اليوم, اما اذا ثبت عكس ذلك فللاستشاري الحق في عمل محضر اثبات حاله, وفي جميع الاحوال تكون المحاضر التي يحررها الاستشاري حجة على المقاول ولو لم يحضر او يوقع على المحضر ، لا يقوم الاستشاري باعادة المعاينة الا اذا اخطره المقاول بموعد انهاء الاعمال وقبل اسبوع من الحلول على الاقل وفي حال وجود ملاحظات على اعمال المشروع لا تمنع من الاستلاام الابتدائي يتم استلام المشروع ويعطى المقاول سبعه ايام لانهاء تلك الملاحظات وفي حال عدم انتهائه من هذه الملاحظات يعتبر محضر الاستلام الابتدائي لاغيا.
B89: 9 | D89: الاشراف الهندسي من قبل الاستشاري | AI89: =B89 -> 9
B90: يتم دفع رسوم شهرية مقابل الاشراف (700) درهم بدون الضريبة وذلك يتضمن الزيارات الاسبوعية والمتابعة بشكل عام-في حال تجاوزت مدة انتهاء المشروع على المدة المتفق عليها , يتم دفع رسوم الاشراف من قبل الطرف المتسبب في التأخير ( المالك او المقاول ) في حال كان الطرفين متسببين في التأخير ف يتم دفع الرسوم المتبقية لأشراف مناصفة بين المالك والمقاول. 1- يقوم المقاول بدفع رسوم (150) درهم عند كل تقديم دفعة من جدول الدفعات المتفق عليه . 2- يحق للإستشاري إيقاف المقاول عن العمل في حالة عدم التقيد بتعليمات الإستشاري ويسري هذا على المقاولين الذين يحضرهم المقاول الرئيسي أو المالك 3-الطرف الثالث غير مسؤول إذا لم ينجز المشروع بالكامل خلال مدة التنفيذ المتعاقد عليها بين الطرف الاول والمقاول. 4-في حال طلب المالك ايقاف الاشراف على المشروع وفسخ العقد بعد انتهاء مدة التنفيذ وقبل ان ينتهي انجاز المشروع بالكامل يجب ان يكون هذا الطلب خطيا قبل شهر على الاقل من انتهاء مدة التنفيذ وبعد موافقة الطرف الثاني فانه يحق للاستشاري تحصيل اتعاب اشراف ثلاثة اشهر اضافية على مدة العقد حسب ما هو مذكور في المادة السادسة عشر من هذا العقد وذلك كتعويض عن الضرر الذي يلحق بالاستشاري نتيجة فسخ العقد واخلاء الطرف. 5-في حال طلب المالك إيقاف الاشراف خلال مدة التنفيذ دون مبرر الطرف الثاني فانه من حق الاستشاري تحصيل اتعابه كاملة حسب ما هو مذكور في هذا العقد قبل اخلاء الطرف وانهاء مهمة الاستشاري وبشرط الا يترتب على هذا الطلب اي ضرر على الطرف الثاني. 6-الاستشاري غير ملزم بالاشراف على أي أعمال خارج التصميم المعماري والإنشائي (التكيف الديكور - المسابح -المصاعد- الحديقة).
B97: 10 | D97: الإستلام النهائي للمشروع | AI97: =B97 -> 10
B98: بعد انتهاء فترة ضمان الصيانة المحددة في العقد, يصدر الاستشاري شهادة الاستلام النهائي بعد معاينة المشروع شريطة ان يكون المقاول قد قام بكل ما يترتب عليه من التزامات خلال فترة الصيانة حيث لا يوجد اي عيوب في المشروع تمنع من اصدار هذه الشهادة من اجل صرف محجوز الضمان وقدره (5%) من قيمة العقد الاجمالية ويلتزم المقاول بدفع مبلغ 2500 درهم كاتعاب للاستشاري نظير ذلك.
B105: 11 | D105: مدة الصيانة | AI105: =B105 -> 11
B106: علي المقاول متابعة ملاحظات المالك و صيانتها بعد الاستلام الابتدائي وحتي الاستلام النهائي للمشروع و في حال عدم تجاوب المقاول يحق للمالك عدم التوقيع في التسليم النهائي حتي يتم معالجة جميع الملاحظات . الطرف الثاني مسؤولا عن سلامة الهيكل الخرساني للمبنى المذكور اعلاه لمدة 10 سنوات (عشرة سنوات) من تاريخ الاستلام الابتدائي.
B113: 12 | D113: الصيانة | AI113: =B113 -> 12
B114: تبدا اعمال الصيانة للمشروع لمدة عام كامل بعد تاريخ الاستلام الابتدائي للمشروع مباشرة.
B118: 13 | D118: انسحاب المقاول بدون سبب | AI118: =B118 -> 13
B119: اذا انسحب المقاول من العمل بالمشروع بدون سبب مقبول من الاستشاري يقوم بدفع ما قيمته 10% من العقد لصالح المالك ودفع رسوم رسو العطاء وارساء المناقصة ونسبتها (4%) من قيمة اجمالي عقد المقاولة كاملا.
B125: 14 | D125: امتناع المالك التسليم الابتدائي | AI125: =B125 -> 14
B126: في حالة امتناع المالك عن التوقيع على محضر الاستلام الابتدائي او النهائي سيتم اخطاره بضرورة بيان السبب خلال خمسة عشر يوما من تاريخ اخطاره، فان انتهت هذه المهلة دون بيان اسباب امتناعه او ان الاسباب التي ابداها غير مقنعه من وجهة نظر الاستشاري، فانه يجوز للاستشاري استلام المبنى وتسليم المقاول كافة مستحقاته ويعتبر المبنى في حوزة المالك وتحت مسؤوليته من تاريخ الاستلام.
B133: 15 | D133: فسخ عقد الاستشاري | AI133: =B133 -> 15
B134: في حالة رغبة المالك في فسخ العقد مع الاستشاري بعد اعتماد المخطط لدى البلدية فعليه دفع 2% من قيمة المشروع للاستشاري نظير اتعابه.
B141: 16 | D141: اتعاب الاستشاري | AI141: =B141 -> 16
B142: يلتزم الطرف الثاني دفع نسبة من قيمة عقد المقاولة كاملا مقابل المخططات المعتمدة و المناقصة كذلك الامر عن أي اعمال اضافية التي تضاف الى العقد لاحقا .
B149: 17 | D149: التاخير عن مراحل الجدول الزمني | AI149: =B149 -> 17
B150: الطرف الثاني ملزم بتقديم جدول زمني قبل توقيع العقد ويتم اعتماده من الطرف الثالث فقط ويتم تطبيق غرامة 2000 درهم للمالك ) في حال تأخر المقاول عن انجاز كل مرحلة على حدى في الجدول الزمني و دون سبب مقنع للتاخير.
B157: 18 | D157: توريد مواد خارجة عن المواصافات | AI157: =B157 -> 18
B158: يتم تغريم الطرف الثاني 2000 درهم (2000 للمالك ) في حال تم توريد اي مادة او خامة مخالفة للمواصفات المعتمدة وغير مقبولة من الاستشاري .
B165: 19 | D165: اعتماد الامر التغييري | AI165: =B165 -> 19
B166: في حال تم العمل على المخططات المعدلة من غير تقديم الامر التغييري من قبل الطرف الثاني للاستشاري و المالك لاعتماده فإن المقاول يتحمل مسؤوليته بذلك.
B173: 20 | D173: تقرير شهري | AI173: =B173 -> 20
B174: الطرف الثاني ملزم بتقديم تقرير شهري كتابي عن سير الاعمال في الموقع ويتم تغريمه درهم500 بحالة عدم الالتزام يدفعها للمالك او متابعة و تقرير يومي عن طريق مجموعة الواتساب الخاصة بالمشروع.
B181: 21 | D181: الدفعات الخاصة | AI181: =B181 -> 21
B182: الدفعات الخاصة تتم عن طريق الاستشاري فقط وفي حال تم دفع المالك الدفعة مباشرة للمقاول وبدون علم الاستشاري فإن المالك يتحمل مسؤوليته بذلك .
B189: 22 | D189: تقرير مع كل دفعة خاصة | AI189: =B189 -> 22
B190: يتم تقديم تقرير مفصل من قبل المقاول عند كل دفعة يتم تقديمها ويكون التقرير شامل لكافة الاعمال المنجزة والجارية وموضحة بالصور والتفاصيل اللازمة .
B197: 23 | D197: اختيار مواد التشطيب | AI197: =B197 -> 23
B198: يجب على المالك اختيار المواصفات المتعلقة به تجنبا للتأخير وذلك يتم بالتنسيق مع الاستشاري لكل مرحلة وبند على حدى , في حالة تأخير المالك فان المقاول لا يتحمل أي مسوولية.
B205: 24 | D205: المناقصة | AI205: =B205 -> 24
B206: يتم تقديم المناقصة من قبل المقاول للاستشاري بكامل تفاصيلها من حساب كميات والمخططات و 3D مع ختم وتوقيع على كل ورقة او مخطط يتم تقديمه معرفا بالتاريخ .
B213: 25 | D213: الدفعه الختامية | AI213: =B213 -> 25
B214: لا يتم اعتماد الدفعه الختامية وصرفها للمقاول الا بعد استيفاء الاتي: 1. رخصة البناء الاصلية. 2. مفاتيح المبنى الداخلية والخارجية. 3. جدول الأحمال الخاص بتوصيل الكهرباء والماء 4. عدم ممانعه من البلدية بتوصيل الكهرباء والماء 5. خطاب ضمان الطبقات العازلة لمدة 10 سنوات 6. خطاب ضمان اعمال الدهانات لمدة 3 سنوات 7. خطاب ضمان خزانات المياه لمدة 3 سنوات 8. خطاب ضمان الاجهزة (سخانات + مراوح شفط + المضخات) (اذا كانت من ضمن الأعمال المشمولة بعقده)
B220: 26 | D220: الالتزام بدفع الضريبة | AI220: =B220 -> 26
B221: يلتزم كل الأطراف المساهمون في هذا المشروع بمتطلبات المرسوم بقانون اتحادي رقم (08) لسنة 2018 .ولائحته التنفيذية المعلنة و اللذان ينظمان ضريبة القيمة المضافة ( VAT ) و تطبيقها في دولة الامارات حيث تحتسب نسبة 5% تضاف الى القيمة الاجمالية للمشروع
B226: 27 | D226: شيك الضمان | AI226: =B226 -> 27
B227: كما أنه على المقاول تحرير شيك ضمان باسم المالك بقيمة الدفعة الاولى يسلم لدى الاستشاري و يحفظ عند الاستشاري حتي التسليم الابتدائي .
B234: 28 | D234: مدة التنفيذ | AI234: =B234 -> 28
B235: مدة المشروع | H235: 24شهر | K235: من تاريخ امر المباشرة
B241: 29 | D241: عدم التراجع عن السعر بعد توقيع العقد | AI241: =B241 -> 29
B242: يتحمل المقاول كامل المسؤولية عن عرض السعر المقدم من طرفه بعد توقيع العقد ويعتبر مطلعا كامل الاطلاع وملما بجميع الشروط والأحكام والمواصفات المنصوص عليها في أوراق المناقصة وليس له الحق في التراجع أو الأعتراض عن أي بند مهما كانت الأسباب.
B249: 30 | D249: توفير عمالة قانونية و مهندس ذو خبرة | AI249: =B249 -> 30
B250: على المقاول الالتزام بما تشمله هذه المناقصة من مواصفات فنية ومدة زمنية وكميات كما عليه تأمين العمالة القانونية وذات الخبرة والكفاءة لتسيير العمل دون اخلال أو توقف ومهندس ذو خبرة كافية لانجاز العمل حسب المواصفات ويكون متواجدا بشكل دائم.
B256: 31 | D256: تقديم مخططات تنفيذية | AI256: =B256 -> 31
B257: على المقاول تقديم مخططات تنفيذية كاملة لكافة أعمال الكهروميكانيك او مد الااستشاري بجميع الملاحظات بما يتوافق مع متطلبات الدوائر والجهات المختصة لضمان موافقتها على الأعمال قبل البدء في التنفيذ و الا سيتحمل المقاول تبعات التغيير في الموقع ويكون التسعير على مساحات الصبيات المنفذة المعتمدة من الاستشاري .
B263: 32 | D263: مواد غير موصفة | AI263: =B263 -> 32
B264: على المقاول الحصول على اعتماد المالك والاستشاري للمواد الغير موصفه بالمواصفات قبل التوريد، بخلاف ذلك يتحمل وحده مسؤولية مطابقتها للمواصفات وفي حالة اعتماد المالك مع المقاول مباشرة وبدون الرجوع للاستشاري فإن الطرفان يتحملان المسئولية ويقتصر دور الاستشاري على متابعة اختيارات المالك فقط دون أدنى مسئولية على الاستشاري .
B270: 33 | D270: مدة التعديل عند الاستشاري | AI270: =B270 -> 33
B271: في حالة طلب المالك للتعديل فانه يتم احتساب المدة التي تم فيها التعديل و الارفاق للجهات المختصة و لا يتحمل الاستشاري مدة التاخير ان كانت خارج نطاق المكتب
B278: 34 | D278: اختيار المالك شركات التشطيب | AI278: =B278 -> 34
B279: يحق للمالك اختيار شركات التشطيب مع اعتبار فرق السعر سواء كان بالزيادة أو بالنقصان وتشمل شركات التشطيب : ( الأبواب الخشبية - الألومينيوم - الحديد الديكوري - البورسلين - الرخام - السيراميك - الأطقم الصحية ) .
B286: 35 | D286: الزيادة في الأسعار | AI286: =B286 -> 35
B287: في حالة زيادة أسعار المواد بعد التعاقد بزيادة تتخطى قيمة 10 % من السعر المتعاقد عليه يحق للمقاول التقدم بطلب لاسترداد فرق السعر وذلك بشرط أن يكون معدل سير الأعمال طبقاً للمواعيد المتفق عليها في الجدول الزمني وخلال مدة التعاقد وفي حالة كان المقاول هو السبب في تأخير سير الأعمال ان كانت الزيادة المذكورة ناتجة عن التأخر في العمل يتحمل المقاول كافة تكاليف هذا التأخير من حيث زيادة أسعار المواد .
B294: 36 | D294: احتساب قيمة التعديل | AI294: =B294 -> 36
B295: في حالة قيام المالك بالتعديل في المشروع بعد التنفيذ يتم احتساب قيمة التعديل بنفس قيمة وحده قياس البند المعدل بشرط تقديم عرض سعر قبل البدء في أعمال التعديل وإلا لا يحق له المطالبة بأي مبالغ مالية و يحق للاستشاري احتساب قيمة التعديل و تقديمها للمالك .
B299: 37 | D299: رسوم التعديل | AI299: =B299 -> 37
B300: في حالة قيام المالك أو المقاول بالتقدم بطلب للاستشاري للإجراء تعديلات على التصميم كلياً يقوم الطرف المتسبب في التعديل بسداد رسوم للاستشاري تقدر ب 2000 درهم للتعديل و 500 درهم للاعتماد ويشمل التعديل في المخططات المعماري والانشائية والمناظير والخدمات بأنواعها كالصرف والكهرباء والمياة والاتصالات وخلافه وفي حال كان التعديل بسيط ولا يؤثر على باقي المخططات يتم سداد رسوم 300 درهم للأستشاري ولا يسري هذا في حاله وجود تناقض بين المخططات او بينها وبين المنظور ولا بد من تعديلها لتتطابق المخططات .
B307: 38 | D307: الاطلاع علي جميع مخططات المشروع | AI307: =B307 -> 38
B308: على المقاول قبل توقيع العقد الاطلاع على المخططات و المواصفات و الشروط و التأكد من تطابق جميع المخططات الانشائية والمعمارية والخدمات و المناظير 3D وتنبيه الاستشاري لأي اختلاف في تطابق المخططات وذلك لتفادي التغيير و التعديل في الموقع قبل التنفيذ و في حالة عدم تنبيه الاستشاري بوجود اختلاف قبل الشروع في العمل يتحمل المقاول كامل المسؤولية في التعديلات المطلوبة و التاخير المترتب عن ذلك و اعتبار أن توقيعه عليها يعني موافقته على جميع ما ورد بها وتعتبر المناظير المقدمة من الاستشاري في ملف المناقصة هي المعتمدة من ناحية الشكل و التشطيبات في حال اختلاف مع المخططات المعتمدة .
B315: 39 | D315: تقديم جدول زمني | AI315: =B315 -> 39
B316: يتعين تقديم جدول زمني و جدول تحليل كميات و أسعار ( BOQ ) كشرط للتوقيع على العقد و استكمال الرخصة .
B323: 40 | D323: في حال تعارض بين اللغتين | AI323: =B323 -> 40
B324: في حال تعارض في المواصفات بين اللغة العربية و الانجليزية تعتمد اللغة العربية بعد مراجعة الاستشاري .
B331: 41 | D331: اختلاف في البنود | AI331: =B331 -> 41
...

Sheet حاوية
B1: موضوع التعاقد: | AD1: (فيلا دور ارضي واول)
B3: قيمة التعاقد: | K3: =المدخلات!AR8 -> 0 | R3: درهم اماراتي فقط لا غير
B4: الموقع: | H4: =المدخلات!AR3 -> 0
B5: قسيمة رقم: | J5: =المدخلات!AR4 -> 0
B6: مدة التنفيذ الاجمالية: | O6: =المدخلات!$P$11 -> الخران | R6: شهر من تاريخ أمر المباشرة.
B8: انه في يوم | I8: =المدخلات!AR7 -> 46021 | O8: =المدخلات!P14 -> 0 | X8: إتفق كل من :
B9: الطرف الأول: | J9: =المدخلات!P3 -> احمد ابراهيم النعيمي
B10: موبايل رقم: | J10: =المدخلات!P6 -> 0
B12: الطرف الثاني: | J12: =المدخلات!AR10 -> 0
B13: موبايل رقم: | J13: =المدخلات!$AR$11 -> 0
B15: وبحضور المكتب الإستشاري ( سافانا ديزاين للإستشارات الهندسية) كشاهد على العقد والتوقيع وعنوانه ابراج جلفار الطابق الرابع مكتب 407 هاتف 2273478 /07 ,متحرك: 0525015080 على أن يقوم المقاول بتنفيذ المشروع المذكور أعلاه حسب المخططات وبنود التعاقد وتعليمات الإستشاري وعلى أن يكون الإستشاري المذكور أعلاه مفوضا من طرف المالك للإشراف على التنفيذ وعلى الطرف الثاني الإلتزام بتنفيذ كافة تعليمات الإستشاري أثناء التنفيذ وكذلك الرجوع إليه للسؤال عن أي إستفسار كما أن للإستشاري جميع الصلاحيات والتي يجب أن يلتزم بها الطرف الثاني.
B21: تمت هذه الإتفاقية بموافقة كل من المالك والمقاول بوجود الإستشاري
B22: المالك | AD22: المقاول
B23: =المدخلات!P3 -> احمد ابراهيم النعيمي | AD23: =المدخلات!AR10 -> 0
B27: الاستشاري
B28: سافانا ديزاين للإستشارات الهندسية

Sheet محضر تسليم موقع
A3: محضر تسليم موقع
B5: التاريخ : | G5: =المدخلات!AR14 -> 0
B7: المشروع: | H7: =المدخلات!P4 -> فيلا دور أرضي و اول وسور
B8: المالك: | G8: =المدخلات!P3 -> احمد ابراهيم النعيمي
B9: المقاول: | H9: =المدخلات!AR10 -> 0
B10: الاستشاري: | I10: سافانا ديزاين للاستشارات الهندسية
B13: الامارة : راس الخيمه | T13: المنطقة: | Z13: =المدخلات!AR3 -> 0 | AL13: رقم القسيمة: | AU13: =المدخلات!AR4 -> 0
B15: تم تسليم الموقع المذكور اعلاه الى المقاول خاليا من العوائق وصالحا للبناء فيه, ويبدا احتساب مدة التنفيذ من اليوم التالي من تاريخ تسليم الموقع شاملة فترة التحضير.
B20: وتفضلوا بقبول فائق الاحترام والتقدير،،،
B23: المالك | T23: المقاول | AL23: الاستشاري
B24: =المدخلات!P3 -> احمد ابراهيم النعيمي | T24: =المدخلات!AR10 -> 0 | AL24: سافانا ديزاين للاستشارات الهندسية

Sheet تواريخ الصب
B2: معلومات المشروع
B3: المالك | O3: =المدخلات!P3 -> احمد ابراهيم النعيمي | AQ3: المنطقة | AV3: =المدخلات!$AR$3 -> 0
B4: وصف المشروع | O4: =المدخلات!P4 -> فيلا دور أرضي و اول وسور | AQ4: رقم القسيمة | AV4: =المدخلات!AR4 -> 0 | BM4: 45524
B6: تواريخ الصب
B8: البنود | AO8: التاريخ | AW8: عدد الأيام بين كل بند
B9: إستلام الموقع
B10: استلام الدفعة الاولي
B11: الحفر | AW11: =AO11-AN9 -> 0
B12: صب النظافة | AW12: =AO12-AO11 -> 0
B13: صب القواعد | AW13: =AO13-AO12 -> 0
B14: صب رقاب الاعمدة | AW14: =AO14-AO13 -> 0
B15: صب الجسور | AW15: =AO15-AO14 -> 0
B16: صب البلاطات الأرضية | AW16: =AO16-AO15 -> 0
B17: صب أعمدة الأرضي | AW17: =AO17-AO16 -> 0
B18: صب سقف الأرضي | AW18: =AO18-AO17 -> 0
B19: صب أعمدة الأول | AW19: =AO19-AO18 -> 0
B20: صب سقف الأول | AW20: =AO20-AO19 -> 0
B21: بداية طابوق الأرض | AW21: =AO21-AO20 -> 0
B22: بداية طابوق أول | AW22: =AO22-AO21 -> 0
AW24: =SUM(AW11:BE22) -> 0
B26: ملاحظات | AO26: مهندس الاشراف :

Sheet متباعة الاشراف 
B1: المالك | G1: =المدخلات!P3 -> احمد ابراهيم النعيمي | O1: المنطقة | T1: =المدخلات!AR3 -> 0 | AB1: رقم القسيمة | AG1: =المدخلات!AR4 -> 0
B4: متباعة الاشراف
F7: 1 | G7: 2 | H7: 3 | I7: 4 | J7: 5 | K7: 6 | L7: 7 | M7: 8 | N7: 9 | O7: 10 | P7: 11 | Q7: 12 | R7: 13 | S7: 14 | T7: 15 | U7: 16 | V7: 17 | W7: 18 | X7: 19 | Y7: 20 | Z7: 21 | AA7: 22 | AB7: 23 | AC7: 24 | AD7: 25 | AE7: 26 | AF7: 27 | AG7: 28 | AH7: 29 | AI7: 30 | AJ7: 31
A8: 1 | B8: 45524 | AK8: =SUM(F8:AJ8) -> 0
A9: 2 | B9: 45556 | AK9: =SUM(F9:AJ9) -> 0
A10: 3 | B10: 45588 | AK10: =SUM(F10:AJ10) -> 0
A11: 4 | B11: 45620 | AK11: =SUM(F11:AJ11) -> 0
A12: 5 | B12: 45652 | AK12: =SUM(F12:AJ12) -> 0
A13: 6 | B13: 45684 | AK13: =SUM(F13:AJ13) -> 0
A14: 7 | B14: 45716 | AK14: =SUM(F14:AJ14) -> 0
A15: 8 | B15: 45717 | AK15: =SUM(F15:AJ15) -> 0
A16: 9 | B16: 45750 | AK16: =SUM(F16:AJ16) -> 0
A17: 10 | B17: 45781 | AK17: =SUM(F17:AJ17) -> 0
A18: 11 | B18: 45814 | AK18: =SUM(F18:AJ18) -> 0
A19: 12 | B19: 45845 | AK19: =SUM(F19:AJ19) -> 0
... A26: 19 | B26: 46081 | AK26: =SUM(F26:AJ26) -> 0
B27: =SUM(AK8:AN26) -> 0

Sheet التكلفة التقديرية
A1: التكلفة التقديرية
A3: مشروع انشاء وانجاز | H3: =المدخلات!P4 -> فيلا دور أرضي و اول وسور
A4: المالك: | H4: =المدخلات!P3 -> احمد ابراهيم النعيمي
A5: المقاول: | H5: =المدخلات!AR10 -> 0
A6: رقم القسيمة | G6: =المدخلات!$P$12 -> 403100010 | Q6: المنطقة | V6: =المدخلات!$P$11 -> الخران | AD6: بإمارة | AG6: رأس الخيمة
A8: مساحة البناء بالقدم المربع | B8: المساحة بالفووت | I8: مساحة السور | L8: مقدم المالك | V8: مدة الدفع
A10: 5300 | I10: 150 | L10: 150000 | V10: 24
A13: سعر الفيلا | Q13: السور | AN13: 10.765
A14: المساحة | G14: سعر الفوت | K14: إجمالي سعر | Q14: مساحة السور | Z14: سعر المتر الطولي | AF14: إجمالي تكلفة السور
A15: =A10 -> 5300 | G15: 192 | K15: =G15*A15 -> 1017600 | Q15: =I10 -> 150 | Z15: 800 | AF15: =Z15*Q15 -> 120000
A19: إجمالي سعر الفيلا | Q19: إجمالي السور
A20: =K15 -> 1017600 | Q20: =AF15 -> 120000
A25: السعر النهائي للمشروع بدون ضريبة | Q25: =Q20+A20 -> 1137600
A27: الضريبة | Q27: =Q25*5% -> 56880
A29: السعر النهائي للمشروع (شامل الضريبة) | Q29: =Q25+Q27 -> 1194480
A31: 800000 | Q31: =Q29-A31 -> 394480
A34: البنك | Q34: المالك
A35: تمويل البنك | H35: مقدم البنك | Q35: إجمالي المالك | AB35: مقدم المالك
A36: =A31 -> 800000 | H36: -------- | Q36: =Q31 -> 394480 | AB36: =L10 -> 150000
A41: المبلغ المتبقي / المالك | Q41: الدفع (الشهري) | AB41: =V10 -> 24
A43: =Q36-AB36 -> 244480 | Q43: =A43/AB41 -> 10186.667
R254: .

Sheet حساب الكميات بنك 
B2: حساب كميات المشروع
B3: معلومات المشروع
B4: المالك | O4: =المدخلات!$P$3 -> احمد ابراهيم النعيمي | AC4: المنطقة | AQ4: =المدخلات!$P$11 -> الخران
B5: وصف المشروع | O5: =المدخلات!$P$4 -> فيلا دور أرضي و اول وسور | AC5: رقم القسيمة | AQ5: =المدخلات!$P$12 -> 403100010
B6: مساحة السور بالمتر المربع | O6: =المدخلات!$AR$5 -> 118 | AC6: مساحة البناء بالقدم المربع | AQ6: =المدخلات!$AY$5 -> 5549
B25: بيانات المقاول
B26: اسم الشركة: | O26: =المدخلات!$AR$3 -> 0 | AC26: المهندس المسؤول: | AQ26: =المدخلات!$AR$6 -> 0
B27: تاريخ المناقصة: | O27: =المدخلات!$AR$7 -> 46021 | AC27: رقم الهاتف: | AQ27: =المدخلات!$AR$11 -> 0
B28: رقم رخصة المقاول: | O28: =المدخلات!$AR$4 -> 0 | AC28: مدة تنفيذ المشروع: | AQ28: 24 شهر
B30: عرض السعر | AQ30: ختم الشركة العارضة
B31: تكلفة انشاء وانجاز الفيلا | AC31: =AO202+AO210 -> 704000
B32: تكلفة انشاء وإنجاز السور | AC32: =AO213 -> 96000
B33: تكلفة انشاء وإنجاز الفيلا مع السور | AC33: =AO220 -> 800000
B38: أولا : أعمال الهيكل
B39: (A) أعمال المياه الجوفية والتربة
B40: الرقم | E40: البند | AO40: الوحدة | AS40: الكمية | AW40: السعر | BA40: الإجمالي
B41: A1 | C41: B1 | D41: B1 | E41: أعمال تجفيف المياه الجوفية إن وجدت حسب فحص التربة | F41: عزل الأسقف نوعية ألتك يسعر الفرق فقط | G41: عزل الأسقف نوعية ألتك يسعر الفرق فقط | H41: عزل الأسقف نوعية ألتك يسعر الفرق فقط | I41: عزل الأسقف نوعية ألتك يسعر الفرق فقط | J41: عزل الأسقف نوعية ألتك يسعر الفرق فقط | K41: عزل الأسقف نوعية ألتك يسعر الفرق فقط | L41: عزل الأسقف نوعية ألتك يسعر الفرق فقط | M41: عزل الأسقف نوعية ألتك يسعر الفرق فقط | N41: عزل الأسقف نوعية ألتك يسعر الفرق فقط | O41: عزل الأسقف نوعية ألتك يسعر الفرق فقط | P41: عزل الأسقف نوعية ألتك يسعر الفرق فقط | Q41: عزل الأسقف نوعية ألتك يسعر الفرق فقط | R41: عزل الأسقف نوعية ألتك يسعر الفرق فقط | S41: عزل الأسقف نوعية ألتك يسعر الفرق فقط | T41: عزل الأسقف نوعية ألتك يسعر الفرق فقط | U41: عزل الأسقف نوعية ألتك يسعر الفرق فقط | V41: عزل الأسقف نوعية ألتك يسعر الفرق فقط | W41: عزل الأسقف نوعية ألتك يسعر الفرق فقط | X41: عزل الأسقف نوعية ألتك يسعر الفرق فقط | Y41: عزل الأسقف نوعية ألتك يسعر الفرق فقط | Z41: عزل الأسقف نوعية ألتك يسعر الفرق فقط | AA41: عزل الأسقف نوعية ألتك يسعر الفرق فقط | AB41: عزل الأسقف نوعية ألتك يسعر الفرق فقط | AC41: عزل الأسقف نوعية ألتك يسعر الفرق فقط | AD41: عزل الأسقف نوعية ألتك يسعر الفرق فقط | AE41: عزل الأسقف نوعية ألتك يسعر الفرق فقط | AF41: عزل الأسقف نوعية ألتك يسعر الفرق فقط | AG41: عزل الأسقف نوعية ألتك يسعر الفرق فقط | AH41: عزل الأسقف نوعية ألتك يسعر الفرق فقط | AI41: عزل الأسقف نوعية ألتك يسعر الفرق فقط | AJ41: عزل الأسقف نوعية ألتك يسعر الفرق فقط | AK41: عزل الأسقف نوعية ألتك يسعر الفرق فقط | AL41: عزل الأسقف نوعية ألتك يسعر الفرق فقط | AM41: عزل الأسقف نوعية ألتك يسعر الفرق فقط | AN41: عزل الأسقف نوعية ألتك يسعر الفرق فقط | AO41: L.S | AP41: M2 | AQ41: M2 | AR41: M2 | AS41: 0 | AW41: 0 | BA41: =AW41*AS41 -> 0
B42: A2 | C42: B2 | D42: B2 | E42: أعمال إحلال التربة إن وجدت حسب فحص التربة | F42: الأسمنت بلاستر للحوائط الداخلية. | G42: الأسمنت بلاستر للحوائط الداخلية. | H42: الأسمنت بلاستر للحوائط الداخلية. | I42: الأسمنت بلاستر للحوائط الداخلية. | J42: الأسمنت بلاستر للحوائط الداخلية. | K42: الأسمنت بلاستر للحوائط الداخلية. | L42: الأسمنت بلاستر للحوائط الداخلية. | M42: الأسمنت بلاستر للحوائط الداخلية. | N42: الأسمنت بلاستر للحوائط الداخلية. | O42: الأسمنت بلاستر للحوائط الداخلية. | P42: الأسمنت بلاستر للحوائط الداخلية. | Q42: الأسمنت بلاستر للحوائط الداخلية. | R42: الأسمنت بلاستر للحوائط الداخلية. | S42: الأسمنت بلاستر للحوائط الداخلية. | T42: الأسمنت بلاستر للحوائط الداخلية. | U42: الأسمنت بلاستر للحوائط الداخلية. | V42: الأسمنت بلاستر للحوائط الداخلية. | W42: الأسمنت بلاستر للحوائط الداخلية. | X42: الأسمنت بلاستر للحوائط الداخلية. | Y42: الأسمنت بلاستر للحوائط الداخلية. | Z42: الأسمنت بلاستر للحوائط الداخلية. | AA42: الأسمنت بلاستر للحوائط الداخلية. | AB42: الأسمنت بلاستر للحوائط الداخلية. | AC42: الأسمنت بلاستر للحوائط الداخلية. | AD42: الأسمنت بلاستر للحوائط الداخلية. | AE42: الأسمنت بلاستر للحوائط الداخلية. | AF42: الأسمنت بلاستر للحوائط الداخلية. | AG42: الأسمنت بلاستر للحوائط الداخلية. | AH42: الأسمنت بلاستر للحوائط الداخلية. | AI42: الأسمنت بلاستر للحوائط الداخلية. | AJ42: الأسمنت بلاستر للحوائط الداخلية. | AK42: الأسمنت بلاستر للحوائط الداخلية. | AL42: الأسمنت بلاستر للحوائط الداخلية. | AM42: الأسمنت بلاستر للحوائط الداخلية. | AN42: الأسمنت بلاستر للحوائط الداخلية. | AO42: L.S | AP42: M2 | AQ42: M2 | AR42: M2 | AS42: 0 | AW42: 0 | BA42: =AW42*AS42 -> 0
B43: (A) إجمالي سعر أعمال المياه الجوفية والتربة | AO43: =SUM(BA41:BD42) -> 0
B45: (B) أعمال تحضير وتجهيز الموقع
B46: الرقم | E46: البند | AO46: الوحدة | AS46: الكمية | AW46: السعر | BA46: الإجمالي
B47: B1 | C47: B1 | D47: B1 | E47: تجهيز الموقع السور المؤقت | F47: عزل الأسقف نوعية ألتك يسعر الفرق فقط | G47: عزل الأسقف نوعية ألتك يسعر الفرق فقط | H47: عزل الأسقف نوعية ألتك يسعر الفرق فقط | I47: عزل الأسقف نوعية ألتك يسعر الفرق فقط | J47: عزل الأسقف نوعية ألتك يسعر الفرق فقط | K47: عزل الأسقف نوعية ألتك يسعر الفرق فقط | L47: عزل الأسقف نوعية ألتك يسعر الفرق فقط | M47: عزل الأسقف نوعية ألتك يسعر الفرق فقط | N47: عزل الأسقف نوعية ألتك يسعر الفرق فقط | O47: عزل الأسقف نوعية ألتك يسعر الفرق فقط | P47: عزل الأسقف نوعية ألتك يسعر الفرق فقط | Q47: عزل الأسقف نوعية ألتك يسعر الفرق فقط | R47: عزل الأسقف نوعية ألتك يسعر الفرق فقط | S47: عزل الأسقف نوعية ألتك يسعر الفرق فقط | T47: عزل الأسقف نوعية ألتك يسعر الفرق فقط | U47: عزل الأسقف نوعية ألتك يسعر الفرق فقط | V47: عزل الأسقف نوعية ألتك يسعر الفرق فقط | W47: عزل الأسقف نوعية ألتك يسعر الفرق فقط | X47: عزل الأسقف نوعية ألتك يسعر الفرق فقط | Y47: عزل الأسقف نوعية ألتك يسعر الفرق فقط | Z47: عزل الأسقف نوعية ألتك يسعر الفرق فقط | AA47: عزل الأسقف نوعية ألتك يسعر الفرق فقط | AB47: عزل الأسقف نوعية ألتك يسعر الفرق فقط | AC47: عزل الأسقف نوعية ألتك يسعر الفرق فقط | AD47: عزل الأسقف نوعية ألتك يسعر الفرق فقط | AE47: عزل الأسقف نوعية ألتك يسعر الفرق فقط | AF47: عزل الأسقف نوعية ألتك يسعر الفرق فقط | AG47: عزل الأسقف نوعية ألتك يسعر الفرق فقط | AH47: عزل الأسقف نوعية ألتك يسعر الفرق فقط | AI47: عزل الأسقف نوعية ألتك يسعر الفرق فقط | AJ47: عزل الأسقف نوعية ألتك يسعر الفرق فقط | AK47: عزل الأسقف نوعية ألتك يسعر الفرق فقط | AL47: عزل الأسقف نوعية ألتك يسعر الفرق فقط | AM47: عزل الأسقف نوعية ألتك يسعر الفرق فقط | AN47: عزل الأسقف نوعية ألتك يسعر الفرق فقط | AO47: مقطوغ | AP47: M2 | AQ47: M2 | AR47: M2 | AS47: - | AW47: - | BA47: -
B48: B2 | C48: B1 | D48: B1 | E48: اللوحة الخارجية (بيانات المشروع) | F48: عزل الأسقف نوعية ألتك يسعر الفرق فقط | G48: عزل الأسقف نوعية ألتك يسعر الفرق فقط | H48: عزل الأسقف نوعية ألتك يسعر الفرق فقط | I48: عزل الأسقف نوعية ألتك يسعر الفرق فقط | J48: عزل الأسقف نوعية ألتك يسعر الفرق فقط | K48: عزل الأسقف نوعية ألتك يسعر الفرق فقط | L48: عزل الأسقف نوعية ألتك يسعر الفرق فقط | M48: عزل الأسقف نوعية ألتك يسعر الفرق فقط | N48: عزل الأسقف نوعية ألتك يسعر الفرق فقط | O48: عزل الأسقف نوعية ألتك يسعر الفرق فقط | P48: عزل الأسقف نوعية ألتك يسعر الفرق فقط | Q48: عزل الأسقف نوعية ألتك يسعر الفرق فقط | R48: عزل الأسقف نوعية ألتك يسعر الفرق فقط | S48: عزل الأسقف نوعية ألتك يسعر الفرق فقط | T48: عزل الأسقف نوعية ألتك يسعر الفرق فقط | U48: عزل الأسقف نوعية ألتك يسعر الفرق فقط | V48: عزل الأسقف نوعية ألتك يسعر الفرق فقط | W48: عزل الأسقف نوعية ألتك يسعر الفرق فقط | X48: عزل الأسقف نوعية ألتك يسعر الفرق فقط | Y48: عزل الأسقف نوعية ألتك يسعر الفرق فقط | Z48: عزل الأسقف نوعية ألتك يسعر الفرق فقط | AA48: عزل الأسقف نوعية ألتك يسعر الفرق فقط | AB48: عزل الأسقف نوعية ألتك يسعر الفرق فقط | AC48: عزل الأسقف نوعية ألتك يسعر الفرق فقط | AD48: عزل الأسقف نوعية ألتك يسعر الفرق فقط | AE48: عزل الأسقف نوعية ألتك يسعر الفرق فقط | AF48: عزل الأسقف نوعية ألتك يسعر الفرق فقط | AG48: عزل الأسقف نوعية ألتك يسعر الفرق فقط | AH48: عزل الأسقف نوعية ألتك يسعر الفرق فقط | AI48: عزل الأسقف نوعية ألتك يسعر الفرق فقط | AJ48: عزل الأسقف نوعية ألتك يسعر الفرق فقط | AK48: عزل الأسقف نوعية ألتك يسعر الفرق فقط | AL48: عزل الأسقف نوعية ألتك يسعر الفرق فقط | AM48: عزل الأسقف نوعية ألتك يسعر الفرق فقط | AN48: عزل الأسقف نوعية ألتك يسعر الفرق فقط | AO48: مقطوغ | AP48: M2 | AQ48: M2 | AR48: M2 | AS48: - | AW48: - | BA48: -
B49: B3 | C49: B1 | D49: B1 | E49: إزالة المباني القديمة (ان وجدت) | F49: عزل الأسقف نوعية ألتك يسعر الفرق فقط | G49: عزل الأسقف نوعية ألتك يسعر الفرق فقط | H49: عزل الأسقف نوعية ألتك يسعر الفرق فقط | I49: عزل الأسقف نوعية ألتك يسعر الفرق فقط | J49: عزل الأسقف نوعية ألتك يسعر الفرق فقط | K49: عزل الأسقف نوعية ألتك يسعر الفرق فقط | L49: عزل الأسقف نوعية ألتك يسعر الفرق فقط | M49: عزل الأسقف نوعية ألتك يسعر الفرق فقط | N49: عزل الأسقف نوعية ألتك يسعر الفرق فقط | O49: عزل الأسقف نوعية ألتك يسعر الفرق فقط | P49: عزل الأسقف نوعية ألتك يسعر الفرق فقط | Q49: عزل الأسقف نوعية ألتك يسعر الفرق فقط | R49: عزل الأسقف نوعية ألتك يسعر الفرق فقط | S49: عزل الأسقف نوعية ألتك يسعر الفرق فقط | T49: عزل الأسقف نوعية ألتك يسعر الفرق فقط | U49: عزل الأسقف نوعية ألتك يسعر الفرق فقط | V49: عزل الأسقف نوعية ألتك يسعر الفرق فقط | W49: عزل الأسقف نوعية ألتك يسعر الفرق فقط | X49: عزل الأسقف نوعية ألتك يسعر الفرق فقط | Y49: عزل الأسقف نوعية ألتك يسعر الفرق فقط | Z49: عزل الأسقف نوعية ألتك يسعر الفرق فقط | AA49: عزل الأسقف نوعية ألتك يسعر الفرق فقط | AB49: عزل الأسقف نوعية ألتك يسعر الفرق فقط | AC49: عزل الأسقف نوعية ألتك يسعر الفرق فقط | AD49: عزل الأسقف نوعية ألتك يسعر الفرق فقط | AE49: عزل الأسقف نوعية ألتك يسعر الفرق فقط | AF49: عزل الأسقف نوعية ألتك يسعر الفرق فقط | AG49: عزل الأسقف نوعية ألتك يسعر الفرق فقط | AH49: عزل الأسقف نوعية ألتك يسعر الفرق فقط | AI49: عزل الأسقف نوعية ألتك يسعر الفرق فقط | AJ49: عزل الأسقف نوعية ألتك يسعر الفرق فقط | AK49: عزل الأسقف نوعية ألتك يسعر الفرق فقط | AL49: عزل الأسقف نوعية ألتك يسعر الفرق فقط | AM49: عزل الأسقف نوعية ألتك يسعر الفرق فقط | AN49: عزل الأسقف نوعية ألتك يسعر الفرق فقط | AO49: مقطوغ | AP49: M2 | AQ49: M2 | AR49: M2 | AS49: - | AW49: - | BA49: -
B50: B4 | C50: B1 | D50: B1 | E50: الخدمات المؤقته (كهرباء , ماء , الخ) | F50: عزل الأسقف نوعية ألتك يسعر الفرق فقط | G50: عزل الأسقف نوعية ألتك يسعر الفرق فقط | H50: عزل الأسقف نوعية ألتك يسعر الفرق فقط | I50: عزل الأسقف نوعية ألتك يسعر الفرق فقط | J50: عزل الأسقف نوعية ألتك يسعر الفرق فقط | K50: عزل الأسقف نوعية ألتك يسعر الفرق فقط | L50: عزل الأسقف نوعية ألتك يسعر الفرق فقط | M50: عزل الأسقف نوعية ألتك يسعر الفرق فقط | N50: عزل الأسقف نوعية ألتك يسعر الفرق فقط | O50: عزل الأسقف نوعية ألتك يسعر الفرق فقط | P50: عزل الأسقف نوعية ألتك يسعر الفرق فقط | Q50: عزل الأسقف نوعية ألتك يسعر الفرق فقط | R50: عزل الأسقف نوعية ألتك يسعر الفرق فقط | S50: عزل الأسقف نوعية ألتك يسعر الفرق فقط | T50: عزل الأسقف نوعية ألتك يسعر الفرق فقط | U50: عزل الأسقف نوعية ألتك يسعر الفرق فقط | V50: عزل الأسقف نوعية ألتك يسعر الفرق فقط | W50: عزل الأسقف نوعية ألتك يسعر الفرق فقط | X50: عزل الأسقف نوعية ألتك يسعر الفرق فقط | Y50: عزل الأسقف نوعية ألتك يسعر الفرق فقط | Z50: عزل الأسقف نوعية ألتك يسعر الفرق فقط | AA50: عزل الأسقف نوعية ألتك يسعر الفرق فقط | AB50: عزل الأسقف نوعية ألتك يسعر الفرق فقط | AC50: عزل الأسقف نوعية ألتك يسعر الفرق فقط | AD50: عزل الأسقف نوعية ألتك يسعر الفرق فقط | AE50: عزل الأسقف نوعية ألتك يسعر الفرق فقط | AF50: عزل الأسقف نوعية ألتك يسعر الفرق فقط | AG50: عزل الأسقف نوعية ألتك يسعر الفرق فقط | AH50: عزل الأسقف نوعية ألتك يسعر الفرق فقط | AI50: عزل الأسقف نوعية ألتك يسعر الفرق فقط | AJ50: عزل الأسقف نوعية ألتك يسعر الفرق فقط | AK50: عزل الأسقف نوعية ألتك يسعر الفرق فقط | AL50: عزل الأسقف نوعية ألتك يسعر الفرق فقط | AM50: عزل الأسقف نوعية ألتك يسعر الفرق فقط | AN50: عزل الأسقف نوعية ألتك يسعر الفرق فقط | AO50: مقطوغ | AP50: M2 | AQ50: M2 | AR50: M2 | AS50: - | AW50: - | BA50: -
B51: B5 | C51: B1 | D51: B1 | E51: اعمال فحص التربة (حسب المواصفات) | F51: عزل الأسقف نوعية ألتك يسعر الفرق فقط | G51: عزل الأسقف نوعية ألتك يسعر الفرق فقط | H51: عزل الأسقف نوعية ألتك يسعر الفرق فقط | I51: عزل الأسقف نوعية ألتك يسعر الفرق فقط | J51: عزل الأسقف نوعية ألتك يسعر الفرق فقط | K51: عزل الأسقف نوعية ألتك يسعر الفرق فقط | L51: عزل الأسقف نوعية ألتك يسعر الفرق فقط | M51: عزل الأسقف نوعية ألتك يسعر الفرق فقط | N51: عزل الأسقف نوعية ألتك يسعر الفرق فقط | O51: عزل الأسقف نوعية ألتك يسعر الفرق فقط | P51: عزل الأسقف نوعية ألتك يسعر الفرق فقط | Q51: عزل الأسقف نوعية ألتك يسعر الفرق فقط | R51: عزل الأسقف نوعية ألتك يسعر الفرق فقط | S51: عزل الأسقف نوعية ألتك يسعر الفرق فقط | T51: عزل الأسقف نوعية ألتك يسعر الفرق فقط | U51: عزل الأسقف نوعية ألتك يسعر الفرق فقط | V51: عزل الأسقف نوعية ألتك يسعر الفرق فقط | W51: عزل الأسقف نوعية ألتك يسعر الفرق فقط | X51: عزل الأسقف نوعية ألتك يسعر الفرق فقط | Y51: عزل الأسقف نوعية ألتك يسعر الفرق فقط | Z51: عزل الأسقف نوعية ألتك يسعر الفرق فقط | AA51: عزل الأسقف نوعية ألتك يسعر الفرق فقط | AB51: عزل الأسقف نوعية ألتك يسعر الفرق فقط | AC51: عزل الأسقف نوعية ألتك يسعر الفرق فقط | AD51: عزل الأسقف نوعية ألتك يسعر الفرق فقط | AE51: عزل الأسقف نوعية ألتك يسعر الفرق فقط | AF51: عزل الأسقف نوعية ألتك يسعر الفرق فقط | AG51: عزل الأسقف نوعية ألتك يسعر الفرق فقط | AH51: عزل الأسقف نوعية ألتك يسعر الفرق فقط | AI51: عزل الأسقف نوعية ألتك يسعر الفرق فقط | AJ51: عزل الأسقف نوعية ألتك يسعر الفرق فقط | AK51: عزل الأسقف نوعية ألتك يسعر الفرق فقط | AL51: عزل الأسقف نوعية ألتك يسعر الفرق فقط | AM51: عزل الأسقف نوعية ألتك يسعر الفرق فقط | AN51: عزل الأسقف نوعية ألتك يسعر الفرق فقط | AO51: مقطوغ | AP51: M2 | AQ51: M2 | AR51: M2 | AS51: - | AW51: - | BA51: -
B52: B6 | C52: B1 | D52: B1 | E52: الاختبارات واعتماد المواد حسب المواصفات | F52: عزل الأسقف نوعية ألتك يسعر الفرق فقط | G52: عزل الأسقف نوعية ألتك يسعر الفرق فقط | H52: عزل الأسقف نوعية ألتك يسعر الفرق فقط | I52: عزل الأسقف نوعية ألتك يسعر الفرق فقط | J52: عزل الأسقف نوعية ألتك يسعر الفرق فقط | K52: عزل الأسقف نوعية ألتك يسعر الفرق فقط | L52: عزل الأسقف نوعية ألتك يسعر الفرق فقط | M52: عزل الأسقف نوعية ألتك يسعر الفرق فقط | N52: عزل الأسقف نوعية ألتك يسعر الفرق فقط | O52: عزل الأسقف نوعية ألتك يسعر الفرق فقط | P52: عزل الأسقف نوعية ألتك يسعر الفرق فقط | Q52: عزل الأسقف نوعية ألتك يسعر الفرق فقط | R52: عزل الأسقف نوعية ألتك يسعر الفرق فقط | S52: عزل الأسقف نوعية ألتك يسعر الفرق فقط | T52: عزل الأسقف نوعية ألتك يسعر الفرق فقط | U52: عزل الأسقف نوعية ألتك يسعر الفرق فقط | V52: عزل الأسقف نوعية ألتك يسعر الفرق فقط | W52: عزل الأسقف نوعية ألتك يسعر الفرق فقط | X52: عزل الأسقف نوعية ألتك يسعر الفرق فقط | Y52: عزل الأسقف نوعية ألتك يسعر الفرق فقط | Z52: عزل الأسقف نوعية ألتك يسعر الفرق فقط | AA52: عزل الأسقف نوعية ألتك يسعر الفرق فقط | AB52: عزل الأسقف نوعية ألتك يسعر الفرق فقط | AC52: عزل الأسقف نوعية ألتك يسعر الفرق فقط | AD52: عزل الأسقف نوعية ألتك يسعر الفرق فقط | AE52: عزل الأسقف نوعية ألتك يسعر الفرق فقط | AF52: عزل الأسقف نوعية ألتك يسعر الفرق فقط | AG52: عزل الأسقف نوعية ألتك يسعر الفرق فقط | AH52: عزل الأسقف نوعية ألتك يسعر الفرق فقط | AI52: عزل الأسقف نوعية ألتك يسعر الفرق فقط | AJ52: عزل الأسقف نوعية ألتك يسعر الفرق فقط | AK52: عزل الأسقف نوعية ألتك يسعر الفرق فقط | AL52: عزل الأسقف نوعية ألتك يسعر الفرق فقط | AM52: عزل الأسقف نوعية ألتك يسعر الفرق فقط | AN52: عزل الأسقف نوعية ألتك يسعر الفرق فقط | AO52: مقطوغ | AP52: M2 | AQ52: M2 | AR52: M2 | AS52: - | AW52: - | BA52: -
B53: B7 | C53: B1 | D53: B1 | E53: المخططات التنفيذية لاعمال الخدمات | F53: عزل الأسقف نوعية ألتك يسعر الفرق فقط | G53: عزل الأسقف نوعية ألتك يسعر الفرق فقط | H53: عزل الأسقف نوعية ألتك يسعر الفرق فقط | I53: عزل الأسقف نوعية ألتك يسعر الفرق فقط | J53: عزل الأسقف نوعية ألتك يسعر الفرق فقط | K53: عزل الأسقف نوعية ألتك يسعر الفرق فقط | L53: عزل الأسقف نوعية ألتك يسعر الفرق فقط | M53: عزل الأسقف نوعية ألتك يسعر الفرق فقط | N53: عزل الأسقف نوعية ألتك يسعر الفرق فقط | O53: عزل الأسقف نوعية ألتك يسعر الفرق فقط | P53: عزل الأسقف نوعية ألتك يسعر الفرق فقط | Q53: عزل الأسقف نوعية ألتك يسعر الفرق فقط | R53: عزل الأسقف نوعية ألتك يسعر الفرق فقط | S53: عزل الأسقف نوعية ألتك يسعر الفرق فقط | T53: عزل الأسقف نوعية ألتك يسعر الفرق فقط | U53: عزل الأسقف نوعية ألتك يسعر الفرق فقط | V53: عزل الأسقف نوعية ألتك يسعر الفرق فقط | W53: عزل الأسقف نوعية ألتك يسعر الفرق فقط | X53: عزل الأسقف نوعية ألتك يسعر الفرق فقط | Y53: عزل الأسقف نوعية ألتك يسعر الفرق فقط | Z53: عزل الأسقف نوعية ألتك يسعر الفرق فقط | AA53: عزل الأسقف نوعية ألتك يسعر الفرق فقط | AB53: عزل الأسقف نوعية ألتك يسعر الفرق فقط | AC53: عزل الأسقف نوعية ألتك يسعر الفرق فقط | AD53: عزل الأسقف نوعية ألتك يسعر الفرق فقط | AE53: عزل الأسقف نوعية ألتك يسعر الفرق فقط | AF53: عزل الأسقف نوعية ألتك يسعر الفرق فقط | AG53: عزل الأسقف نوعية ألتك يسعر الفرق فقط | AH53: عزل الأسقف نوعية ألتك يسعر الفرق فقط | AI53: عزل الأسقف نوعية ألتك يسعر الفرق فقط | AJ53: عزل الأسقف نوعية ألتك يسعر الفرق فقط | AK53: عزل الأسقف نوعية ألتك يسعر الفرق فقط | AL53: عزل الأسقف نوعية ألتك يسعر الفرق فقط | AM53: عزل الأسقف نوعية ألتك يسعر الفرق فقط | AN53: عزل الأسقف نوعية ألتك يسعر الفرق فقط | AO53: مقطوغ | AP53: M2 | AQ53: M2 | AR53: M2 | AS53: - | AW53: - | BA53: -
B54: B8 | C54: B1 | D54: B1 | E54: المخططات الواقعية بعد التنفيذ | F54: عزل الأسقف نوعية ألتك يسعر الفرق فقط | G54: عزل الأسقف نوعية ألتك يسعر الفرق فقط | H54: عزل الأسقف نوعية ألتك يسعر الفرق فقط | I54: عزل الأسقف نوعية ألتك يسعر الفرق فقط | J54: عزل الأسقف نوعية ألتك يسعر الفرق فقط | K54: عزل الأسقف نوعية ألتك يسعر الفرق فقط | L54: عزل الأسقف نوعية ألتك يسعر الفرق فقط | M54: عزل الأسقف نوعية ألتك يسعر الفرق فقط | N54: عزل الأسقف نوعية ألتك يسعر الفرق فقط | O54: عزل الأسقف نوعية ألتك يسعر الفرق فقط | P54: عزل الأسقف نوعية ألتك يسعر الفرق فقط | Q54: عزل الأسقف نوعية ألتك يسعر الفرق فقط | R54: عزل الأسقف نوعية ألتك يسعر الفرق فقط | S54: عزل الأسقف نوعية ألتك يسعر الفرق فقط | T54: عزل الأسقف نوعية ألتك يسعر الفرق فقط | U54: عزل الأسقف نوعية ألتك يسعر الفرق فقط | V54: عزل الأسقف نوعية ألتك يسعر الفرق فقط | W54: عزل الأسقف نوعية ألتك يسعر الفرق فقط | X54: عزل الأسقف نوعية ألتك يسعر الفرق فقط | Y54: عزل الأسقف نوعية ألتك يسعر الفرق فقط | Z54: عزل الأسقف نوعية ألتك يسعر الفرق فقط | AA54: عزل الأسقف نوعية ألتك يسعر الفرق فقط | AB54: عزل الأسقف نوعية ألتك يسعر الفرق فقط | AC54: عزل الأسقف نوعية ألتك يسعر الفرق فقط | AD54: عزل الأسقف نوعية ألتك يسعر الفرق فقط | AE54: عزل الأسقف نوعية ألتك يسعر الفرق فقط | AF54: عزل الأسقف نوعية ألتك يسعر الفرق فقط | AG54: عزل الأسقف نوعية ألتك يسعر الفرق فقط | AH54: عزل الأسقف نوعية ألتك يسعر الفرق فقط | AI54: عزل الأسقف نوعية ألتك يسعر الفرق فقط | AJ54: عزل الأسقف نوعية ألتك يسعر الفرق فقط | AK54: عزل الأسقف نوعية ألتك يسعر الفرق فقط | AL54: عزل الأسقف نوعية ألتك يسعر الفرق فقط | AM54: عزل الأسقف نوعية ألتك يسعر الفرق فقط | AN54: عزل الأسقف نوعية ألتك يسعر الفرق فقط | AO54: مقطوغ | AP54: M2 | AQ54: M2 | AR54: M2 | AS54: - | AW54: - | BA54: -
B55: B9 | C55: B1 | D55: B1 | E55: تنسيق و تنظيف الموقع بعد نهاية العمل | F55: عزل الأسقف نوعية ألتك يسعر الفرق فقط | G55: عزل الأسقف نوعية ألتك يسعر الفرق فقط | H55: عزل الأسقف نوعية ألتك يسعر الفرق فقط | I55: عزل الأسقف نوعية ألتك يسعر الفرق فقط | J55: عزل الأسقف نوعية ألتك يسعر الفرق فقط | K55: عزل الأسقف نوعية ألتك يسعر الفرق فقط | L55: عزل الأسقف نوعية ألتك يسعر الفرق فقط | M55: عزل الأسقف نوعية ألتك يسعر الفرق فقط | N55: عزل الأسقف نوعية ألتك يسعر الفرق فقط | O55: عزل الأسقف نوعية ألتك يسعر الفرق فقط | P55: عزل الأسقف نوعية ألتك يسعر الفرق فقط | Q55: عزل الأسقف نوعية ألتك يسعر الفرق فقط | R55: عزل الأسقف نوعية ألتك يسعر الفرق فقط | S55: عزل الأسقف نوعية ألتك يسعر الفرق فقط | T55: عزل الأسقف نوعية ألتك يسعر الفرق فقط | U55: عزل الأسقف نوعية ألتك يسعر الفرق فقط | V55: عزل الأسقف نوعية ألتك يسعر الفرق فقط | W55: عزل الأسقف نوعية ألتك يسعر الفرق فقط | X55: عزل الأسقف نوعية ألتك يسعر الفرق فقط | Y55: عزل الأسقف نوعية ألتك يسعر الفرق فقط | Z55: عزل الأسقف نوعية ألتك يسعر الفرق فقط | AA55: عزل الأسقف نوعية ألتك يسعر الفرق فقط | AB55: عزل الأسقف نوعية ألتك يسعر الفرق فقط | AC55: عزل الأسقف نوعية ألتك يسعر الفرق فقط | AD55: عزل الأسقف نوعية ألتك يسعر الفرق فقط | AE55: عزل الأسقف نوعية ألتك يسعر الفرق فقط | AF55: عزل الأسقف نوعية ألتك يسعر الفرق فقط | AG55: عزل الأسقف نوعية ألتك يسعر الفرق فقط | AH55: عزل الأسقف نوعية ألتك يسعر الفرق فقط | AI55: عزل الأسقف نوعية ألتك يسعر الفرق فقط | AJ55: عزل الأسقف نوعية ألتك يسعر الفرق فقط | AK55: عزل الأسقف نوعية ألتك يسعر الفرق فقط | AL55: عزل الأسقف نوعية ألتك يسعر الفرق فقط | AM55: عزل الأسقف نوعية ألتك يسعر الفرق فقط | AN55: عزل الأسقف نوعية ألتك يسعر الفرق فقط | AO55: مقطوغ | AP55: M2 | AQ55: M2 | AR55: M2 | AS55: - | AW55: - | BA55: -
B56: (B) إجمالي سعر أعمال تحضير وتجهيز الموقع | AO56: 40000
B58: (C) أعمال تحت منسوب الأرض
B59: الرقم | E59: البند | AO59: الوحدة | AS59: الكمية | AW59: السعر | BA59: الإجمالي
B60: C1 | C60: B1 | D60: B1 | E60: أعمال الحفر | AO60: M3 | AP60: M2 | AQ60: M2 | AR60: M2 | AS60: 100 | AW60: 15 | BA60: =AW60*AS60 -> 1500
B61: C2 | C61: B1 | D61: B1 | E61: أعمال خرسانة عادية للفيلا و الدرج الخارجي و الرامب | AO61: M3 | AP61: M2 | AQ61: M2 | AR61: M2 | AS61: 25 | AW61: 1000 | BA61: =AW61*AS61 -> 25000
B62: C3 | C62: B1 | D62: B1 | E62: أعمال خرسانة مسلحة للفيلا و الدرج الخارجي | AO62: M3 | AP62: M2 | AQ62: M2 | AR62: M2 | AS62: 15 | AW62: 1500 | BA62: =AW62*AS62 -> 22500
B63: C4 | C63: B1 | D63: B1 | E63: أعمال طابوق مصمت أسفل الجسور الأرضية | AO63: M2 | AS63: 60 | AW63: 75 | BA63: =AW63*AS63 -> 4500
B64: C5 | C64: B1 | D64: B1 | E64: أعمال الجسور الأرضية السفلية للفيلا | AO64: M3 | AS64: 20 | AW64: 1000 | BA64: =AW64*AS64 -> 20000
B65: C6 | C65: B1 | D65: B1 | E65: أعمال الدفان والدمك | AO65: M3 | AS65: 100 | AW65: 21 | BA65: =AW65*AS65 -> 2100
B66: C7 | C66: B1 | D66: B1 | E66: أعمال الخرسانة الأرضية | AO66: M3 | AS66: 37 | AW66: 700 | BA66: =AW66*AS66 -> 25900
B67: C8 | C67: B1 | D67: B1 | E67: أعمال معالجة النمل الأبيض (مرتين) | AO67: L.S | AS67: 250 | AW67: 10 | BA67: =AW67*AS67 -> 2500
B68: (C) إجمالي سعر أعمال تحت منسوب الأرض | AO68: =SUM(BA60:BD67) -> 104000
B70: (D) أعمال فوق منسوب الأرض
B71: الرقم | E71: البند | AO71: الوحدة | AS71: الكمية | AW71: السعر | BA71: الإجمالي
B72: D1 | E72: أعمال خرسانة مسلحة للأعمدة | AO72: M3 | AS72: 15 | AW72: 1200 | BA72: =AW72*AS72 -> 18000
B73: D2 | E73: أعمال خرسانة مسلحة للسقف الارضي | AO73: M3 | AS73: 100 | AW73: 1000 | BA73: =AW73*AS73 -> 100000
B74: D3 | E74: أعمال خرسانة مسلحة للجسور و الكمرات | AO74: M3 | AP74: M2 | AQ74: M2 | AR74: M2 | AS74: 25 | AW74: 1200 | BA74: =AW74*AS74 -> 30000
B75: D4 | E75: أعمال خرسانة السلالم الداخلية | AO75: M3 | AS75: 5 | AW75: 900 | BA75: =AW75*AS75 -> 4500
B76: D5 | E76: أعمال خرسانة السلالم الخارجية | AO76: M3 | AS76: 3 | AW76: 600 | BA76: =AW76*AS76 -> 1800
B77: D6 | E77: أعمال خرسانة الأعتاب والأقواس ولنتل و الديكورات و الأبواب و اعتاب تركيب الزجاج و الهاندريل | AO77: مقطوع | AS77: 1 | AW77: 5950 | BA77: =AW77*AS77 -> 5950
B78: D7 | E78: خرسانة مسلحة للباربيت حسب المخطط | AO78: M3 | AS78: 3 | AW78: 600 | BA78: =AW78*AS78 -> 1800
B79: D8 | E79: خرسانة لقواعد الخزانات و التكييف | AO79: مقطوع | AS79: 1 | AW79: 5950 | BA79: =AW79*AS79 -> 5950
B80: (D) إجمالي سعر أعمال فوق منسوب الأرض | AO80: =SUM(BA72:BD79) -> 168000
B82: (E) أعمال الطابوق
B83: الرقم | E83: البند | AO83: الوحدة | AS83: الكمية | AW83: السعر | BA83: الإجمالي
B84: E1 | C84: B1 | D84: B1 | E84: توريد وتركيب طابوق 20 سم معزول حسب المخططات | AO84: M2 | AP84: M2 | AQ84: M2 | AR84: M2 | AS84: 300 | AW84: 55 | BA84: =AW84*AS84 -> 16500
B85: E2 | C85: B1 | D85: B1 | E85: توريد وتركيب طابوق خالي 20 سم حسب المخططات | AO85: M2 | AP85: M2 | AQ85: M2 | AR85: M2 | AS85: 500 | AW85: 60 | BA85: =AW85*AS85 -> 30000
B86: E3 | C86: B1 | D86: B1 | E86: توريد وتركيب طابوق خالي 10 سم حسب المخططات | AO86: M2 | AP86: M2 | AQ86: M2 | AR86: M2 | AS86: 25 | AW86: 60 | BA86: =AW86*AS86 -> 1500
B87: (E) إجمالي سعر أعمال الطابوق | AO87: =SUM(BA84:BD86) -> 48000
B90: اجمالي أولا : أعمال الهيكل | AO90: =$AO$87+$AO$80+$AO$68+$AO$56+$AO$43 -> 360000
B92: ثانيا : أعمال التشطيبات والاكساء
B94: (F) أعمال الطبقات العازلة
B95: الرقم | E95: البند | AO95: الوحدة | AS95: الكمية | AW95: السعر | BA95: الإجمالي
B96: H1 | C96: B1 | D96: B1 | E96: الاساسات | AO96: مقطوع | AP96: M2 | AQ96: M2 | AR96: M2 | AS96: 1 | AW96: 7500 | BA96: =AW96*AS96 -> 7500
B97: H2 | C97: B1 | D97: B1 | E97: الحمامات و التواليتات | AO97: M2 | AP97: M2 | AQ97: M2 | AR97: M2 | AS97: 25 | AW97: 60 | BA97: =AW97*AS97 -> 1500
B98: H3 | C98: B1 | D98: B1 | E98: نعلات الحمامات و التواليتات و المطابخ | AO98: M.L | AP98: M2 | AQ98: M2 | AR98: M2 | AS98: 20 | AW98: 50 | BA98: =AW98*AS98 -> 1000
B99: H4 | C99: B1 | D99: B1 | E99: الاسطح | AO99: M2 | AP99: M2 | AQ99: M2 | AR99: M2 | AS99: 200 | AW99: 120 | BA99: =AW99*AS99 -> 24000
B100: H5 | C100: B1 | D100: B1 | E100: نعلات عند حواف الاسطح | AO100: M.L | AP100: M2 | AQ100: M2 | AR100: M2 | AS100: 200 | AW100: 30 | BA100: =AW100*AS100 -> 6000
B101: (F) أعمال الطبقات العازلة | AO101: =SUM(BA96:BD100) -> 40000
B103: (I) أعمال الأصباغ للفيلا
B109: (G) اعمال التشطيبات
B110: الرقم | E110: البند | AO110: الوحدة | AS110: الكمية | AW110: السعر | BA110: الإجمالي
B111: J1 | E111: جميع ارضيات الفيلا سيراميك | AO111: M2 | AS111: 250 | AW111: 70 | BA111: =AW111*AS111 -> 17500
B112: J2 | E112: ارضيات رخام لبسطات الدرج الداخلي | AO112: M2 | AS112: 13 | AW112: 150 | BA112: =AW112*AS112 -> 1950
B113: J3 | E113: درجات قائمة و نايمة رخام للدرج الداخلي | AO113: L.M | AS113: 500 | AW113: 60 | BA113: =AW113*AS113 -> 30000
B114: J4 | E114: البراطيش | AO114: L.M | AS114: 21.25 | AW114: 40 | BA114: =AW114*AS114 -> 850
B115: J5 | E115: نعلات جميع ارضيات الفيلا | AO115: L.M | AS115: 100 | AW115: 20 | BA115: =AW115*AS115 -> 2000
B116: J6 | E116: نعلات الادراج الداخلية للرخام | AO116: L.M | AS116: 20 | AW116: 60 | BA116: =AW116*AS116 -> 1200
B117: J7 | E117: نعلات الادراج الخارجية غرانيت | AO117: L.M | AS117: 10 | AW117: 50 | BA117: =AW117*AS117 -> 500
B118: J8 | E118: بلاستر داخلي للجدران | AO118: M2 | AS118: 500 | AW118: 35 | BA118: =AW118*AS118 -> 17500
B119: J9 | E119: صبغ الجدران الداخلية | AO119: M2 | AS119: 500 | AW119: 25 | BA119: =AW119*AS119 -> 12500
B120: J10 | E120: سيراميك للحمامات و المطابخ و المغاسل | AO120: M2 | AS120: 100 | AW120: 40 | BA120: =AW120*AS120 -> 4000
B121: J11 | E121: بلاستر الاسقف برايمر+ صبغ | AO121: M2 | AS121: 200 | AW121: 25 | BA121: =AW121*AS121 -> 5000
B122: J12 | E122: الاسقف المستعارة جبس بورد لتغطية دكتات التكييف | AO122: M2 | AS122: 25 | AW122: 40 | BA122: =AW122*AS122 -> 1000
B123: J13 | E123: واجهات الفيلا الخارجية [المحارة و البلاستر] مع صبغ | AO123: M2 | AS123: 300 | AW123: 60 | BA123: =AW123*AS123 -> 18000
B124: (G) اعمال التشطيبات الداخلية | AO124: =AVERAGE(BA120+BA116+BA115+BA114+BA113+BA112+BA111+BA117+BA118+BA119+BA121+BA122+BA123) -> 112000
B126: (H) الأعمال الصحية
B127: الرقم | E127: البند | AO127: الوحدة | AS127: الكمية | AW127: السعر | BA127: الإجمالي
B128: L1 | C128: B1 | D128: B1 | E128: الانابيب و قطع التوصيل الخارجية | AO128: مقطوع | AP128: M2 | AQ128: M2 | AR128: M2 | AS128: - | AW128: - | BA128: -
B129: L2 | C129: B1 | D129: B1 | E129: الانابيب و قطع التوصيل الداخلية | AO129: مقطوع | AP129: M2 | AQ129: M2 | AR129: M2 | AS129: - | AW129: - | BA129: -
B130: L3 | C130: B1 | D130: B1 | E130: الخلاطات و اكسسوارات الحمامات و التواليتات | AO130: مقطوع | AP130: M2 | AQ130: M2 | AR130: M2 | AS130: - | AW130: - | BA130: -
B131: L4 | C131: B1 | D131: B1 | E131: المضخات | AO131: مقطوع | AP131: M2 | AQ131: M2 | AR131: M2 | AS131: - | AW131: - | BA131: -
B132: L5 | C132: B1 | D132: B1 | E132: خزانات المياه العلوية | AO132: مقطوع | AP132: M2 | AQ132: M2 | AR132: M2 | AS132: - | AW132: - | BA132: -
B133: L6 | C133: B1 | D133: B1 | E133: رسوم توصيل الخدمه ( المياه ) | AO133: مقطوع | AP133: M2 | AQ133: M2 | AR133: M2 | AS133: - | AW133: - | BA133: -
B134: L7 | C134: B1 | D134: B1 | E134: الانابيب ( المواسير ) والقطع الخاصه - خارجى | AO134: مقطوع | AP134: M2 | AQ134: M2 | AR134: M2 | AS134: - | AW134: - | BA134: -
B135: L8 | C135: B1 | D135: B1 | E135: الانابيب ( المواسير ) والقطع الخاصه - داخلى | AO135: مقطوع | AP135: M2 | AQ135: M2 | AR135: M2 | AS135: - | AW135: - | BA135: -
B136: L9 | C136: B1 | D136: B1 | E136: جميع اطقم حمامات غرف النوم وغرفه الطعام | AO136: مقطوع | AP136: M2 | AQ136: M2 | AR136: M2 | AS136: - | AW136: - | BA136: -
B137: L10 | C137: B1 | D137: B1 | E137: الجلى تراب والمنهولات | AO137: مقطوع | AP137: M2 | AQ137: M2 | AR137: M2 | AS137: - | AW137: - | BA137: -
B138: L11 | C138: B1 | D138: B1 | E138: رسوم توصيل الخدمه ( الصرف ) | AO138: مقطوع | AP138: M2 | AQ138: M2 | AR138: M2 | AS138: - | AW138: - | BA138: -
B139: (H) الأعمال الصحية | AO139: 48000
...

Sheet basss
A1: عقد الاتفاق Agreement
A3: بإشرافنا نحن
A4: سافانا ديزاين للإستشارات الهندسية والتصميم الداخلي- رأس الخيمة
A6: مكتب 407 أبراج جلفار رأس الخيمة
A7: 525015080
A9: تم الاتفاق بين كل من
A10: الطرف الاول | B10: (السادة الملاك) | D10: =المدخلات!P3 -> احمد ابراهيم النعيمي
A11: الطرف الثاني | B11: ( المقاول ) | D11: =المدخلات!AR10 -> 0
A12: الطرف الثالث | B12: ( الاستشاري) | D12: سافانا ديزاين للاستشارات الهندسية
A14: المشروع
A15: وصف المشروع | D15: =#REF! -> #REF!
A16: المنطقة | D16: =المدخلات!AR3 -> 0
A17: رقم القسيمة | D17: =#REF! -> #REF!
A19: =#REF! -> #REF! | E19: =#REF! -> #REF!
A21: يقوم الطرف الثاني بتنفيذ وانشاء وانجاز وصيانة المشروع المذكور اعلاه لقاء مبلغ وقدره
A22: ........................اماراتي فقط بدون الضريبة
A23: و ذلك حسب المتفق عليه والمعتمد وفق للمناقصة التي جرت
A25: توقيع وختم المقاول | D25: توقيع وختم الملاك | G25: توقيع وختم الاستشاري
A29: بنود العقد
A30: كافة مستندات المشروع و جميع متعلقاته متكاملة فيما بينها و تشمل المشروع ككل أي بحال عدم ذكر اي بند بالمواصفات او المخططات وتم ذكره بجدول الكميات او المخططات المعتمدة أو اي مستند اخر غير ذلك , والعكس صحيح على المقاول الالتزام به و العمل على تضمينه بأعمال المشروع اينما ذكر .علي المقاول ارجاع العقد موقع علي كل صفحة والمواصافات و المخططات وتوقيعه عليها يعتبر انه اطلع علي جميع تفاصيل المشروع
A32: 1 | B32: إصدار التعليمات, الرسوم | I32: =A32 -> 1
A33: لا يحق للمالك اصدار اي تعليمات للمقاول تتعلق بتنفيذ المشروع الا عن طريق الاستشاري
A34: 2 | B34: مقاولي الباطن | G34: 2 | I34: =A34 -> 2
A35: يجوز للطرف الثاني اسناد جزء من الاعمال الى مقاولي الباطن المعتمدين والمسجلين لدى البلدية بموجب موافقة خطية من الاستشاري
A36: يكون المقاول مسؤول مسؤولية كاملة عن اعمال المقاول الباطن من حيث الجودة والتنفيذ واصول الصناعه والضمانات
A37: يتعهد الطرف الثاني بالتنسيق بين جميع المقاولين الباطن دون اي استثناء ودون اي احقية في المطالبة باي مبلغ اضافة نظير ذلك.
A38: في حال اسناد المالك بعض الاعمال لمقاولي الباطن يكون عن طريق المقاول الرئيسي.
A39: 3 | B39: فسخ التعاقد | G39: 3 | I39: =A39 -> 3
A40: يحق للمهندس الاستشاري فسخ العقد في الحالات
A41: اذا تاخر المقاول عن بدء الاعمال بعد تسليم الموقع
A42: اذا تاخر المقاول في اتمام العمل وتسليمه في المواعيد المحدده لكل مرحلة في الجدول الزمني المعتمد
A43: اذا اظهر المقاول بطئا في سير العمل لدرجة يرى الاستشاري منها عدم قدرة الطرف الثاني على اتمام العمل في موعده على ان يقوم الاستشاري بكتابة ذلك خطيا للمقاول.
A44: اذا اخل المقاول ببرنامج العمل المحدد بشكل يؤثر على مستوى التنفيذ او الاخلال بالمواصفات المتفق عليها
A45: اذا انسحب المقاول عن العمل او تركه او افلس
A46: اذا اسند الطرف الثاني العمل لمقاول باطن دون اخطار الاستشاري
A47: في حال تاخير الطرف الاول عن سداد اي من مستحقات الطرف الثاني في موعد اقصاه 15 يوم فمن حق الطرف الثاني التوقف عن العمل وذلك بعد اخطار الاستشاري خطيا وتحسب فتره التاخير على المالك لصالح المقاول كمدة اضافية للمشروع.
A48: يحق للطرف الثاني الغاء التعاقد في حالة تاخير المالك بسداد الدفعات المستحقة عليه او اخلال المالك بالتزاماته
A49: 4 | B49: الاثار المترتبة على فسخ العقد | G49: 4 | I49: =A49 -> 4
A50: حساب غرامة التاخير على الطرف الثاني طبقا للعقد حتى تاريخ ابلاغ المقاول بقرار السحب.
A51: يتم تنفيذ الاعمال المتبقية كلها او بعضها على حساب المقاول على ان تطرح الاعمال المتبقية في مناقصة جديدة او يعهد بتنفيذها الى احد المقاولين بطريق الممارسة مع تحميل المقاول النتائج المترتبة عن هذا الاجراء
A52: حجز اي دفعات متبقيىة للمقاول وحجز الضمانات البنكية ومحجوزات الصيانة لحين الانتهاء من المشروع (تمويل خاص فقط). في حال تاخر المالك بسداد المبالغ المستحقة عليه اكثر من شهر يحق للطرف الثاني فسخ العقد على ان يتم احتساب الاعمال المنجزه من طرف المقاول واحتساب قيمة باقي الاعمال الغير منجزه وخصمها من قيمة العقد الاساسية مع خصم المبالغ المسددة
A53: 5 | B53: حل النزاع | G53: =A53 -> 5 | I53: =A53 -> 5
A54: اي نزاع ينشا عن تطبيق احكام هذا العقد يكون الفصل فيه اختصاص محاكم راس الخيمة ولا علاقة لبلدية راس الخيمة في حل النزاع ويكون اختصاصها تنظيمي فقط .
A58: 6 | B58: محجوزات الصيانة | G58: =A58 -> 6 | I58: =A58 -> 6
A59: يستقطع 5% من قيمة الاعمال المنفذه بالدفعات الجارية او التي يتم صرفها بمعرفة المقرض كمحجوز صيانة وذلك ضمانا لحسن تنفيذ الاعمال وبعد الاستلام الابتدائي وحصر الاعمال نهائيا يتم صرف المستحقات الختامية للاعمال بعد استقطاع ما على المقاول من التزامات وما سبق صرفه كدفعات ويصرف له الباقي بعد حجز محجوز الصيانة من قيمة الاعمال المنفذة لمدة سنة من تاريخ الاستلام الابتدائي (تمويل خاص فقط) .
A60: 7 | B60: الإستلام الابتدائي للمشروع | G60: =A60 -> 7 | I60: =A60 -> 7
A61: يجب على المقاول اخطار الاستشاري باليوم الذي يتم فيه انهاء الاعمال على ان يكون هذا الاخطار قبل حلول هذا اليوم باسبوع على الاقل ليتم اخطار المالك والمقاول بموجب الاستلام الابتدائي يتم بحضور المقاول او مهندسه. وفي حاله عدم حضوره يقوم الاستشاري بعمله في غيابه فاذا ثبت ان الاعمال في حاله تسمح باستلامها يتم تحرير محضرا باستلام الاعمال استلاما مبدئيا في ذات اليوم, اما اذا ثبت عكس ذلك فللاستشاري الحق في عمل محضر اثبات حاله, وفي جميع الاحوال تكون المحاضر التي يحررها الاستشاري حجة على المقاول ولو لم يحضر او يوقع على المحضر ، لا يقوم الاستشاري باعادة المعاينة الا اذا اخطره المقاول بموعد انهاء الاعمال وقبل اسبوع من الحلول على الاقل وفي حال وجود ملاحظات على اعمال المشروع لا تمنع من الاستلاام الابتدائي يتم استلام المشروع ويعطى المقاول سبعه ايام لانهاء تلك الملاحظات وفي حال عدم انتهائه من هذه الملاحظات يعتبر محضر الاستلام الابتدائي لاغيا.
A62: 8 | B62: الاشراف الهندسي من قبل الاستشاري | G62: =A62 -> 8 | I62: =A62 -> 8
A63: يتم دفع رسوم شهرية مقابل الاشراف (700) درهم بدون الضريبة وذلك يتضمن الزيارات الاسبوعية والمتابعة بشكل عام-في حال تجاوزت مدة انتهاء المشروع على المدة المتفق عليها , يتم دفع رسوم الاشراف من قبل الطرف المتسبب في التأخير ( المالك او المقاول ) في حال كان الطرفين متسببين في التأخير ف يتم دفع الرسوم المتبقية لأشراف مناصفة بين المالك والمقاول.
A64: يحق للإستشاري إيقاف المقاول عن العمل في حالة عدم التقيد بتعليمات الإستشاري ويسري هذا على المقاولين الذين يحضرهم المقاول الرئيسي أو المالك
A65: الطرف الثالث غير مسؤول إذا لم ينجز المشروع بالكامل خلال مدة التنفيذ المتعاقد عليها بين الطرف الاول والمقاول.
